Workbook

Sheet 2026
A1: Setor (Cod) | B1: Setor | C1: Emenda | D1: Emenda (Modalidade) | E1: Emenda (Tipo) | F1: Autor (Cod) | G1: Autor | H1: Autor (Tipo) | I1: Autor (UF) | J1: Partido | K1: Órgão (Cod) | L1: Órgão | M1: UO (Cod) | N1: UO | O1: Funcional | P1: Função | Q1: Subfunção | R1: Programa | S1: Ação | T1: Subtítulo | U1: UF | V1: Localidade | W1: Esfera (Cod) | X1: GND (Cod) | Y1: Mod. Aplic. (Cod) | Z1: ID Uso (Cod) | AA1: Identificador Primário (Cod) | AB1: Fonte (Cod) | AC1: Valor Solicitado | AD1: Emenda (Justificativa) | AE1: OM | AF1: Objeto
A2: 13 | B2: DEFESA | C2: 12700001 | D2: INDIVIDUAL | E2: INCLUSÃO - APROPRIAÇÃO | F2: 1270 | G2: JOÃO CARLOS BACELAR | H2: DEPUTADO FEDERAL | I2: BA | J2: PL | K2: 52000 | L2: MINISTÉRIO DA DEFESA | M2: 52121 | N2: COMANDO DO EXÉRCITO | O2: 05.122.0032.2000.0029 | P2: DEFESA NACIONAL | Q2: ADMINISTRAÇÃO GERAL | R2: PROGRAMA DE GESTÃO E MANUTENÇÃO DO PODER EXECUTIVO | S2: ADMINISTRAÇÃO DA UNIDADE | T2: NO ESTADO DA BAHIA | U2: BA | V2: BAHIA | W2: F | X2: 4 | Y2: 90 | Z2: 0 | AA2: 6 | AB2: 1000 | AC2: 250000 | AD2: MELHORAR A ESTRUTURA DOS SETORES EDUCACIONAIS E ADMINISTRATIVOS, PROPORCIONANDO MAIOR EFETIVIDADE NA EXECUÇÃO DOS PROCESSOS | AE2: Colégio Militar de Salvador | AF2: Material permanente
A3: 13 | B3: DEFESA | C3: 12700002 | D3: INDIVIDUAL | E3: INCLUSÃO - APROPRIAÇÃO | F3: 1270 | G3: JOÃO CARLOS BACELAR | H3: DEPUTADO FEDERAL | I3: BA | J3: PL | K3: 52000 | L3: MINISTÉRIO DA DEFESA | M3: 52131 | N3: COMANDO DA MARINHA | O3: 05.152.6112.219D.0029 | P3: DEFESA NACIONAL | Q3: DEFESA NAVAL | R3: DEFESA NACIONAL | S3: ADEQUAÇÃO DE ATIVOS DE INFRAESTRUTURA DAS ORGANIZAÇÕES MILITARES | T3: NO ESTADO DA BAHIA | U3: BA | V3: BAHIA | W3: F | X3: 4 | Y3: 90 | Z3: 0 | AA3: 6 | AB3: 1000 | AC3: 150000 | AD3: ESTA PROPOSTA DE EMENDA VISA A AQUISIÇÃO DE EQUIPAMENTOS E EXECUÇÃO DE OBRAS NECESSÁRIAS A REVITALIZAÇÃO E ADEQUAÇÃO DA INFRAESTRUTURA DA DELEGACIA DA CAPITANIA DOS PORTOS EM PORTO SEGURO.
A4: 13 | B4: DEFESA | C4: 12770013 | D4: INDIVIDUAL | E4: INCLUSÃO - APROPRIAÇÃO | F4: 1277 | G4: WELLINGTON ROBERTO | H4: DEPUTADO FEDERAL | I4: PB | J4: PSD | K4: 52000 | L4: MINISTÉRIO DA DEFESA | M4: 52931 | N4: FUNDO NAVAL | O4: 05.125.6112.21BY.0001 | P4: DEFESA NACIONAL | Q4: NORMATIZAÇÃO E FISCALIZAÇÃO | R4: DEFESA NACIONAL | S4: FISCALIZAÇÃO DA NAVEGAÇÃO AQUAVIÁRIA | T4: NACIONAL | U4: NA | V4: NACIONAL | W4: F | X4: 4 | Y4: 90 | Z4: 0 | AA4: 6 | AB4: 1000 | AC4: 100000 | AD4: RECURSOS PARA DAR CONTINUIDADE NO PROCESSO DE AUMENTO DAS CAPACIDADES OPERACIONAIS DA CAPITANIA.
A5: 13 | B5: DEFESA | C5: 14510005 | D5: INDIVIDUAL | E5: INCLUSÃO - APROPRIAÇÃO | F5: 1451 | G5: VANDER LOUBET | H5: DEPUTADO FEDERAL | I5: MS | J5: PT | K5: 52000 | L5: MINISTÉRIO DA DEFESA | M5: 52121 | N5: COMANDO DO EXÉRCITO | O5: 05.153.6112.21A0.5218 | P5: DEFESA NACIONAL | Q5: DEFESA TERRESTRE | R5: DEFESA NACIONAL | S5: APRESTAMENTO DAS FORÇAS - MANUTENÇÃO DA PRONTIDÃO E DA CAPACIDADE OPERATIVA | T5: NO MUNICÍPIO DE CAMPO GRANDE - MS | U5: MS | V5: CAMPO GRANDE | W5: F | X5: 4 | Y5: 90 | Z5: 0 | AA5: 6 | AB5: 1000 | AC5: 500000 | AD5: APRESTAMENTO DAS FORÇAS - MANUTENÇÃO DA PRONTIDÃO E DA CAPACIDADE OPERATIVA - ADEQUAÇÃO DAS INSTALAÇÕES PARA O SERVIÇO MILITAR FEMININO DM CAMPO GRANDE - MS. | AE5: Cmdo 9ª RM | AF5: Mobiliário para o SMIF
A6: 13 | B6: DEFESA | C6: 14510009 | D6: INDIVIDUAL | E6: ACRÉSCIMO - APROPRIAÇÃO | F6: 1451 | G6: VANDER LOUBET | H6: DEPUTADO FEDERAL | I6: MS | J6: PT | K6: 52000 | L6: MINISTÉRIO DA DEFESA | M6: 52931 | N6: FUNDO NAVAL | O6: 05.152.6112.21A0.0001 | P6: DEFESA NACIONAL | Q6: DEFESA NAVAL | R6: DEFESA NACIONAL | S6: APRESTAMENTO DAS FORÇAS - MANUTENÇÃO DA PRONTIDÃO E DA CAPACIDADE OPERATIVA | T6: NACIONAL | U6: NA | V6: NACIONAL | W6: F | X6: 4 | Y6: 90 | Z6: 0 | AA6: 6 | AB6: 1000 | AC6: 300000 | AD6: AGÊNCIA FLUVIAL DE PORTO MURTINHO_x000D_ CNPJ: 00.394.502/0365-05_x000D_ _x000D_ MODERNIZAÇÃO DO PARQUE DE INFORMÁTICA E AQUISIÇÃO DE ITENS DE MOBILIÁRIO DA AGÊNCIA FLUVIAL DE PORTO MURTINHO, A FIM DE PROPORCIONAR EFICIÊNCIA E CELERIDADE AO ATENDIMENTO AOS CIDADÃOS SUL MATO-GROSSENSES QUE BUSCAM OS SERVIÇOS OFERECIDOS PELA AGÊNCIA.
A7: 13 | B7: DEFESA | C7: 15270016 | D7: INDIVIDUAL | E7: INCLUSÃO - APROPRIAÇÃO | F7: 1527 | G7: CARLOS SAMPAIO | H7: DEPUTADO FEDERAL | I7: SP | J7: PSD | K7: 52000 | L7: MINISTÉRIO DA DEFESA | M7: 52111 | N7: COMANDO DA AERONÁUTICA | O7: 05.122.0032.2000.0035 | P7: DEFESA NACIONAL | Q7: ADMINISTRAÇÃO GERAL | R7: PROGRAMA DE GESTÃO E MANUTENÇÃO DO PODER EXECUTIVO | S7: ADMINISTRAÇÃO DA UNIDADE | T7: NO ESTADO DE SÃO PAULO | U7: SP | V7: SÃO PAULO | W7: F | X7: 3 | Y7: 90 | Z7: 0 | AA7: 6 | AB7: 1000 | AC7: 300000 | AD7: A FORÇA AÉAREA BRASILEIRA (FAB), COMO INSTITUIÇÃO DE ESTADO, ATUA, INITERRUPTAMENTE, NA DEFESA DA PÁTRIA, NA MANUTENÇÃO DA SOBERANIA DO NOSSO ESPAÇO AÉREO, NA PROTEÇÃO DE NOSSAS FRONTEIRAS E NA INTEGRAÇÃO DO TERRITÓRIO NACIONAL._x000D_ ADEMAIS, SUBSIDIARIAMENTE, A FAB CUMPRE MISSÕES HUMANITÁRIAS E REPATRIAÇÃO DE NACIONAIS, DE TRANSPORTE DE ÓRGÃOS E TECIDOS, BEM COMO CONTRIBUI COM O DESENVOLVIMENTO TECNOLÓGICO, GERANDO EMPREGOS E RIQUEZAS AO PAÍS._x000D_ PELO EXPOSTO, PARA CONTRIBUIR COM A FAB NO CUMPRIMENTO DE SUA MISSÃO CONSTITUCIONAL EM BENEFÍCIO DA SOCIEDADE BRASILEIRA, É NECESSÁRIO O APOIO AOS PROJETOS E ATIVIDADES MENCIONADOS A SEGUIR COM O APORTE DE RECURSOS DE EMENDAS PARLAMENTARES NA LEI ORÇAMENTÁRIA ANUAL (LOA) DE 2026._x000D_ _x000D_ OM BENEFICIADA: ESQUADRÃO DE DEMONSTRAÇÃO AÉREA_x000D_ OBJETO RESUMIDO: READEQUAÇÃO DA INFRAESTRUTURA DO HANGAR DA ESQUADRILHA DA FUMAÇA.
A8: 13 | B8: DEFESA | C8: 15680002 | D8: INDIVIDUAL | E8: INCLUSÃO - APROPRIAÇÃO | F8: 1568 | G8: GILBERTO NASCIMENTO | H8: DEPUTADO FEDERAL | I8: SP | J8: PODE | K8: 52000 | L8: MINISTÉRIO DA DEFESA | M8: 52111 | N8: COMANDO DA AERONÁUTICA | O8: 05.301.0032.2E74.0035 | P8: DEFESA NACIONAL | Q8: ATENÇÃO BÁSICA | R8: PROGRAMA DE GESTÃO E MANUTENÇÃO DO PODER EXECUTIVO | S8: ESTRUTURAÇÃO E MODERNIZAÇÃO DE UNIDADES DE SAÚDE DAS FORÇAS ARMADAS | T8: NO ESTADO DE SÃO PAULO | U8: SP | V8: SÃO PAULO | W8: S | X8: 4 | Y8: 90 | Z8: 0 | AA8: 6 | AB8: 1000 | AC8: 450000 | AD8: CNPJ PARA LANÇAMENTO NO SIOP: 00.394.429/0001-00 - COMANDO DA AERONÁUTICA_x000D_ OM BENEFICIADA: HOSPITAL DE FORÇA AÉREA DE SÃO PAULO_x000D_ OBJETO RESUMIDO: AQUISIÇÃO DE CENTRAL DE INCLUSÃO HISTOLÓGICA E IMPRESSORA DE CASSETES HISTOLÓGICOS._x000D_ JUSTIFICATIVA:_x000D_ A FORÇA AÉREA BRASILEIRA (FAB), COMO INSTITUIÇÃO DE ESTADO, ATUA, ININTERRUPTAMENTE, NA DEFESA DA PÁTRIA, NA MANUTENÇÃO DA SOBERANIA DO NOSSO ESPAÇO AÉREO, NA PROTEÇÃO DE NOSSAS FRONTEIRAS E NA INTEGRAÇÃO DO TERRITÓRIO NACIONAL._x000D_ ADEMAIS, SUBSIDIARIAMENTE, A FAB CUMPRE MISSÕES HUMANITÁRIAS E DE REPATRIAÇÃO DE NACIONAIS, DE TRANSPORTE DE ÓRGÃOS E TECIDOS, BEM COMO CONTRIBUI COM O DESENVOLVIMENTO TECNOLÓGICO, GERANDO EMPREGOS E RIQUEZAS AO PAÍS._x000D_ PELO EXPOSTO, PARA CONTRIBUIR COM A FAB NO CUMPRIMENTO DE SUA MISSÃO CONSTITUCIONAL EM BENEFÍCIO DA SOCIEDADE BRASILEIRA, É NECESSÁRIO O APOIO AOS PROJETOS E ATIVIDADES SUPRAMENCIONADOS COM O APORTE DE RECURSOS DE EMENDAS PARLAMENTARES NA LEI ORÇAMENTÁRIA ANUAL (LOA) DE 2026.
A9: 13 | B9: DEFESA | C9: 15680003 | D9: INDIVIDUAL | E9: INCLUSÃO - APROPRIAÇÃO | F9: 1568 | G9: GILBERTO NASCIMENTO | H9: DEPUTADO FEDERAL | I9: SP | J9: PODE | K9: 52000 | L9: MINISTÉRIO DA DEFESA | M9: 52121 | N9: COMANDO DO EXÉRCITO | O9: 05.301.0032.2E74.3928 | P9: DEFESA NACIONAL | Q9: ATENÇÃO BÁSICA | R9: PROGRAMA DE GESTÃO E MANUTENÇÃO DO PODER EXECUTIVO | S9: ESTRUTURAÇÃO E MODERNIZAÇÃO DE UNIDADES DE SAÚDE DAS FORÇAS ARMADAS | T9: NO MUNICÍPIO DE SÃO PAULO - SP | U9: SP | V9: SÃO PAULO | W9: S | X9: 4 | Y9: 90 | Z9: 0 | AA9: 6 | AB9: 1000 | AC9: 500000 | AD9: BENEFICIÁRIO PARA LANÇAMENTO NO SIOP - CNPJ: 00.394.452/0001-03_x000D_ REALIZAR A BIÓPSIA DE PRÓSTATA POR VIA TRANSPERINEAL, UTILIZANDO ULTRASSONOGRAFIA COM SOFTWARE DE FUSÃO DE IMAGENS EM TEMPO REAL, O QUE PERMITE EXAMES MAIS RÁPIDOS E PRECISOS, ALÉM DE GERAR ECONOMIA COM A REDUÇÃO DE ENCAMINHAMENTOS._x000D_ A AQUISIÇÃO DO EQUIPAMENTO CELL SAVER MINIMIZARÁ A NECESSIDADE DE SANGUE DE DOADORES, REDUZINDO O RISCO DE COMPLICAÇÕES ASSOCIADAS ÀS TRANSFUSÕES ALOGÊNICAS. O USO DO PRÓPRIO SANGUE DO PACIENTE REDUZ O RISCO DE INCOMPATIBILIDADE SANGUÍNEA E DE TRANSMISSÃO DE DOENÇAS INFECCIOSAS._x000D_ _x000D_ HOSPITAL MILITAR DE ÁREA DE SÃO PAULO (HMASP), NO MUNICÍPIO DE SÃO PAULO - SP. | AE9: HMASP | AF9: Aparelho de ultrassom e Cell Saver
A10: 13 | B10: DEFESA | C10: 15680014 | D10: INDIVIDUAL | E10: ACRÉSCIMO - APROPRIAÇÃO | F10: 1568 | G10: GILBERTO NASCIMENTO | H10: DEPUTADO FEDERAL | I10: SP | J10: PODE | K10: 52000 | L10: MINISTÉRIO DA DEFESA | M10: 52931 | N10: FUNDO NAVAL | O10: 05.122.0032.2000.0001 | P10: DEFESA NACIONAL | Q10: ADMINISTRAÇÃO GERAL | R10: PROGRAMA DE GESTÃO E MANUTENÇÃO DO PODER EXECUTIVO | S10: ADMINISTRAÇÃO DA UNIDADE | T10: NACIONAL | U10: NA | V10: NACIONAL | W10: F | X10: 3 | Y10: 90 | Z10: 0 | AA10: 6 | AB10: 1000 | AC10: 300000 | AD10: COMANDO DO 8º DISTRITO NAVAL - COM8ºDN_x000D_ CNPJ: 00.394.502/0455-98_x000D_ _x000D_ "O COMANDO DO 8º DISTRITO NAVAL, NO ÂMBITO DE SUAS ATRIBUIÇÕES COMO REPRESENTANTE DA AUTORIDADE MARÍTIMA, COORDENA OS SERVIÇOS DE BUSCA, SALVAMENTO, FISCALIZAÇÃO E INSPEÇÃO NAVAL NOS ESTADOS DE SÃO PAULO E PARANÁ._x000D_ POR MEIO DE SEUS DOIS GRUPAMENTOS OPERATIVOS: O GRUPAMENTO DE PATRULHA NAVAL DO SUL-SUDESTE (COM SEUS 03 NAVIOS) E O 4º BATALHÃO DE OPERAÇÕES LITORÂNEAS DE FUZILEIROS NAVAIS, EM SANTOS-SP, (COM SEU EFETIVO DE 01 COMPANHIA) COMANDA OPERAÇÕES NAVAIS, CONJUNTAS E INTERAGÊNCIAS EM TODO O LITORAL PAULISTA, PARANAENSE, INTERIORES E FRONTEIRA OESTE._x000D_ NESSE SENTIDO, VISANDO MELHORAR E APRIMORAR A SUA CAPACIDADE OPERACIONAL PARA O CUMPRIMENTO DE SUA MISSÃO, O COMANDO DO 8º DISTRITO NAVAL NECESSITA DE VIATURAS PRONTAS E ADEQUADAS, E CAPAZES DE TRANSPORTAR SEUS MILITARES NA AMPLA ÁREA DE JURISDIÇÃO DOS DOIS ESTADOS DA FEDERAÇÃO E ESTAR APTO A PRESTAR OS DEVERES CONSTITUCIONAIS E SEUS SERVIÇOS À SOCIEDADE CIVIL._x000D_ A MANUTENÇÃO DESSES MEIOS SÃO DE VITAL IMPORTÂNCIA PARA QUE POSSAMOS ESTAR PRONTOS PARA O ATENDIMENTO DAS DEMANDAS DA SOCIEDADE, COM VISTAS A DESLOCAR PESSOAL E MEIOS, VIA RODOVIÁRIA, QUANDO NECESSÁRIO, PRESERVAR À SEGURANÇA DA NAVEGAÇÃO, SALVAGUARDA DA VIDA HUMANA NO MAR E PREVENIR A POLUIÇÃO HÍDRICA._x000D_ EM FACE DAS ATUAIS RESTRIÇÕES ORÇAMENTÁRIAS, COMPREENDEMOS QUE NOSSAS NECESSIDADES ESTÃO ACIMA DAS POSSIBILIDADES DE INVESTIMENTO E, POR ESSE MOTIVO, SUBMETEMOS À APRECIAÇÃO DE VOSSA EXCELÊNCIA, COMO PARTÍCIPE DA GESTÃO PÚBLICA EM FAVOR DO NOSSO ESTADO, A PRESENTE PROPOSTA DE EMENDA PARLAMENTAR, TENDO COMO BENEFICIÁRIO O COM8ºDN."
A11: 13 | B11: DEFESA | C11: 15810007 | D11: INDIVIDUAL | E11: INCLUSÃO - APROPRIAÇÃO | F11: 1581 | G11: JEFFERSON CAMPOS | H11: DEPUTADO FEDERAL | I11: SP | J11: PL | K11: 52000 | L11: MINISTÉRIO DA DEFESA | M11: 52121 | N11: COMANDO DO EXÉRCITO | O11: 05.153.6112.21A0. | P11: DEFESA NACIONAL | Q11: DEFESA TERRESTRE | R11: DEFESA NACIONAL | S11: APRESTAMENTO DAS FORÇAS - MANUTENÇÃO DA PRONTIDÃO E DA CAPACIDADE OPERATIVA | T11: COLEGIO MILITAR DE SÃO PAULO (CMSP) MUNICIPIO DE SÃO PAULO, INSTRUMENTOS MUSICAIS E EQUIPAMENTTOS DE APOIO PARA BANDA DE MUSICA - NACIONAL | U11: NA | V11: NACIONAL | W11: F | X11: 3 | Y11: 90 | Z11: 0 | AA11: 6 | AB11: 1000 | AC11: 200000 | AD11: BENEFICIARIO PARA LANÇAMENTO NO SIOP CNPJ. 00.394.452/0001-03, ADIQUIRIR NOVOS INSTRUMENTOS E EQUIPAMENTOS, MELHORANDO AS CONDIÇÕES PARA OS ENSAIOS E APRESENTAÇÃO DA BANDA DE MUSICA DA UNIDADE, QUE APOIA DIVERSOS EVENTOS CULTURAIS NO MUNICIPIO DE SÃO PAULO - SP. | AE11: CPOR/SP | AF11: Instrumentos musicais
A12: 13 | B12: DEFESA | C12: 15810007 | D12: INDIVIDUAL | E12: INCLUSÃO - APROPRIAÇÃO | F12: 1581 | G12: JEFFERSON CAMPOS | H12: DEPUTADO FEDERAL | I12: SP | J12: PL | K12: 52000 | L12: MINISTÉRIO DA DEFESA | M12: 52121 | N12: COMANDO DO EXÉRCITO | O12: 05.153.6112.21A0. | P12: DEFESA NACIONAL | Q12: DEFESA TERRESTRE | R12: DEFESA NACIONAL | S12: APRESTAMENTO DAS FORÇAS - MANUTENÇÃO DA PRONTIDÃO E DA CAPACIDADE OPERATIVA | T12: COLEGIO MILITAR DE SÃO PAULO (CMSP) MUNICIPIO DE SÃO PAULO, INSTRUMENTOS MUSICAIS E EQUIPAMENTTOS DE APOIO PARA BANDA DE MUSICA - NACIONAL | U12: NA | V12: NACIONAL | W12: F | X12: 4 | Y12: 90 | Z12: 0 | AA12: 6 | AB12: 1000 | AC12: 200000 | AD12: BENEFICIARIO PARA LANÇAMENTO NO SIOP CNPJ. 00.394.452/0001-03, ADIQUIRIR NOVOS INSTRUMENTOS E EQUIPAMENTOS, MELHORANDO AS CONDIÇÕES PARA OS ENSAIOS E APRESENTAÇÃO DA BANDA DE MUSICA DA UNIDADE, QUE APOIA DIVERSOS EVENTOS CULTURAIS NO MUNICIPIO DE SÃO PAULO - SP. | AE12: CPOR/SP | AF12: Instrumentos musicais
A13: 13 | B13: DEFESA | C13: 18670002 | D13: INDIVIDUAL | E13: INCLUSÃO - APROPRIAÇÃO | F13: 1867 | G13: LUIZ CARLOS HAULY | H13: DEPUTADO FEDERAL | I13: PR | J13: PODE | K13: 52000 | L13: MINISTÉRIO DA DEFESA | M13: 52111 | N13: COMANDO DA AERONÁUTICA | O13: 05.301.0032.2E74.0001 | P13: DEFESA NACIONAL | Q13: ATENÇÃO BÁSICA | R13: PROGRAMA DE GESTÃO E MANUTENÇÃO DO PODER EXECUTIVO | S13: ESTRUTURAÇÃO E MODERNIZAÇÃO DE UNIDADES DE SAÚDE DAS FORÇAS ARMADAS | T13: NACIONAL | U13: NA | V13: NACIONAL | W13: S | X13: 4 | Y13: 90 | Z13: 0 | AA13: 6 | AB13: 1000 | AC13: 250000 | AD13: CNPJ PARA LANÇAMENTO NO SIOP: 00.394.429/0001-00 - COMANDO DA AERONÁUTICA_x000D_ OM BENEFICIADA: GRUPO DE SAÚDE DE CURITIBA_x000D_ OBJETO RESUMIDO: AQUISIÇÃO DE APARELHO DE VIDEOENDOSCÓPIO._x000D_ JUSTIFICATIVA:_x000D_ A FORÇA AÉREA BRASILEIRA (FAB), COMO INSTITUIÇÃO DE ESTADO, ATUA, ININTERRUPTAMENTE, NA DEFESA DA PÁTRIA, NA MANUTENÇÃO DA SOBERANIA DO NOSSO ESPAÇO AÉREO, NA PROTEÇÃO DE NOSSAS FRONTEIRAS E NA INTEGRAÇÃO DO TERRITÓRIO NACIONAL._x000D_ ADEMAIS, SUBSIDIARIAMENTE, A FAB CUMPRE MISSÕES HUMANITÁRIAS E DE REPATRIAÇÃO DE NACIONAIS, DE TRANSPORTE DE ÓRGÃOS E TECIDOS, BEM COMO CONTRIBUI COM O DESENVOLVIMENTO TECNOLÓGICO, GERANDO EMPREGOS E RIQUEZAS AO PAÍS._x000D_ PELO EXPOSTO, PARA CONTRIBUIR COM A FAB NO CUMPRIMENTO DE SUA MISSÃO CONSTITUCIONAL EM BENEFÍCIO DA SOCIEDADE BRASILEIRA, É NECESSÁRIO O APOIO AOS PROJETOS E ATIVIDADES SUPRAMENCIONADOS COM O APORTE DE RECURSOS DE EMENDAS PARLAMENTARES NA LEI ORÇAMENTÁRIA ANUAL (LOA) DE 2026.
A14: 13 | B14: DEFESA | C14: 19600024 | D14: INDIVIDUAL | E14: INCLUSÃO - APROPRIAÇÃO | F14: 1960 | G14: RUBENS OTONI | H14: DEPUTADO FEDERAL | I14: GO | J14: PT | K14: 52000 | L14: MINISTÉRIO DA DEFESA | M14: 52111 | N14: COMANDO DA AERONÁUTICA | O14: 05.122.0032.2000.0052 | P14: DEFESA NACIONAL | Q14: ADMINISTRAÇÃO GERAL | R14: PROGRAMA DE GESTÃO E MANUTENÇÃO DO PODER EXECUTIVO | S14: ADMINISTRAÇÃO DA UNIDADE | T14: NO ESTADO DE GOIÁS | U14: GO | V14: GOIÁS | W14: F | X14: 3 | Y14: 90 | Z14: 0 | AA14: 6 | AB14: 1000 | AC14: 200000 | AD14: A FORÇA AÉREA BRASILEIRA (FAB), COMO INSTITUIÇÃO DE ESTADO, ATUA, ININTERRUPTAMENTE, NA DEFESA DA PÁTRIA, NA MANUTENÇÃO DA SOBERANIA DO NOSSO ESPAÇO AÉREO, NA PROTEÇÃO DE NOSSAS FRONTEIRAS E NA INTEGRAÇÃO DO TERRITÓRIO NACIONAL._x000D_ ADEMAIS, SUBSIDIARIAMENTE, A FAB CUMPRE MISSÕES HUMANITÁRIAS E DE REPATRIAÇÃO DE NACIONAIS, DE TRANSPORTE DE ÓRGÃOS E TECIDOS, BEM COMO CONTRIBUI COM O DESENVOLVIMENTO TECNOLÓGICO, GERANDO EMPREGOS E RIQUEZAS AO PAÍS._x000D_ PELO EXPOSTO, PARA CONTRIBUIR COM A FAB NO CUMPRIMENTO DE SUA MISSÃO CONSTITUCIONAL EM BENEFÍCIO DA SOCIEDADE BRASILEIRA, É NECESSÁRIO O APOIO AOS PROJETOS E ATIVIDADES SUPRAMENCIONADOS COM O APORTE DE RECURSOS DE EMENDAS PARLAMENTARES NA LEI ORÇAMENTÁRIA ANUAL (LOA) DE 2026."
A15: 13 | B15: DEFESA | C15: 20290015 | D15: INDIVIDUAL | E15: ACRÉSCIMO - APROPRIAÇÃO | F15: 2029 | G15: MAGNO MALTA | H15: SENADOR | I15: ES | J15: PL | K15: 52000 | L15: MINISTÉRIO DA DEFESA | M15: 52131 | N15: COMANDO DA MARINHA | O15: 05.152.6112.219D.0001 | P15: DEFESA NACIONAL | Q15: DEFESA NAVAL | R15: DEFESA NACIONAL | S15: ADEQUAÇÃO DE ATIVOS DE INFRAESTRUTURA DAS ORGANIZAÇÕES MILITARES | T15: NACIONAL | U15: NA | V15: NACIONAL | W15: F | X15: 3 | Y15: 90 | Z15: 0 | AA15: 6 | AB15: 1000 | AC15: 400000 | AD15: ESCOLA DE APRENDIZES-MARINHEIROS DO ESPÍRITO SANTO (EAMES)_x000D_ CNPJ: 00.394.502/0188-68_x000D_ _x000D_ ESTA PROPOSTA POR OBJETIVO A CONSTRUÇÃO DA GARAGEM DE BARCOS DA ESCOLA DE APRENDIZES-MARINHEIROS DO ESPÍRITO SANTO (EAMES). A ESTRUTURA DESEJADA VISA ATENDER A NECESSIDADE DA GUARDA/CONSERVAÇÃO DAS EMBARCAÇÕES MIÚDAS, MATERIAIS E EQUIPAMENTOS QUE SÃO IMPRESCINDÍVEIS NO APOIO ÀS ATIVIDADES NÁUTICAS DE VELA E REMO, MODALIDADES ESTAS, INTEGRANTES DA FORMAÇÃO DOS MARINHEIROS DA MARINHA DO BRASIL. OUTROSSIM, AS ATIVIDADES NÁUTICAS DE VELA SÃO OFERECIDAS À 400 CRIANÇAS ATENDIDAS PELO PROGRAMA FORÇAS NO ESPORTE (PROFESP), ORIUNDAS DE 12 ESCOLAS DA REDE PÚBLICA DE ENSINO DO MUNICÍPIO DE VILA VELHA-ES, VISANDO À INCLUSÃO SOCIAL POR MEIO DA PRÁTICA ESPORTIVA ORIENTADA. OUTRA POSSIBILIDADE DE EMPREGO DO ESPAÇO SERIA EM PROVEITO DAS ATIVIDADES PRATICADAS PELOS ESCOTEIROS DO MAR, PARCEIROS DA MARINHA DO BRASIL QUE, POR MEIO DE SUA VERTENTE ESPECÍFICA DO ESCOTISMO, TÊM O OBJETIVO DE DESENVOLVER NOS JOVENS O GOSTO PELO MAR E HABILIDADES MARINHEIRAS, CONTRIBUINDO NO FOMENTO DA MENTALIDADE MARÍTIMA DA SOCIEDADE CAPIXABA.
A16: 13 | B16: DEFESA | C16: 20830009 | D16: INDIVIDUAL | E16: INCLUSÃO - APROPRIAÇÃO | F16: 2083 | G16: ANDRÉ FIGUEIREDO | H16: DEPUTADO FEDERAL | I16: CE | J16: PDT | K16: 52000 | L16: MINISTÉRIO DA DEFESA | M16: 52931 | N16: FUNDO NAVAL | O16: 05.125.6112.21BY.0023 | P16: DEFESA NACIONAL | Q16: NORMATIZAÇÃO E FISCALIZAÇÃO | R16: DEFESA NACIONAL | S16: FISCALIZAÇÃO DA NAVEGAÇÃO AQUAVIÁRIA | T16: NO ESTADO DO CEARÁ | U16: CE | V16: CEARÁ | W16: F | X16: 4 | Y16: 90 | Z16: 0 | AA16: 6 | AB16: 1000 | AC16: 100000 | AD16: AUXILIAR A CAPITANIA DOS PORTOS NO CEARA A DESENVOLVER SUAS ATIVIDADES DE PROTEÇÃO E FISCALIZAÇÃO
A17: 13 | B17: DEFESA | C17: 22100001 | D17: INDIVIDUAL | E17: ACRÉSCIMO - APROPRIAÇÃO | F17: 2210 | G17: ESPERIDIÃO AMIN | H17: SENADOR | I17: SC | J17: PP | K17: 52000 | L17: MINISTÉRIO DA DEFESA | M17: 52131 | N17: COMANDO DA MARINHA | O17: 05.152.6112.219D.0001 | P17: DEFESA NACIONAL | Q17: DEFESA NAVAL | R17: DEFESA NACIONAL | S17: ADEQUAÇÃO DE ATIVOS DE INFRAESTRUTURA DAS ORGANIZAÇÕES MILITARES | T17: NACIONAL | U17: NA | V17: NACIONAL | W17: F | X17: 3 | Y17: 90 | Z17: 0 | AA17: 6 | AB17: 1000 | AC17: 900000 | AD17: CAPITANIA DOS PORTOS DE SANTA CATARINA - CPSC_x000D_ CNPJ: 00.394.502/0048-08_x000D_ _x000D_ A PRESENTE PROPOSTA TEM COMO OBJETIVOS:_x000D_ A) DAR CONTINUIDADE À RECUPERAÇÃO DO FORTE SANTA BÁRBARA, DA CASA DE APOIO E DO AUDITÓRIO AMAZÔNIA AZUL, ALÉM DE ADAPTAR O MUSEU DE ARQUEOLOGIA SUBAQUÁTICA. O FORTE SANTA BÁRBARA ABRIGA O CCMSC, SENDO ESTE UM IMPORTANTE ATRATIVO CULTURAL, TURÍSTICO E EDUCACIONAL, QUE BUSCA DISSEMINAR A MENTALIDADE MARÍTIMA E OFERECENDO UMA OPÇÃO CULTURAL E DE LAZER PARA A POPULAÇÃO CATARINENSE. DESDE SUA ABERTURA EM 2016, O CENTRO RECEBEU MAIS DE 28.000 VISITANTES E DESEMPENHA UM PAPEL SIGNIFICATIVO NA DIVULGAÇÃO DA HISTÓRIA, DA MENTALIDADE MARÍTIMA E DAS TRADIÇÕES MARINHEIRAS. NO ENTANTO, AS EDIFICAÇÕES DO CENTRO ESTÃO BASTANTE DEGRADADAS E HÁ UMA FALTA DE ACESSIBILIDADE ADEQUADA PARA PESSOAS COM NECESSIDADES ESPECIAIS. A REVITALIZAÇÃO PERMITIRÁ A PRESERVAÇÃO DO PATRIMÔNIO HISTÓRICO E CULTURAL, GARANTIRÁ A INTEGRIDADE E A SEGURANÇA DOS VISITANTES, ESTIMULARÁ O TURISMO E FOMENTARÁ A ECONOMIA LOCAL._x000D_ B) RECUPERAR E REVITALIZAR AS INSTALAÇÕES DO CASARÃO DA ILHA DO ARVOREDO E SUAS ADJACÊNCIAS, ALÉM DA MANUTENÇÃO DOS SINAIS NÁUTICOS. CONSIDERANDO A IMPORTÂNCIA DOS AUXÍLIOS À NAVEGAÇÃO PARA O DESENVOLVIMENTO DAS ATIVIDADES MARÍTIMAS, É NECESSÁRIO GARANTIR O PLENO FUNCIONAMENTO DOS DIVERSOS FARÓIS E FAROLETES AO LONGO DA COSTA CATARINENSE, QUE CONFEREM SEGURANÇA À NAVEGAÇÃO PARA A COMUNIDADE MARÍTIMA. O INVESTIMENTO VISA ASSEGURAR A CONTINUIDADE E A EFICÁCIA DESSES DISPOSITIVOS DE SEGURANÇA._x000D_ C) RECUPERAÇÃO DAS INSTALAÇÕES DO FAROL DA ILHA DA PAZ, ALIADA À IMPLANTAÇÃO DE UM SISTEMA FOTOVOLTAICO, VISANDO AMPLIAR A AUTONOMIA ENERGÉTICA LOCAL, REDUZIR CUSTOS OPERACIONAIS E ASSEGURAR A CONTINUIDADE DAS ATIVIDADES DESEMPENHADAS.
A18: 13 | B18: DEFESA | C18: 22100001 | D18: INDIVIDUAL | E18: ACRÉSCIMO - APROPRIAÇÃO | F18: 2210 | G18: ESPERIDIÃO AMIN | H18: SENADOR | I18: SC | J18: PP | K18: 52000 | L18: MINISTÉRIO DA DEFESA | M18: 52131 | N18: COMANDO DA MARINHA | O18: 05.152.6112.219D.0001 | P18: DEFESA NACIONAL | Q18: DEFESA NAVAL | R18: DEFESA NACIONAL | S18: ADEQUAÇÃO DE ATIVOS DE INFRAESTRUTURA DAS ORGANIZAÇÕES MILITARES | T18: NACIONAL | U18: NA | V18: NACIONAL | W18: F | X18: 4 | Y18: 90 | Z18: 0 | AA18: 6 | AB18: 1000 | AC18: 600000 | AD18: CAPITANIA DOS PORTOS DE SANTA CATARINA - CPSC_x000D_ CNPJ: 00.394.502/0048-08_x000D_ _x000D_ A PRESENTE PROPOSTA TEM COMO OBJETIVOS:_x000D_ A) DAR CONTINUIDADE À RECUPERAÇÃO DO FORTE SANTA BÁRBARA, DA CASA DE APOIO E DO AUDITÓRIO AMAZÔNIA AZUL, ALÉM DE ADAPTAR O MUSEU DE ARQUEOLOGIA SUBAQUÁTICA. O FORTE SANTA BÁRBARA ABRIGA O CCMSC, SENDO ESTE UM IMPORTANTE ATRATIVO CULTURAL, TURÍSTICO E EDUCACIONAL, QUE BUSCA DISSEMINAR A MENTALIDADE MARÍTIMA E OFERECENDO UMA OPÇÃO CULTURAL E DE LAZER PARA A POPULAÇÃO CATARINENSE. DESDE SUA ABERTURA EM 2016, O CENTRO RECEBEU MAIS DE 28.000 VISITANTES E DESEMPENHA UM PAPEL SIGNIFICATIVO NA DIVULGAÇÃO DA HISTÓRIA, DA MENTALIDADE MARÍTIMA E DAS TRADIÇÕES MARINHEIRAS. NO ENTANTO, AS EDIFICAÇÕES DO CENTRO ESTÃO BASTANTE DEGRADADAS E HÁ UMA FALTA DE ACESSIBILIDADE ADEQUADA PARA PESSOAS COM NECESSIDADES ESPECIAIS. A REVITALIZAÇÃO PERMITIRÁ A PRESERVAÇÃO DO PATRIMÔNIO HISTÓRICO E CULTURAL, GARANTIRÁ A INTEGRIDADE E A SEGURANÇA DOS VISITANTES, ESTIMULARÁ O TURISMO E FOMENTARÁ A ECONOMIA LOCAL._x000D_ B) RECUPERAR E REVITALIZAR AS INSTALAÇÕES DO CASARÃO DA ILHA DO ARVOREDO E SUAS ADJACÊNCIAS, ALÉM DA MANUTENÇÃO DOS SINAIS NÁUTICOS. CONSIDERANDO A IMPORTÂNCIA DOS AUXÍLIOS À NAVEGAÇÃO PARA O DESENVOLVIMENTO DAS ATIVIDADES MARÍTIMAS, É NECESSÁRIO GARANTIR O PLENO FUNCIONAMENTO DOS DIVERSOS FARÓIS E FAROLETES AO LONGO DA COSTA CATARINENSE, QUE CONFEREM SEGURANÇA À NAVEGAÇÃO PARA A COMUNIDADE MARÍTIMA. O INVESTIMENTO VISA ASSEGURAR A CONTINUIDADE E A EFICÁCIA DESSES DISPOSITIVOS DE SEGURANÇA._x000D_ C) RECUPERAÇÃO DAS INSTALAÇÕES DO FAROL DA ILHA DA PAZ, ALIADA À IMPLANTAÇÃO DE UM SISTEMA FOTOVOLTAICO, VISANDO AMPLIAR A AUTONOMIA ENERGÉTICA LOCAL, REDUZIR CUSTOS OPERACIONAIS E ASSEGURAR A CONTINUIDADE DAS ATIVIDADES DESEMPENHADAS.
A19: 13 | B19: DEFESA | C19: 22100002 | D19: INDIVIDUAL | E19: ACRÉSCIMO - APROPRIAÇÃO | F19: 2210 | G19: ESPERIDIÃO AMIN | H19: SENADOR | I19: SC | J19: PP | K19: 52000 | L19: MINISTÉRIO DA DEFESA | M19: 52121 | N19: COMANDO DO EXÉRCITO | O19: 05.122.0032.2000.0001 | P19: DEFESA NACIONAL | Q19: ADMINISTRAÇÃO GERAL | R19: PROGRAMA DE GESTÃO E MANUTENÇÃO DO PODER EXECUTIVO | S19: ADMINISTRAÇÃO DA UNIDADE | T19: NACIONAL | U19: NA | V19: NACIONAL | W19: F | X19: 4 | Y19: 90 | Z19: 0 | AA19: 6 | AB19: 1000 | AC19: 850000 | AD19: BENEFICIÁRIO PARA LANÇAMENTO NO SIOP - CNPJ: 00.394.452/0001-03_x000D_ REDUZIR DESPESAS DE CUSTEIO COM ENERGIA ELÉTRICA, AUMENTAR A SEGURANÇA ENERGÉTICA DA UNIDADE E CONTRIBUIR PARA A PRESERVAÇÃO DO MEIO AMBIENTE E DESENVOLVIMENTO SUSTENTÁVEL._x000D_ _x000D_ 63º BATALHÃO DE INFANTARIA (63º BI), NO MUNICÍPIO DE FLORIANÓPOLIS - SC | AE19: 63º BI | AF19: Usina fotovoltaica
A20: 13 | B20: DEFESA | C20: 22100020 | D20: INDIVIDUAL | E20: INCLUSÃO - APROPRIAÇÃO | F20: 2210 | G20: ESPERIDIÃO AMIN | H20: SENADOR | I20: SC | J20: PP | K20: 52000 | L20: MINISTÉRIO DA DEFESA | M20: 52111 | N20: COMANDO DA AERONÁUTICA | O20: 05.301.0032.2E74.0042 | P20: DEFESA NACIONAL | Q20: ATENÇÃO BÁSICA | R20: PROGRAMA DE GESTÃO E MANUTENÇÃO DO PODER EXECUTIVO | S20: ESTRUTURAÇÃO E MODERNIZAÇÃO DE UNIDADES DE SAÚDE DAS FORÇAS ARMADAS | T20: NO ESTADO DE SANTA CATARINA | U20: SC | V20: SANTA CATARINA | W20: S | X20: 4 | Y20: 90 | Z20: 0 | AA20: 6 | AB20: 1000 | AC20: 500000 | AD20: CNPJ PARA LANÇAMENTO NO SIOP: 00.394.429/0001-00 - COMANDO DA AERONÁUTICA_x000D_ OM BENEFICIADA: GRUPO DE SAÚDE DE FLORIANÓPOLIS_x000D_ OBJETO RESUMIDO: AQUISIÇÃO DE EQUIPAMENTOS MÉDICOS E ODONTOLÓGICOS._x000D_ JUSTIFICATIVA:_x000D_ A FORÇA AÉREA BRASILEIRA (FAB), COMO INSTITUIÇÃO DE ESTADO, ATUA, ININTERRUPTAMENTE, NA DEFESA DA PÁTRIA, NA MANUTENÇÃO DA SOBERANIA DO NOSSO ESPAÇO AÉREO, NA PROTEÇÃO DE NOSSAS FRONTEIRAS E NA INTEGRAÇÃO DO TERRITÓRIO NACIONAL._x000D_ ADEMAIS, SUBSIDIARIAMENTE, A FAB CUMPRE MISSÕES HUMANITÁRIAS E DE REPATRIAÇÃO DE NACIONAIS, DE TRANSPORTE DE ÓRGÃOS E TECIDOS, BEM COMO CONTRIBUI COM O DESENVOLVIMENTO TECNOLÓGICO, GERANDO EMPREGOS E RIQUEZAS AO PAÍS._x000D_ PELO EXPOSTO, PARA CONTRIBUIR COM A FAB NO CUMPRIMENTO DE SUA MISSÃO CONSTITUCIONAL EM BENEFÍCIO DA SOCIEDADE BRASILEIRA, É NECESSÁRIO O APOIO AOS PROJETOS E ATIVIDADES SUPRAMENCIONADOS COM O APORTE DE RECURSOS DE EMENDAS PARLAMENTARES NA LEI ORÇAMENTÁRIA ANUAL (LOA) DE 2026.
A21: 13 | B21: DEFESA | C21: 22630007 | D21: INDIVIDUAL | E21: ACRÉSCIMO - APROPRIAÇÃO | F21: 2263 | G21: JADER BARBALHO | H21: SENADOR | I21: PA | J21: MDB | K21: 52000 | L21: MINISTÉRIO DA DEFESA | M21: 52121 | N21: COMANDO DO EXÉRCITO | O21: 05.153.6112.21A0.0001 | P21: DEFESA NACIONAL | Q21: DEFESA TERRESTRE | R21: DEFESA NACIONAL | S21: APRESTAMENTO DAS FORÇAS - MANUTENÇÃO DA PRONTIDÃO E DA CAPACIDADE OPERATIVA | T21: NACIONAL | U21: NA | V21: NACIONAL | W21: F | X21: 4 | Y21: 90 | Z21: 0 | AA21: 6 | AB21: 1000 | AC21: 200000 | AD21: BENEFICIÁRIO PARA LANÇAMENTO NO SIOP - CNPJ: 00.394.452/0001-03_x000D_ INSTRUMENTOS MUSICAIS PARA A BANDA DE MÚSICA DOS ALUNOS DO COLÉGIO MILITAR DE BELÉM (CMBEL), NO MUNICÍPIO DE BELÉM - PA. ADQUIRIR NOVOS INSTRUMENTOS, MELHORANDO AS CONDIÇÕES PARA OS ENSAIOS E APRESENTAÇÕES DA BANDA DE MÚSICA DOS ALUNOS, QUE APOIA DIVERSOS EVENTOS CULTURAIS NO MUNICÍPIO. | AE21: 2º BIS | AF21: Ambulância tipo “B” – Suporte básico
A22: 13 | B22: DEFESA | C22: 22630008 | D22: INDIVIDUAL | E22: ACRÉSCIMO - APROPRIAÇÃO | F22: 2263 | G22: JADER BARBALHO | H22: SENADOR | I22: PA | J22: MDB | K22: 52000 | L22: MINISTÉRIO DA DEFESA | M22: 52931 | N22: FUNDO NAVAL | O22: 05.152.6112.21A0.0001 | P22: DEFESA NACIONAL | Q22: DEFESA NAVAL | R22: DEFESA NACIONAL | S22: APRESTAMENTO DAS FORÇAS - MANUTENÇÃO DA PRONTIDÃO E DA CAPACIDADE OPERATIVA | T22: NACIONAL | U22: NA | V22: NACIONAL | W22: F | X22: 3 | Y22: 90 | Z22: 0 | AA22: 6 | AB22: 1000 | AC22: 500000 | AD22: GRUPAMENTO DE PATRULHA NAVAL DO NORTE_x000D_ CNPJ: 00.394.502/0152-57_x000D_ _x000D_ CUSTEIO DA MANUTENÇÃO E A PREPARAÇÃO DOS NAVIOS E EMBARCAÇÕES SUBORDINADAS, QUE REALIZAM AÇÕES CÍVICO-SOCIAIS (ACISO) E ASSISTÊNCIAS HOSPITALARES (ASSHOP), E QUE APOIAM, QUANDO NECESSÁRIO, NOS ATENDIMENTOS REALIZADOS PELO NÁVIO-AUXILIAR “PARÁ” E PELO NAVIO DE ASSISTÊNCIA HOSPITALAR “SARGENTO LIMA”, PROPICIANDO O ACESSO ÀS ÁREAS REMOTAS, QUANDO DO SEU EMPREGO EM OPERAÇÕES DE APOIO AO ESTADO DO PARÁ.
A23: 13 | B23: DEFESA | C23: 22630009 | D23: INDIVIDUAL | E23: INCLUSÃO - APROPRIAÇÃO | F23: 2263 | G23: JADER BARBALHO | H23: SENADOR | I23: PA | J23: MDB | K23: 52000 | L23: MINISTÉRIO DA DEFESA | M23: 52911 | N23: FUNDO AERONÁUTICO | O23: 05.368.6112.21GP.0015 | P23: DEFESA NACIONAL | Q23: EDUCAÇÃO BÁSICA | R23: DEFESA NACIONAL | S23: FUNCIONAMENTO DOS ESTABELECIMENTOS DE EDUCAÇÃO BÁSICA MILITARES DO MINISTÉRIO DA DEFESA | T23: NO ESTADO DO PARÁ | U23: PA | V23: PARÁ | W23: F | X23: 4 | Y23: 90 | Z23: 0 | AA23: 6 | AB23: 1000 | AC23: 500000 | AD23: CNPJ PARA LANÇAMENTO NO SIOP: 00.394.429/0001-00 - COMANDO DA AERONÁUTICA_x000D_ OM BENEFICIADA: COLÉGIO TENENTE RÊGO BARROS_x000D_ OBJETO RESUMIDO: AQUISIÇÃO DE MOBILIÁRIO E READEQUAÇÃO DAS SALAS DOS PROFESSORES._x000D_ JUSTIFICATIVA:_x000D_ A FORÇA AÉREA BRASILEIRA (FAB), COMO INSTITUIÇÃO DE ESTADO, ATUA, ININTERRUPTAMENTE, NA DEFESA DA PÁTRIA, NA MANUTENÇÃO DA SOBERANIA DO NOSSO ESPAÇO AÉREO, NA PROTEÇÃO DE NOSSAS FRONTEIRAS E NA INTEGRAÇÃO DO TERRITÓRIO NACIONAL._x000D_ ADEMAIS, SUBSIDIARIAMENTE, A FAB CUMPRE MISSÕES HUMANITÁRIAS E DE REPATRIAÇÃO DE NACIONAIS, DE TRANSPORTE DE ÓRGÃOS E TECIDOS, BEM COMO CONTRIBUI COM O DESENVOLVIMENTO TECNOLÓGICO, GERANDO EMPREGOS E RIQUEZAS AO PAÍS._x000D_ PELO EXPOSTO, PARA CONTRIBUIR COM A FAB NO CUMPRIMENTO DE SUA MISSÃO CONSTITUCIONAL EM BENEFÍCIO DA SOCIEDADE BRASILEIRA, É NECESSÁRIO O APOIO AOS PROJETOS E ATIVIDADES SUPRAMENCIONADOS COM O APORTE DE RECURSOS DE EMENDAS PARLAMENTARES NA LEI ORÇAMENTÁRIA ANUAL (LOA) DE 2026.
A24: 13 | B24: DEFESA | C24: 23760004 | D24: INDIVIDUAL | E24: ACRÉSCIMO - APROPRIAÇÃO | F24: 2376 | G24: JAYME CAMPOS | H24: SENADOR | I24: MT | J24: UNIÃO | K24: 52000 | L24: MINISTÉRIO DA DEFESA | M24: 52121 | N24: COMANDO DO EXÉRCITO | O24: 05.153.6112.21A0.0001 | P24: DEFESA NACIONAL | Q24: DEFESA TERRESTRE | R24: DEFESA NACIONAL | S24: APRESTAMENTO DAS FORÇAS - MANUTENÇÃO DA PRONTIDÃO E DA CAPACIDADE OPERATIVA | T24: NACIONAL | U24: NA | V24: NACIONAL | W24: F | X24: 4 | Y24: 90 | Z24: 0 | AA24: 6 | AB24: 1000 | AC24: 1000000 | AD24: A PRESENTE EMENDA TEM POR OBJETIVO DOTAR O BATALHÃO COM EQUIPAMENTOS NECESSÁRIOS PARA AS AÇÕES DE PRONTO ATENDIMENTO A CALAMIDADE PÚBLICA, COMBATE E PREVENÇÃO A INCÊNDIOS FLORESTAIS NO ESTADO DE MATO GROSSO. _x000D_ NA UNIDADE DO BATALHÃO DE CUIABÁ. CNPJ: 00.394.452/0001-03. | AE24: 9º BEC | AF24: Equipar OM de Engenharia para pronto atendimento a calamidades públicas
A25: 13 | B25: DEFESA | C25: 23760005 | D25: INDIVIDUAL | E25: ACRÉSCIMO - APROPRIAÇÃO | F25: 2376 | G25: JAYME CAMPOS | H25: SENADOR | I25: MT | J25: UNIÃO | K25: 52000 | L25: MINISTÉRIO DA DEFESA | M25: 52931 | N25: FUNDO NAVAL | O25: 05.152.6112.21A0.0001 | P25: DEFESA NACIONAL | Q25: DEFESA NAVAL | R25: DEFESA NACIONAL | S25: APRESTAMENTO DAS FORÇAS - MANUTENÇÃO DA PRONTIDÃO E DA CAPACIDADE OPERATIVA | T25: NACIONAL | U25: NA | V25: NACIONAL | W25: F | X25: 4 | Y25: 90 | Z25: 0 | AA25: 6 | AB25: 1000 | AC25: 500000 | AD25: A PRESENTE EMENDA TEM POR OBJETIVO REALIZAR INVESTIMENTOS NAS INSTALAÇÕES DA CAPITANIA FLUVIAL DE MATO GROSSO._x000D_ CAPITANIA FLUVIAL DE MATO GROSSO_x000D_ CNPJ: 00.394.502/0371-45
A26: 13 | B26: DEFESA | C26: 23920005 | D26: INDIVIDUAL | E26: INCLUSÃO - APROPRIAÇÃO | F26: 2392 | G26: FERNANDO COELHO FILHO | H26: DEPUTADO FEDERAL | I26: PE | J26: UNIÃO | K26: 52000 | L26: MINISTÉRIO DA DEFESA | M26: 52121 | N26: COMANDO DO EXÉRCITO | O26: 05.301.0032.2E74.1689 | P26: DEFESA NACIONAL | Q26: ATENÇÃO BÁSICA | R26: PROGRAMA DE GESTÃO E MANUTENÇÃO DO PODER EXECUTIVO | S26: ESTRUTURAÇÃO E MODERNIZAÇÃO DE UNIDADES DE SAÚDE DAS FORÇAS ARMADAS | T26: NO MUNICÍPIO DE PETROLINA - PE | U26: PE | V26: PETROLINA | W26: S | X26: 4 | Y26: 90 | Z26: 0 | AA26: 6 | AB26: 1000 | AC26: 450000 | AD26: A PRESENTE EMENDA TEM COMO OBJETIVO FORTALECER A ESTRUTURA DE SAÚDE DO 72º BATALHÃO DE INFANTARIA DE CAATINGA (72º BI CAAT), LOCALIZADO NO MUNICÍPIO DE PETROLINA/PE, MEDIANTE A AQUISIÇÃO DE AMBULÂNCIA DESTINADA AO ATENDIMENTO DE MILITARES, ALUNOS DA UNIDADE E SEUS DEPENDENTES. O EQUIPAMENTO É ESSENCIAL PARA GARANTIR SUPORTE ADEQUADO EM SITUAÇÕES DE URGÊNCIA E NO TRANSPORTE SEGURO DE PACIENTES EM ESTADO GRAVE. | AE26: 72º BI Caat | AF26: Ambulância tipo “B” – Suporte básico
A27: 13 | B27: DEFESA | C27: 23920007 | D27: INDIVIDUAL | E27: INCLUSÃO - APROPRIAÇÃO | F27: 2392 | G27: FERNANDO COELHO FILHO | H27: DEPUTADO FEDERAL | I27: PE | J27: UNIÃO | K27: 52000 | L27: MINISTÉRIO DA DEFESA | M27: 52931 | N27: FUNDO NAVAL | O27: 05.122.0032.2000.0026 | P27: DEFESA NACIONAL | Q27: ADMINISTRAÇÃO GERAL | R27: PROGRAMA DE GESTÃO E MANUTENÇÃO DO PODER EXECUTIVO | S27: ADMINISTRAÇÃO DA UNIDADE | T27: NO ESTADO DE PERNAMBUCO | U27: PE | V27: PERNAMBUCO | W27: F | X27: 4 | Y27: 99 | Z27: 0 | AA27: 6 | AB27: 1000 | AC27: 250000 | AD27: A PRESENTE EMENDA TEM COMO FINALIDADE VIABILIZAR A AMPLIAÇÃO DO SISTEMA FOTOVOLTAICO DA ESCOLA DE APRENDIZES-MARINHEIROS DE PERNAMBUCO (EAMPE), GARANTINDO MAIOR EFICIÊNCIA ENERGÉTICA, REDUÇÃO DE CUSTOS OPERACIONAIS E MAIOR AUTONOMIA NO CONSUMO DE ENERGIA. A MEDIDA É ESTRATÉGICA PARA FORTALECER AS ATIVIDADES DA INSTITUIÇÃO, QUE ATUALMENTE MANTÉM O PROGRAMA FORÇAS NO ESPORTE (PROFESP), ATENDENDO CERCA DE 150 CRIANÇAS E ADOLESCENTES, E QUE, A PARTIR DE 2026, RECEBERÁ MAIS DE 260 ALUNOS PARA OS CURSOS DE FORMAÇÃO.
A28: 13 | B28: DEFESA | C28: 23970012 | D28: INDIVIDUAL | E28: INCLUSÃO - APROPRIAÇÃO | F28: 2397 | G28: HUGO LEAL | H28: DEPUTADO FEDERAL | I28: RJ | J28: PSD | K28: 52000 | L28: MINISTÉRIO DA DEFESA | M28: 52131 | N28: COMANDO DA MARINHA | O28: 05.152.6112.219D.0001 | P28: DEFESA NACIONAL | Q28: DEFESA NAVAL | R28: DEFESA NACIONAL | S28: ADEQUAÇÃO DE ATIVOS DE INFRAESTRUTURA DAS ORGANIZAÇÕES MILITARES | T28: NACIONAL | U28: NA | V28: NACIONAL | W28: F | X28: 4 | Y28: 90 | Z28: 0 | AA28: 6 | AB28: 1000 | AC28: 500000 | AD28: INVESTIMENTOS NA INFRAESTRUTURA DOS FUZILEIROS NAVAIS (MELHORIA DOS VESTIÁRIOS).
A29: 13 | B29: DEFESA | C29: 24460001 | D29: INDIVIDUAL | E29: INCLUSÃO - APROPRIAÇÃO | F29: 2446 | G29: JOÃO MAIA | H29: DEPUTADO FEDERAL | I29: RN | J29: PP | K29: 52000 | L29: MINISTÉRIO DA DEFESA | M29: 52931 | N29: FUNDO NAVAL | O29: 05.152.6112.21A0.0024 | P29: DEFESA NACIONAL | Q29: DEFESA NAVAL | R29: DEFESA NACIONAL | S29: APRESTAMENTO DAS FORÇAS - MANUTENÇÃO DA PRONTIDÃO E DA CAPACIDADE OPERATIVA | T29: NO ESTADO DO RIO GRANDE DO NORTE | U29: RN | V29: RIO GRANDE DO NORTE | W29: F | X29: 3 | Y29: 90 | Z29: 0 | AA29: 6 | AB29: 1000 | AC29: 300000 | AD29: A PRESENTE EMENDA PARLAMENTAR É DESTINADA À MANUTENÇÃO DE VIATURAS E REFORMA PREDIAL, OBJETIVANDO GARANTIR A PRONTIDÃO OPERATIVA DOS MEIOS EMPREGADOS NAS ATIVIDADES DO_x000D_ BATALHÃO, BEM COMO A READEQUAÇÃO DAS INSTALAÇÕES UTILIZADAS PELO EFETIVO.._x000D_ CNPJ : 00.394.502/0164-90
A30: 13 | B30: DEFESA | C30: 24680001 | D30: INDIVIDUAL | E30: INCLUSÃO - APROPRIAÇÃO | F30: 2468 | G30: LÍDICE DA MATA | H30: DEPUTADO FEDERAL | I30: BA | J30: PSB | K30: 52000 | L30: MINISTÉRIO DA DEFESA | M30: 52131 | N30: COMANDO DA MARINHA | O30: 05.301.0032.2E74.0029 | P30: DEFESA NACIONAL | Q30: ATENÇÃO BÁSICA | R30: PROGRAMA DE GESTÃO E MANUTENÇÃO DO PODER EXECUTIVO | S30: ESTRUTURAÇÃO E MODERNIZAÇÃO DE UNIDADES DE SAÚDE DAS FORÇAS ARMADAS | T30: NO ESTADO DA BAHIA | U30: BA | V30: BAHIA | W30: S | X30: 4 | Y30: 90 | Z30: 0 | AA30: 6 | AB30: 1000 | AC30: 120000 | AD30: HOSPITAL NAVAL DE SALVADOR - HNSA_x000D_ CNPJ: 00.394.502/0067-70_x000D_ _x000D_ CONTEMPLA A COMPRA DE EQUIPAMENTOS MÉDICOS PARA O SETOR DE ONCOLOGIA (INAUGURADO EM JANEIRO DE 2024), UTI, AMBULATÓRIO, LABORATÓRIO E CENTRO CIRÚRGICO, QUE AINDA NECESSITAM DE MATERIAL DE SAÚDE PARA SEU PLENO FUNCIONAMENTO. O HNSA É RESPONSÁVEL PELO ATENDIMENTO DE CERCA DE 16.000 USUÁRIOS ENTRE MILITARES E SEUS DEPENDENTES E, ALÉM DA SUA FUNÇÃO PRECÍPUA, TAMBÉM REALIZA AÇÕES CÍVICO-SOCIAIS EM PROL DE COMUNIDADES RIBEIRINHAS E CAIÇARAS, EM ÁREAS CARENTES. NA BUSCA DIUTURNA PELA MELHORIA DA QUALIDADE DO ATENDIMENTO PRESTADO AOS USUÁRIOS, FACE AO CRESCIMENTO CONTÍNUO DA DEMANDA DE ATENDIMENTO E DADA A IMPORTÂNCIA E CONTRIBUIÇÃO DO HOSPITAL PARA A SOCIEDADE, OBSERVA-SE A NECESSIDADE DE REALIZAÇÃO DE AQUISIÇÕES DE EQUIPAMENTOS DE SAÚDE PARA A VIABILIZAÇÃO DA EXPANSÃO DO ATENDIMENTO AO PÚBLICO, CONTRIBUINDO DIRETAMENTE COM O SISTEMA PÚBLICO DE SAÚDE LOCAL. _x000D_ O NÃO ATENDIMENTO DA DEMANDA SOLICITADA ELEVAM CUSTOS PARA ENCAMINHAMENTO A CLÍNICAS EXTERNAS E REDUZ A SEGURANÇA INDISPENSÁVEL AOS SERVIÇOS DE SAÚDE DESEMPENHADOS, TENDO EM VISTA QUE, OS REFERIDOS EQUIPAMENTOS PERMITEM QUE OS PROCEDIMENTOS E DIAGNÓSTICOS MÉDICOS SEJAM REALIZADOS COM A MÁXIMA PRESTEZA, HABILIDADE E EXCELÊNCIA, DENTRO DAS PRÓPRIAS INSTALAÇÕES DO HNSA.
A31: 13 | B31: DEFESA | C31: 24680003 | D31: INDIVIDUAL | E31: INCLUSÃO - APROPRIAÇÃO | F31: 2468 | G31: LÍDICE DA MATA | H31: DEPUTADO FEDERAL | I31: BA | J31: PSB | K31: 52000 | L31: MINISTÉRIO DA DEFESA | M31: 52121 | N31: COMANDO DO EXÉRCITO | O31: 05.153.6112.219D.0029 | P31: DEFESA NACIONAL | Q31: DEFESA TERRESTRE | R31: DEFESA NACIONAL | S31: ADEQUAÇÃO DE ATIVOS DE INFRAESTRUTURA DAS ORGANIZAÇÕES MILITARES | T31: NO ESTADO DA BAHIA | U31: BA | V31: BAHIA | W31: F | X31: 4 | Y31: 90 | Z31: 0 | AA31: 6 | AB31: 1000 | AC31: 120000 | AD31: ADEQUAÇÃO DE INSTALAÇÕES PARA ACOMODAR AS NOVAS RECRUTAS DO SERVIÇO MILITAR INICIAL FEMININO NA ESCOLA DE SAÚDE E FORMAÇÃO_x000D_ COMPLEMENTAR DO EXÉRCITO, COLÉGIO MILITAR DE SALVADOR, 6º BATALHÃO DE POLÍCIA DO EXÉRCITO E COMANDO DA 6ª REGIÃO MILITAR. | AE31: ESFCEx/CMS | AF31: Adequação de instalações SMIF
A32: 13 | B32: DEFESA | C32: 24680023 | D32: INDIVIDUAL | E32: INCLUSÃO - APROPRIAÇÃO | F32: 2468 | G32: LÍDICE DA MATA | H32: DEPUTADO FEDERAL | I32: BA | J32: PSB | K32: 52000 | L32: MINISTÉRIO DA DEFESA | M32: 52101 | N32: MINISTÉRIO DA DEFESA - ADMINISTRAÇÃO DIRETA | O32: 05.244.6111.21I8.0029 | P32: DEFESA NACIONAL | Q32: ASSISTÊNCIA COMUNITÁRIA | R32: COOPERAÇÃO DA DEFESA PARA O DESENVOLVIMENTO NACIONAL | S32: APOIO A PROJETOS SOCIAIS, EDUCACIONAIS E DE QUALIFICAÇÃO PROFISSIONAL | T32: NO ESTADO DA BAHIA | U32: BA | V32: BAHIA | W32: F | X32: 3 | Y32: 90 | Z32: 0 | AA32: 6 | AB32: 1000 | AC32: 100000 | AD32: O PROGRAMA FORÇAS NO ESPORTE (PROFESP) E O PROJETO JOÃO DO PULO (PJP) SÃO AÇÕES SOCIAIS CONDUZIDAS_x000D_ PELO MINISTÉRIO DA DEFESA (MD) E DESENVOLVIDAS POR INTERMÉDIO DA MARINHA DO BRASIL, DO EXÉRCITO BRASILEIRO_x000D_ E DA FORÇA AÉREA BRASILEIRA. ESSES PROJETOS PODEM CONTAR COM A PARCERIA DOS MINISTÉRIOS DOS DIREITOS_x000D_ HUMANOS E DA CIDADANIA, DA EDUCAÇÃO, DO ESPORTE, DA JUSTIÇA E SEGURANÇA PÚBLICA, DO DESENVOLVIMENTO E_x000D_ ASSISTÊNCIA SOCIAL, FAMÍLIA E COMBATE À FOME E DA SECRETARIA-GERAL DA PRESIDÊNCIA DA REPÚBLICA, DENTRE_x000D_ OUTRAS PASTAS DO EXECUTIVO FEDERAL._x000D_ O PROFESP E O PJP ATENDEM ATUALMENTE 11.479 BENEFICIADOS APROXIMADAMENTE, MAS COM CAPACIDADE PARA_x000D_ ATENDER ATÉ 30.000 JOVENS E CRIANÇAS, NA FAIXA ETÁRIA DE 6 A 18 ANOS, BEM COMO PESSOAS COM DEFICIÊNCIA, EM_x000D_ MAIS DE 200 (DUZENTAS) ORGANIZAÇÕES MILITARES (OM) DAS TRÊS FORÇAS ARMADAS QUE, DE FORMA VOLUNTÁRIA,_x000D_ DISPONIBILIZAM SUAS INSTALAÇÕES PARA A EXECUÇÃO DE ATIVIDADES PLANEJADAS E ELABORADAS COM_x000D_ ACOMPANHAMENTO PEDAGÓGICO, ABRANGENDO TODAS AS UNIDADES DA FEDERAÇÃO, EM MAIS DE 120 (CENTO E VINTE)_x000D_ MUNICÍPIOS, ALCANÇANDO LONGÍNQUAS REGIÕES DO NOSSO TERRITÓRIO, COMO, POR EXEMPLO, ALGUMAS COMUNIDADES_x000D_ INDÍGENAS E OUTRAS NA LINHA DE FRONTEIRA (PELOTÕES ESPECIAIS DE FRONTEIRA)._x000D_ NESTE SENTIDO, MEDIANTE OS COMPROVADOS ÍNDICES DE EFICÁCIA ATINGIDOS PELO PROFESP E PJP E CONSOANTE À_x000D_ SUA EFICIENTE SISTEMÁTICA DE FUNCIONAMENTO, VISLUMBRA-SE A POSSIBILIDADE DE AUMENTAR O NÚMERO DE_x000D_ BENEFICIÁRIOS, COM O FORNECIMENTO DE ALIMENTAÇÃO ADEQUADA E REALIZAÇÃO DE ATIVIDADES DESPORTIVAS E_x000D_ ESCOLARES, NO CONTRATURNO ESCOLAR EM UM AMBIENTE SEGURO, BEM COMO GARANTIR A MANUTENÇÃO DA INFRAESTRUTURA_x000D_ DESPORTIVA NAS INSTALAÇÕES EM QUE O PROGRAMA/PROJETO EM PAUTA É DESENVOLVIDO._x000D_ O RECURSO DA EMENDA CONTRIBUIRÁ PARA O FORTALECIMENTO DA INICIATIVA VOLUNTÁRIA DOS COMANDANTES DE OM_x000D_ QUE DESENVOLVEM O PROFESP E PJP NO ESTADO DA BAHIA E UMA PARCERIA COM V. EXA. TORNAR-SE-Á UM FATOR_x000D_ _x000D_ DE FUNDAMENTAL IMPORTÂNCIA PARA O SUCESSO DO EMPREENDIMENTO EM PROL DOS BENEFICIADOS E DE SUAS FAMÍLIAS._x000D_ ESSES RECURSOS FINANCEIROS SERÃO APLICADOS DENTRO DAS SEGUINTES FINALIDADES:_x000D_ A) ALIMENTAÇÃO DOS BENEFICIADOS;_x000D_ B) AQUISIÇÃO DE UNIFORME E MATERIAL ESPORTIVO PARA OS PARTICIPANTES DO PROGRAMA/PROJETO;_x000D_ C) APOIO À REALIZAÇÃO DE ATIVIDADES EDUCACIONAIS ESPORTIVAS;_x000D_ D) CAPACITAÇÃO PEDAGÓGICA PARA OS PROFESSORES, COORDENADORES E MONITORES; E_x000D_ E) MELHORIA DA INFRAESTRUTURA DAS OM PARTICIPANTES EM PROL DO PROFESP/PJP.
A33: 13 | B33: DEFESA | C33: 24820008 | D33: INDIVIDUAL | E33: ACRÉSCIMO - APROPRIAÇÃO | F33: 2482 | G33: LUIZ FERNANDO FARIA | H33: DEPUTADO FEDERAL | I33: MG | J33: UNIÃO | K33: 52000 | L33: MINISTÉRIO DA DEFESA | M33: 52121 | N33: COMANDO DO EXÉRCITO | O33: 05.153.6112.21A0.0001 | P33: DEFESA NACIONAL | Q33: DEFESA TERRESTRE | R33: DEFESA NACIONAL | S33: APRESTAMENTO DAS FORÇAS - MANUTENÇÃO DA PRONTIDÃO E DA CAPACIDADE OPERATIVA | T33: NACIONAL | U33: NA | V33: NACIONAL | W33: F | X33: 4 | Y33: 90 | Z33: 0 | AA33: 6 | AB33: 1000 | AC33: 350000 | AD33: BENEFICIÁRIO PARA LANÇAMENTO NO SIOP - CNPJ: 00.394.452/0001-03_x000D_ APOIAR O TRANSPORTE DOS MILITARES DA UNIDADE EM MISSÕES E PARA A REALIZAÇÃO DE AÇÕES CÍVICO-SOCIAIS (ACISO) OU EM AÇÕES JUNTO À DEFESA CIVIL E ÀS AUTORIDADES CIVIS QUE NECESSITEM DE APOIO._x000D_ _x000D_ COMPANHIA DE COMANDO DA 4ª BRIGADA LEVE DE MONTANHA (CIA C/4ª BDA INF L MTH), NO MUNICÍPIO DE JUIZ DE FORA - MG. | AE33: Cia C/4ª Bda Inf L Mth | AF33: Vtr Adm tipo Van
A34: 13 | B34: DEFESA | C34: 24820009 | D34: INDIVIDUAL | E34: INCLUSÃO - APROPRIAÇÃO | F34: 2482 | G34: LUIZ FERNANDO FARIA | H34: DEPUTADO FEDERAL | I34: MG | J34: UNIÃO | K34: 52000 | L34: MINISTÉRIO DA DEFESA | M34: 52111 | N34: COMANDO DA AERONÁUTICA | O34: 05.122.0032.2000.0031 | P34: DEFESA NACIONAL | Q34: ADMINISTRAÇÃO GERAL | R34: PROGRAMA DE GESTÃO E MANUTENÇÃO DO PODER EXECUTIVO | S34: ADMINISTRAÇÃO DA UNIDADE | T34: NO ESTADO DE MINAS GERAIS | U34: MG | V34: MINAS GERAIS | W34: F | X34: 4 | Y34: 90 | Z34: 0 | AA34: 6 | AB34: 1000 | AC34: 300000 | AD34: "CNPJ PARA LANÇAMENTO NO SIOP: 00.394.429/0001-00 - COMANDO DA AERONÁUTICA_x000D_ OM BENEFICIADA: ESCOLA PRAPARATÓRIA DE CADETES DO AR_x000D_ OBJETO RESUMIDO: USINA FOTOVOLTAICA DE 300 KW DE POTÊNCIA._x000D_ JUSTIFICATIVA:_x000D_ A FORÇA AÉREA BRASILEIRA (FAB), COMO INSTITUIÇÃO DE ESTADO, ATUA, ININTERRUPTAMENTE, NA DEFESA DA PÁTRIA, NA MANUTENÇÃO DA SOBERANIA DO NOSSO ESPAÇO AÉREO, NA PROTEÇÃO DE NOSSAS FRONTEIRAS E NA INTEGRAÇÃO DO TERRITÓRIO NACIONAL._x000D_ ADEMAIS, SUBSIDIARIAMENTE, A FAB CUMPRE MISSÕES HUMANITÁRIAS E DE REPATRIAÇÃO DE NACIONAIS, DE TRANSPORTE DE ÓRGÃOS E TECIDOS, BEM COMO CONTRIBUI COM O DESENVOLVIMENTO TECNOLÓGICO, GERANDO EMPREGOS E RIQUEZAS AO PAÍS._x000D_ PELO EXPOSTO, PARA CONTRIBUIR COM A FAB NO CUMPRIMENTO DE SUA MISSÃO CONSTITUCIONAL EM BENEFÍCIO DA SOCIEDADE BRASILEIRA, É NECESSÁRIO O APOIO AOS PROJETOS E ATIVIDADES SUPRAMENCIONADOS COM O APORTE DE RECURSOS DE EMENDAS PARLAMENTARES NA LEI ORÇAMENTÁRIA ANUAL (LOA) DE 2026."
A35: 13 | B35: DEFESA | C35: 25170009 | D35: INDIVIDUAL | E35: INCLUSÃO - APROPRIAÇÃO | F35: 2517 | G35: VINICIUS CARVALHO | H35: DEPUTADO FEDERAL | I35: SP | J35: PL | K35: 52000 | L35: MINISTÉRIO DA DEFESA | M35: 52121 | N35: COMANDO DO EXÉRCITO | O35: 05.301.0032.2E74.3474 | P35: DEFESA NACIONAL | Q35: ATENÇÃO BÁSICA | R35: PROGRAMA DE GESTÃO E MANUTENÇÃO DO PODER EXECUTIVO | S35: ESTRUTURAÇÃO E MODERNIZAÇÃO DE UNIDADES DE SAÚDE DAS FORÇAS ARMADAS | T35: NO MUNICÍPIO DE CAMPINAS - SP | U35: SP | V35: CAMPINAS | W35: S | X35: 4 | Y35: 90 | Z35: 0 | AA35: 6 | AB35: 1000 | AC35: 450000 | AD35: BENEFICIÁRIO PARA LANÇAMENTO NO SIOP - CNPJ: 00.394.452/0001-03_x000D_ MELHORAR O APOIO EM SAÚDE PARA OS MILITARES, ALUNOS, DEPENDENTES E A COMUNIDADE LOCAL NO CASO DE TRANSPORTE DE PACIENTES._x000D_ _x000D_ ESCOLA PREPARATÓRIA DE CADETES DO EXÉRCITO (ESPCEX), NO MUNICÍPIO DE CAMPINAS - SP. | AE35: EsPCEx | AF35: Ambulância tipo “B” – Suporte básico
A36: 13 | B36: DEFESA | C36: 25170012 | D36: INDIVIDUAL | E36: ACRÉSCIMO - APROPRIAÇÃO | F36: 2517 | G36: VINICIUS CARVALHO | H36: DEPUTADO FEDERAL | I36: SP | J36: PL | K36: 52000 | L36: MINISTÉRIO DA DEFESA | M36: 52131 | N36: COMANDO DA MARINHA | O36: 05.152.6112.219D.0001 | P36: DEFESA NACIONAL | Q36: DEFESA NAVAL | R36: DEFESA NACIONAL | S36: ADEQUAÇÃO DE ATIVOS DE INFRAESTRUTURA DAS ORGANIZAÇÕES MILITARES | T36: NACIONAL | U36: NA | V36: NACIONAL | W36: F | X36: 4 | Y36: 90 | Z36: 0 | AA36: 6 | AB36: 1000 | AC36: 400000 | AD36: BASE DE FUZILEIROS NAVAIS DA ILHA DAS FLORES - BFNIF_x000D_ CNPJ: 00.394.502/0344-72_x000D_ _x000D_ AS CRIANÇAS E JOVENS DO PROFESP UTILIZAM DIARIAMENTE A ESTRUTURA DO COMPLEXO AQUÁTICO DO CNIF PARA PRÁTICA DOS ESPORTES AQUÁTICOS (NATAÇÃO, PÓLO AQUÁTICO, ETC...) E RECREAÇÃO, CONTRIBUINDO PARA O DESENVOLVIMENTO DAS HABILIDADES MOTORAS, COGNITIVAS E SOCIAIS DOS ALUNOS. ESTE REFERIDO PROJETO ABRANGE A INSTALAÇÃO DE ÁGUA TÉRMICA, COBERTURA NA PISCINA E RAMPA PARA ACESSO DE PCD.
A37: 13 | B37: DEFESA | C37: 26010011 | D37: INDIVIDUAL | E37: INCLUSÃO - APROPRIAÇÃO | F37: 2601 | G37: MÁRCIO MARINHO | H37: DEPUTADO FEDERAL | I37: BA | J37: REPUBLICANOS | K37: 52000 | L37: MINISTÉRIO DA DEFESA | M37: 52931 | N37: FUNDO NAVAL | O37: 05.122.0032.2000.0001 | P37: DEFESA NACIONAL | Q37: ADMINISTRAÇÃO GERAL | R37: PROGRAMA DE GESTÃO E MANUTENÇÃO DO PODER EXECUTIVO | S37: ADMINISTRAÇÃO DA UNIDADE | T37: NACIONAL | U37: NA | V37: NACIONAL | W37: F | X37: 4 | Y37: 90 | Z37: 0 | AA37: 6 | AB37: 1000 | AC37: 1000000 | AD37: A REFERIDA EMENDA VISA ATENDER O COMANDO DO 2º DISTRITO NAVAL, CNPJ 00.394.502/0027-83, NA AQUISIÇÃO DE EQUIPAMENTOS E OBRAS NECESSÁRIAS PARA INSTALAR UMA ESTAÇÃO DE TRANSMISSÃO DE RADIO FM.
A38: 13 | B38: DEFESA | C38: 26760004 | D38: INDIVIDUAL | E38: INCLUSÃO - APROPRIAÇÃO | F38: 2676 | G38: VINICIUS GURGEL | H38: DEPUTADO FEDERAL | I38: AP | J38: PL | K38: 52000 | L38: MINISTÉRIO DA DEFESA | M38: 52121 | N38: COMANDO DO EXÉRCITO | O38: 05.153.6112.219D.0016 | P38: DEFESA NACIONAL | Q38: DEFESA TERRESTRE | R38: DEFESA NACIONAL | S38: ADEQUAÇÃO DE ATIVOS DE INFRAESTRUTURA DAS ORGANIZAÇÕES MILITARES | T38: NO ESTADO DO AMAPÁ | U38: AP | V38: AMAPÁ | W38: F | X38: 4 | Y38: 90 | Z38: 0 | AA38: 6 | AB38: 1000 | AC38: 230000 | AD38: A EMENDA TEM POR OBJETIVO DESTINAR RECURSO PARA A AQUISIÇÃO DE EQUIPAMENTO DE ACADEMIA PARA A UNIDADE DO EXÉRCITO BRASILEIRO NO ESTADO DO AMAPÁ. A MEDIDA VISA APRIMORAR AS CONDIÇÕES DE TREINAMENTO FÍSICO E DE SAÚDE DOS MILITARES, FORTALECENDO A PRONTIDÃO OPERACIONAL E A QUALIDADE DE VIDA DO EFETIVO. | AE38: Cmdo 22ª Bda Inf Sl | AF38: Equipamentos para academia de musculação
A39: 13 | B39: DEFESA | C39: 27010003 | D39: INDIVIDUAL | E39: INCLUSÃO - APROPRIAÇÃO | F39: 2701 | G39: DOMINGOS NETO | H39: DEPUTADO FEDERAL | I39: CE | J39: PSD | K39: 52000 | L39: MINISTÉRIO DA DEFESA | M39: 52121 | N39: COMANDO DO EXÉRCITO | O39: 05.153.6112.21A0.0023 | P39: DEFESA NACIONAL | Q39: DEFESA TERRESTRE | R39: DEFESA NACIONAL | S39: APRESTAMENTO DAS FORÇAS - MANUTENÇÃO DA PRONTIDÃO E DA CAPACIDADE OPERATIVA | T39: NO ESTADO DO CEARÁ | U39: CE | V39: CEARÁ | W39: F | X39: 3 | Y39: 90 | Z39: 0 | AA39: 6 | AB39: 1000 | AC39: 50000 | AD39: A PRESENTE EMENDA VISA PROPORCIONAR MELHORES CONDIÇÕES PARA A PRÁTICA DE ATIVIDADES FÍSICAS DOS ALUNOS E MILITARES DO COLÉGIO MILITAR DE FORTALEZA, COM AQUISIÇÃO DE MESA DE TÊNIS DE MESA, MATERIAIS PARA ESGRIMA, FUTMESA, TABELAS DE BASQUETE, PEBOLIM, ENTRE OUTROS. | AE39: CMF | AF39: Material esportivo e de recreação
A40: 13 | B40: DEFESA | C40: 27010003 | D40: INDIVIDUAL | E40: INCLUSÃO - APROPRIAÇÃO | F40: 2701 | G40: DOMINGOS NETO | H40: DEPUTADO FEDERAL | I40: CE | J40: PSD | K40: 52000 | L40: MINISTÉRIO DA DEFESA | M40: 52121 | N40: COMANDO DO EXÉRCITO | O40: 05.153.6112.21A0.0023 | P40: DEFESA NACIONAL | Q40: DEFESA TERRESTRE | R40: DEFESA NACIONAL | S40: APRESTAMENTO DAS FORÇAS - MANUTENÇÃO DA PRONTIDÃO E DA CAPACIDADE OPERATIVA | T40: NO ESTADO DO CEARÁ | U40: CE | V40: CEARÁ | W40: F | X40: 4 | Y40: 90 | Z40: 0 | AA40: 6 | AB40: 1000 | AC40: 200000 | AD40: A PRESENTE EMENDA VISA PROPORCIONAR MELHORES CONDIÇÕES PARA A PRÁTICA DE ATIVIDADES FÍSICAS DOS ALUNOS E MILITARES DO COLÉGIO MILITAR DE FORTALEZA, COM AQUISIÇÃO DE MESA DE TÊNIS DE MESA, MATERIAIS PARA ESGRIMA, FUTMESA, TABELAS DE BASQUETE, PEBOLIM, ENTRE OUTROS. | AE40: CMF | AF40: Material esportivo e de recreação
A41: 13 | B41: DEFESA | C41: 27140006 | D41: INDIVIDUAL | E41: ACRÉSCIMO - APROPRIAÇÃO | F41: 2714 | G41: ROMERO RODRIGUES | H41: DEPUTADO FEDERAL | I41: PB | J41: PODE | K41: 52000 | L41: MINISTÉRIO DA DEFESA | M41: 52121 | N41: COMANDO DO EXÉRCITO | O41: 05.153.6112.21A0.0001 | P41: DEFESA NACIONAL | Q41: DEFESA TERRESTRE | R41: DEFESA NACIONAL | S41: APRESTAMENTO DAS FORÇAS - MANUTENÇÃO DA PRONTIDÃO E DA CAPACIDADE OPERATIVA | T41: NACIONAL | U41: NA | V41: NACIONAL | W41: F | X41: 4 | Y41: 90 | Z41: 0 | AA41: 6 | AB41: 1000 | AC41: 200000 | AD41: BENEFICIÁRIO PARA LANÇAMENTO NO SIOP - CNPJ: 00.394.452/0001-03_x000D_ ADQUIRIR NOVOS INSTRUMENTOS, MELHORANDO AS CONDIÇÕES PARA OS ENSAIOS E APRESENTAÇÕES DA BANDA DE MÚSICA DA UNIDADE, QUE APOIA DIVERSOS EVENTOS CULTURAIS NO MUNICÍPIO._x000D_ _x000D_ 31º BATALHÃO DE INFANTARIA MOTORIZADO (31º BI MTZ), NO MUNICÍPIO DE CAMPINA GRANDE - PB. | AE41: 31º BI Mtz | AF41: Instrumentos musicais
A42: 13 | B42: DEFESA | C42: 27180015 | D42: INDIVIDUAL | E42: INCLUSÃO - APROPRIAÇÃO | F42: 2718 | G42: AUGUSTO COUTINHO | H42: DEPUTADO FEDERAL | I42: PE | J42: REPUBLICANOS | K42: 52000 | L42: MINISTÉRIO DA DEFESA | M42: 52121 | N42: COMANDO DO EXÉRCITO | O42: 05.122.0032.2000.0026 | P42: DEFESA NACIONAL | Q42: ADMINISTRAÇÃO GERAL | R42: PROGRAMA DE GESTÃO E MANUTENÇÃO DO PODER EXECUTIVO | S42: ADMINISTRAÇÃO DA UNIDADE | T42: NO ESTADO DE PERNAMBUCO | U42: PE | V42: PERNAMBUCO | W42: F | X42: 3 | Y42: 90 | Z42: 0 | AA42: 6 | AB42: 1000 | AC42: 150000 | AD42: A REFERIDA EMENDA VISA MELHORAR AS CONDIÇÕES DE ARMAZENAMENTO E PREPARAÇÃO DOS ALIMENTOS DO REFEITÓRIO, PROPORCIONANDO UMA MELHOR REFEIÇÃO PARA OS ALUNOS DO PROGRAMA FORÇAS NO ESPORTE (PROFESP). | AE42: 4º B Com | AF42: Adequação de instalações (PROFESP)
A43: 13 | B43: DEFESA | C43: 27180016 | D43: INDIVIDUAL | E43: INCLUSÃO - APROPRIAÇÃO | F43: 2718 | G43: AUGUSTO COUTINHO | H43: DEPUTADO FEDERAL | I43: PE | J43: REPUBLICANOS | K43: 52000 | L43: MINISTÉRIO DA DEFESA | M43: 52931 | N43: FUNDO NAVAL | O43: 05.125.6112.21BY.0026 | P43: DEFESA NACIONAL | Q43: NORMATIZAÇÃO E FISCALIZAÇÃO | R43: DEFESA NACIONAL | S43: FISCALIZAÇÃO DA NAVEGAÇÃO AQUAVIÁRIA | T43: NO ESTADO DE PERNAMBUCO | U43: PE | V43: PERNAMBUCO | W43: F | X43: 4 | Y43: 90 | Z43: 0 | AA43: 6 | AB43: 1000 | AC43: 190000 | AD43: ESTA PROPOSTA DE EMENDA VISA A AQUISIÇÃO DE UMA MOTO AQUÁTICA PARA DESEMPENHAR ATIVIDADES DE INSPEÇÃO NAVAL E VISTORIA DE EMBARCAÇÕES DE MODO A INTENSIFICAR ESSAS ATIVIDADES NO LITORAL, RIOS, BARRAGENS E AÇUDES PERNAMBUCANOS. CAPITANIA DOS PORTOS DE PERNAMBUCO (CPPE).
A44: 13 | B44: DEFESA | C44: 27180017 | D44: INDIVIDUAL | E44: INCLUSÃO - APROPRIAÇÃO | F44: 2718 | G44: AUGUSTO COUTINHO | H44: DEPUTADO FEDERAL | I44: PE | J44: REPUBLICANOS | K44: 52000 | L44: MINISTÉRIO DA DEFESA | M44: 52131 | N44: COMANDO DA MARINHA | O44: 05.301.0032.2E74.0026 | P44: DEFESA NACIONAL | Q44: ATENÇÃO BÁSICA | R44: PROGRAMA DE GESTÃO E MANUTENÇÃO DO PODER EXECUTIVO | S44: ESTRUTURAÇÃO E MODERNIZAÇÃO DE UNIDADES DE SAÚDE DAS FORÇAS ARMADAS | T44: NO ESTADO DE PERNAMBUCO | U44: PE | V44: PERNAMBUCO | W44: S | X44: 3 | Y44: 90 | Z44: 0 | AA44: 6 | AB44: 1000 | AC44: 150000 | AD44: HOSPITAL NAVAL DO RECIFE (HNRE)_x000D_ CNPJ: 00.394.502/0066-90_x000D_ _x000D_ A EMENDA TEM COMO OBJETIVO VIABILIZAR A REFORMA DO SERVIÇO DE ODONTOLOGIA DO HOSPITAL NAVAL DE RECIFE, ASSEGURANDO A MODERNIZAÇÃO DAS INSTALAÇÕES. A MELHORIA DA INFRAESTRUTURA PERMITIRÁ OFERECER ATENDIMENTOS ODONTOLÓGICOS DE MAIOR QUALIDADE E GARANTIR MELHORES CONDIÇÕES DE TRABALHO AOS PROFISSIONAIS.
A45: 13 | B45: DEFESA | C45: 27240002 | D45: INDIVIDUAL | E45: INCLUSÃO - APROPRIAÇÃO | F45: 2724 | G45: PASTOR EURICO | H45: DEPUTADO FEDERAL | I45: PE | J45: PSDB | K45: 52000 | L45: MINISTÉRIO DA DEFESA | M45: 52111 | N45: COMANDO DA AERONÁUTICA | O45: 05.301.0032.2E74.0026 | P45: DEFESA NACIONAL | Q45: ATENÇÃO BÁSICA | R45: PROGRAMA DE GESTÃO E MANUTENÇÃO DO PODER EXECUTIVO | S45: ESTRUTURAÇÃO E MODERNIZAÇÃO DE UNIDADES DE SAÚDE DAS FORÇAS ARMADAS | T45: NO ESTADO DE PERNAMBUCO | U45: PE | V45: PERNAMBUCO | W45: S | X45: 4 | Y45: 90 | Z45: 0 | AA45: 6 | AB45: 1000 | AC45: 350000 | AD45: ESTA EMENDA TEM O OBJETIVO DE ALOCAR RECURSOS PARA O COMANDO DA AERONÁUTICA DO BRASIL VISANDO COMPLEMENTAR AS AÇÕES DE ESTRUTURAÇÃO E MODERNIZAÇÃO DAS UNIDADES DE SAÚDE DAS FORÇAS ARMADAS EM PERNAMBUCO. TAL AÇÃO POSSIBILITARÁ A MELHORIA DOS SERVIÇOS OFERTADOS AOS MILITARES GARANTINDO A QUALIDADE DOS DIVERSOS TRATAMENTOS OFERECIDOS.
A46: 13 | B46: DEFESA | C46: 27240007 | D46: INDIVIDUAL | E46: INCLUSÃO - APROPRIAÇÃO | F46: 2724 | G46: PASTOR EURICO | H46: DEPUTADO FEDERAL | I46: PE | J46: PSDB | K46: 52000 | L46: MINISTÉRIO DA DEFESA | M46: 52121 | N46: COMANDO DO EXÉRCITO | O46: 05.153.6112.21A0.0026 | P46: DEFESA NACIONAL | Q46: DEFESA TERRESTRE | R46: DEFESA NACIONAL | S46: APRESTAMENTO DAS FORÇAS - MANUTENÇÃO DA PRONTIDÃO E DA CAPACIDADE OPERATIVA | T46: NO ESTADO DE PERNAMBUCO | U46: PE | V46: PERNAMBUCO | W46: F | X46: 4 | Y46: 90 | Z46: 0 | AA46: 6 | AB46: 1000 | AC46: 320000 | AD46: ESTA EMENDA TEM O OBJETIVO DE ALOCAR RECURSOS PARA O COMANDO DO EXÉRCITO BRASILEIRO VISANDO A MANUTENÇÃO DA PRONTIDÃO E DA CAPACIDADE OPERATIVA DOS BATALHÕES EM PERNAMBUCO. | AE46: 4º BPE | AF46: 8 (oito) motocicletas para escolta
A47: 13 | B47: DEFESA | C47: 27240009 | D47: INDIVIDUAL | E47: INCLUSÃO - APROPRIAÇÃO | F47: 2724 | G47: PASTOR EURICO | H47: DEPUTADO FEDERAL | I47: PE | J47: PSDB | K47: 52000 | L47: MINISTÉRIO DA DEFESA | M47: 52131 | N47: COMANDO DA MARINHA | O47: 05.301.0032.2E74.0026 | P47: DEFESA NACIONAL | Q47: ATENÇÃO BÁSICA | R47: PROGRAMA DE GESTÃO E MANUTENÇÃO DO PODER EXECUTIVO | S47: ESTRUTURAÇÃO E MODERNIZAÇÃO DE UNIDADES DE SAÚDE DAS FORÇAS ARMADAS | T47: NO ESTADO DE PERNAMBUCO | U47: PE | V47: PERNAMBUCO | W47: S | X47: 4 | Y47: 90 | Z47: 0 | AA47: 6 | AB47: 1000 | AC47: 260000 | AD47: ESTA EMENDA TEM O OBJETIVO DE ALOCAR RECURSOS PARA O COMANDO DA MARINHA DO BRASIL VISANDO COMPLEMENTAR AS AÇÕES DE ESTRUTURAÇÃO E MODERNIZAÇÃO DAS UNIDADES DE SAÚDE DAS FORÇAS ARMADAS EM PERNAMBUCO. TAL AÇÃO POSSIBILITARÁ A MELHORIA DOS SERVIÇOS OFERTADOS AOS MILITARES GARANTINDO A QUALIDADE DOS DIVERSOS TRATAMENTOS OFERECIDOS.
A48: 13 | B48: DEFESA | C48: 27370014 | D48: INDIVIDUAL | E48: INCLUSÃO - APROPRIAÇÃO | F48: 2737 | G48: ANTONIO BRITO | H48: DEPUTADO FEDERAL | I48: BA | J48: PSD | K48: 52000 | L48: MINISTÉRIO DA DEFESA | M48: 52131 | N48: COMANDO DA MARINHA | O48: 05.301.0032.2E74.0029 | P48: DEFESA NACIONAL | Q48: ATENÇÃO BÁSICA | R48: PROGRAMA DE GESTÃO E MANUTENÇÃO DO PODER EXECUTIVO | S48: ESTRUTURAÇÃO E MODERNIZAÇÃO DE UNIDADES DE SAÚDE DAS FORÇAS ARMADAS | T48: NO ESTADO DA BAHIA | U48: BA | V48: BAHIA | W48: S | X48: 4 | Y48: 90 | Z48: 0 | AA48: 6 | AB48: 1000 | AC48: 250000 | AD48: ESSA EMENDA VISA ALOCAR RECURSOS PARA O HOSPITAL NAVAL DE SALVADOR , PARA CONTRIBUIR COM A MELHORIA DAS INSTALAAÇÕES COM O OBJETIVO DO APRIMORAMENTO DOS SERVIÇOS PRESTADOS AOS USUÁRIOS DO SISTEMA DE SAÚDE DA MARINHA.
A49: 13 | B49: DEFESA | C49: 27370015 | D49: INDIVIDUAL | E49: ACRÉSCIMO - APROPRIAÇÃO | F49: 2737 | G49: ANTONIO BRITO | H49: DEPUTADO FEDERAL | I49: BA | J49: PSD | K49: 52000 | L49: MINISTÉRIO DA DEFESA | M49: 52121 | N49: COMANDO DO EXÉRCITO | O49: 05.153.6112.219D.0001 | P49: DEFESA NACIONAL | Q49: DEFESA TERRESTRE | R49: DEFESA NACIONAL | S49: ADEQUAÇÃO DE ATIVOS DE INFRAESTRUTURA DAS ORGANIZAÇÕES MILITARES | T49: NACIONAL | U49: NA | V49: NACIONAL | W49: F | X49: 3 | Y49: 90 | Z49: 0 | AA49: 6 | AB49: 1000 | AC49: 250000 | AD49: BENEFICIÁRIO PARA LANÇAMENTO NO SIOP - CNPJ: 00.394.452/0001-03_x000D_ MEHORAR O ATENDIMENTO MÉDICO, PSICOLÓGICO E DENTÁRIO AOS ALUNOS DA ESCOLA DE SAÚDE E FORMAÇÃO COMPLEMENTAR DO EXÉRCITO (ESFCEX) E DO COLÉGIO MILITAR DE SALVADOR (CMS), ALÉM DE SERVIR COMO LOCAL DE INSTRUÇÃO PRÁTICA AOS ALUNOS DE SAÚDE._x000D_ _x000D_ ESCOLA DE SAÚDE E FORMAÇÃO COMPLEMENTAR DO EXÉRCITO (ESFCEX), NO MUNICÍPIO DE SALVADOR - BA | AE49: ESFCEx | AF49: Adequação da Seção de Saúde
A50: 13 | B50: DEFESA | C50: 27390011 | D50: INDIVIDUAL | E50: ACRÉSCIMO - APROPRIAÇÃO | F50: 2739 | G50: ARTHUR OLIVEIRA MAIA | H50: DEPUTADO FEDERAL | I50: BA | J50: UNIÃO | K50: 52000 | L50: MINISTÉRIO DA DEFESA | M50: 52121 | N50: COMANDO DO EXÉRCITO | O50: 05.122.0032.2000.0001 | P50: DEFESA NACIONAL | Q50: ADMINISTRAÇÃO GERAL | R50: PROGRAMA DE GESTÃO E MANUTENÇÃO DO PODER EXECUTIVO | S50: ADMINISTRAÇÃO DA UNIDADE | T50: NACIONAL | U50: NA | V50: NACIONAL | W50: F | X50: 3 | Y50: 90 | Z50: 0 | AA50: 6 | AB50: 1000 | AC50: 300000 | AD50: BENEFICIÁRIO PARA LANÇAMENTO NO SIOP - CNPJ: 00.394.452/0001-03_x000D_ ADEQUAR E MELHORAR AS INSTALAÇÕES DA COMISSÃO DE SELEÇÃO PERMANENTE DAS FORÇAS ARMADAS (CSPFA), POSTO DE RECRUTAMENTO MILITAR (PRM) E DO CENTRO MARECHAL CANTUÁRIA, QUE PRESTA INÚMEROS SERVIÇOS ASSISTENCIAIS, EDUCATIVOS, CULTURAIS, ENTRE OUTROS À FAMÍLIA MILITAR E À COMUNIDADE DO ENTORNO EM SALVADOR._x000D_ _x000D_ EXÉRCITO BRASILEIRO – EMENDA INDIVIDUAL – BA – ADMINISTRAÇÃO DA UNIDADE NA (O) COMANDO DA 6ª REGIÃO MILITAR (CMDO 6ª RM), NO MUNICÍPIO DE SALVADOR - BA | AE50: Cmdo 6ª RM | AF50: Adequação das instalações e Material permanente
A51: 13 | B51: DEFESA | C51: 27390011 | D51: INDIVIDUAL | E51: ACRÉSCIMO - APROPRIAÇÃO | F51: 2739 | G51: ARTHUR OLIVEIRA MAIA | H51: DEPUTADO FEDERAL | I51: BA | J51: UNIÃO | K51: 52000 | L51: MINISTÉRIO DA DEFESA | M51: 52121 | N51: COMANDO DO EXÉRCITO | O51: 05.122.0032.2000.0001 | P51: DEFESA NACIONAL | Q51: ADMINISTRAÇÃO GERAL | R51: PROGRAMA DE GESTÃO E MANUTENÇÃO DO PODER EXECUTIVO | S51: ADMINISTRAÇÃO DA UNIDADE | T51: NACIONAL | U51: NA | V51: NACIONAL | W51: F | X51: 4 | Y51: 90 | Z51: 0 | AA51: 6 | AB51: 1000 | AC51: 200000 | AD51: BENEFICIÁRIO PARA LANÇAMENTO NO SIOP - CNPJ: 00.394.452/0001-03_x000D_ ADEQUAR E MELHORAR AS INSTALAÇÕES DA COMISSÃO DE SELEÇÃO PERMANENTE DAS FORÇAS ARMADAS (CSPFA), POSTO DE RECRUTAMENTO MILITAR (PRM) E DO CENTRO MARECHAL CANTUÁRIA, QUE PRESTA INÚMEROS SERVIÇOS ASSISTENCIAIS, EDUCATIVOS, CULTURAIS, ENTRE OUTROS À FAMÍLIA MILITAR E À COMUNIDADE DO ENTORNO EM SALVADOR._x000D_ _x000D_ EXÉRCITO BRASILEIRO – EMENDA INDIVIDUAL – BA – ADMINISTRAÇÃO DA UNIDADE NA (O) COMANDO DA 6ª REGIÃO MILITAR (CMDO 6ª RM), NO MUNICÍPIO DE SALVADOR - BA | AE51: Cmdo 6ª RM | AF51: Adequação das instalações e Material permanente
A52: 13 | B52: DEFESA | C52: 27590005 | D52: INDIVIDUAL | E52: INCLUSÃO - APROPRIAÇÃO | F52: 2759 | G52: EROS BIONDINI | H52: DEPUTADO FEDERAL | I52: MG | J52: PL | K52: 52000 | L52: MINISTÉRIO DA DEFESA | M52: 52121 | N52: COMANDO DO EXÉRCITO | O52: 05.301.0032.2E74.3132 | P52: DEFESA NACIONAL | Q52: ATENÇÃO BÁSICA | R52: PROGRAMA DE GESTÃO E MANUTENÇÃO DO PODER EXECUTIVO | S52: ESTRUTURAÇÃO E MODERNIZAÇÃO DE UNIDADES DE SAÚDE DAS FORÇAS ARMADAS | T52: NO MUNICÍPIO DE SETE LAGOAS - MG | U52: MG | V52: SETE LAGOAS | W52: S | X52: 4 | Y52: 90 | Z52: 0 | AA52: 6 | AB52: 1000 | AC52: 200000 | AD52: EMENDA QUE VISA AQUISIÇÃO DE UM VEÍCULO TIPO AMBULÂNCIA TENDO COMO BENEFICIÁRIO PARA O 4º GRUPO DE ARTILHARIA ANTIAÉREA (4º GAAAE), NO MUNICÍPIO DE SETE LAGOAS - MG. PARA FINS DE HOMOLOGAÇÃO NO SISTEMA DO SIOP FAZER CONSTAR POR MEIO DO CNPJ: 00.394.452/0001-03 SUA INSERÇÃO. IMPORTANTE INFORMAR QUE A AMBULÂNCIA PERMITIRÁ MAIOR AUTONOMIA NA REMOÇÃO DE FERIDOS PARA UNIDADES HOSPITALARES, EM SETE LAGOAS OU EM OUTRO MUNICÍPIO, EVITANDO DEPENDÊNCIA DE SERVIÇOS EXTERNOS QUE PODEM NÃO ATENDER COM A URGÊNCIA NECESSÁRIA. | AE52: 4º GAAAe | AF52: Ambulância tipo “B” – Suporte básico
A53: 13 | B53: DEFESA | C53: 27620005 | D53: INDIVIDUAL | E53: INCLUSÃO - APROPRIAÇÃO | F53: 2762 | G53: LUIS TIBÉ | H53: DEPUTADO FEDERAL | I53: MG | J53: AVANTE | K53: 52000 | L53: MINISTÉRIO DA DEFESA | M53: 52121 | N53: COMANDO DO EXÉRCITO | O53: 05.153.6112.21A0.0031 | P53: DEFESA NACIONAL | Q53: DEFESA TERRESTRE | R53: DEFESA NACIONAL | S53: APRESTAMENTO DAS FORÇAS - MANUTENÇÃO DA PRONTIDÃO E DA CAPACIDADE OPERATIVA | T53: NO ESTADO DE MINAS GERAIS | U53: MG | V53: MINAS GERAIS | W53: F | X53: 4 | Y53: 90 | Z53: 0 | AA53: 6 | AB53: 1000 | AC53: 150000 | AD53: PROPORCIONAR MELHORES CONDIÇÕES PARA A REALIZAÇÃO DAS REFEIÇÕES, AUMENTANDO O BEM-ESTAR E A PRODUTIVIDADE DOS MILITARES. | AE53: 4º D Sup | AF53: Mobiliário para refeitórios
A54: 13 | B54: DEFESA | C54: 27680004 | D54: INDIVIDUAL | E54: INCLUSÃO - APROPRIAÇÃO | F54: 2768 | G54: WELITON PRADO | H54: DEPUTADO FEDERAL | I54: MG | J54: PSD | K54: 52000 | L54: MINISTÉRIO DA DEFESA | M54: 52121 | N54: COMANDO DO EXÉRCITO | O54: 05.153.6112.21A0.3166 | P54: DEFESA NACIONAL | Q54: DEFESA TERRESTRE | R54: DEFESA NACIONAL | S54: APRESTAMENTO DAS FORÇAS - MANUTENÇÃO DA PRONTIDÃO E DA CAPACIDADE OPERATIVA | T54: NO MUNICÍPIO DE UBERLÂNDIA - MG | U54: MG | V54: UBERLÂNDIA | W54: F | X54: 4 | Y54: 90 | Z54: 0 | AA54: 6 | AB54: 1000 | AC54: 850000 | AD54: A PRESENTE EMENDA VISA GARANTIR INVESTIMENTOS PARA O 36º BATALHÃO DE INFANTARIA MECANIZADO (36º BI MEC) DO EXÉRCITO BRASILEIRO, EM UBERLÂNDIA MG, QUE NECESSITA APRIMORAR SUAS ESTRUTURAS E MODERNIZAR A ÁREA OPERACIONAL , AMPLIANDO A CAPACIDADE OPERATIVA COM A AQUISIÇÃO DE EQUIPAMENTOS, COMO VIATURA TIPO AMBULÂNCIA OPERACIONAL, PARA APOIAR AS ATIVIDADES E ATENDER O PLANO DE COMBATE A INCÊNDIO, E INSTRUMENTOS MUSICAIS PARA A BANDA DE MÚSICA DO BATALHÃO QUE SEMPRE ESTÁ PRESENTE NAS COMUNIDADES, NOS EVENTOS SOCIAIS E CÍVICO MILITARES DA CIDADE. | AE54: 36º BI Mec | AF54: Ambulância operacional e instrumentos musicais
A55: 13 | B55: DEFESA | C55: 28130005 | D55: INDIVIDUAL | E55: INCLUSÃO - APROPRIAÇÃO | F55: 2813 | G55: PAULO FREIRE COSTA | H55: DEPUTADO FEDERAL | I55: SP | J55: PL | K55: 52000 | L55: MINISTÉRIO DA DEFESA | M55: 52111 | N55: COMANDO DA AERONÁUTICA | O55: 05.151.6112.219D.0035 | P55: DEFESA NACIONAL | Q55: DEFESA AÉREA | R55: DEFESA NACIONAL | S55: ADEQUAÇÃO DE ATIVOS DE INFRAESTRUTURA DAS ORGANIZAÇÕES MILITARES | T55: NO ESTADO DE SÃO PAULO | U55: SP | V55: SÃO PAULO | W55: F | X55: 4 | Y55: 99 | Z55: 0 | AA55: 6 | AB55: 1000 | AC55: 200000 | AD55: ATENDER A UMA READEQUAÇÃO NO COMANDO DA AERONAUTICA EM MUNICIPIOS DO ESTADO DE SÃO PAULO
A56: 13 | B56: DEFESA | C56: 28580007 | D56: INDIVIDUAL | E56: INCLUSÃO - APROPRIAÇÃO | F56: 2858 | G56: ALCEU MOREIRA | H56: DEPUTADO FEDERAL | I56: RS | J56: MDB | K56: 52000 | L56: MINISTÉRIO DA DEFESA | M56: 52131 | N56: COMANDO DA MARINHA | O56: 05.152.6112.219D.0043 | P56: DEFESA NACIONAL | Q56: DEFESA NAVAL | R56: DEFESA NACIONAL | S56: ADEQUAÇÃO DE ATIVOS DE INFRAESTRUTURA DAS ORGANIZAÇÕES MILITARES | T56: NO ESTADO DO RIO GRANDE DO SUL | U56: RS | V56: RIO GRANDE DO SUL | W56: F | X56: 4 | Y56: 90 | Z56: 0 | AA56: 6 | AB56: 1000 | AC56: 110000 | AD56: FORTALECIMENTO DE INFRAESTRUTURA EM ÁREA DA MARINHA NO ESTADO DO RIO GRANDE DO SUL.
A57: 13 | B57: DEFESA | C57: 28580009 | D57: INDIVIDUAL | E57: ACRÉSCIMO - APROPRIAÇÃO | F57: 2858 | G57: ALCEU MOREIRA | H57: DEPUTADO FEDERAL | I57: RS | J57: MDB | K57: 52000 | L57: MINISTÉRIO DA DEFESA | M57: 52931 | N57: FUNDO NAVAL | O57: 05.122.0032.2000.0001 | P57: DEFESA NACIONAL | Q57: ADMINISTRAÇÃO GERAL | R57: PROGRAMA DE GESTÃO E MANUTENÇÃO DO PODER EXECUTIVO | S57: ADMINISTRAÇÃO DA UNIDADE | T57: NACIONAL | U57: NA | V57: NACIONAL | W57: F | X57: 4 | Y57: 90 | Z57: 0 | AA57: 6 | AB57: 1000 | AC57: 80000 | AD57: EMENDA VISA QUALIFICAÇÃO E COMPRA DE EQUIPAMENTOS PARA ATENDER A MARINHA NO LITORAL NORTE DO ESTADO DO RIO GRANDE DO SUL.
A58: 13 | B58: DEFESA | C58: 29350001 | D58: INDIVIDUAL | E58: ACRÉSCIMO - APROPRIAÇÃO | F58: 2935 | G58: MAGDA MOFATTO | H58: DEPUTADO FEDERAL | I58: GO | J58: PL | K58: 52000 | L58: MINISTÉRIO DA DEFESA | M58: 52221 | N58: INDÚSTRIA DE MATERIAL BÉLICO DO BRASIL - IMBEL | O58: 05.122.0032.2000.0001 | P58: DEFESA NACIONAL | Q58: ADMINISTRAÇÃO GERAL | R58: PROGRAMA DE GESTÃO E MANUTENÇÃO DO PODER EXECUTIVO | S58: ADMINISTRAÇÃO DA UNIDADE | T58: NACIONAL | U58: NA | V58: NACIONAL | W58: F | X58: 4 | Y58: 90 | Z58: 0 | AA58: 6 | AB58: 1000 | AC58: 600000 | AD58: CRIAR UM CENTRO DE TREINAMENTO MULTIDISCIPLINAR NA FÁBRICA PARA OS 700 FUNCIONÁRIOS, COM TODA INFRAESTRUTURA NECESSÁRIA PARA REUNIÕES, VIDEOCONFERÊNCIAS, CAPACITAÇÃO E TREINAMENTO, ALÉM DE ATENDER A COMUNIDADE LOCAL E FAMILIARES DOS COLABORADORES | AE58: IMBEL | AF58: Readequação e reforma da Seção de Treinamento.
A59: 13 | B59: DEFESA | C59: 29350006 | D59: INDIVIDUAL | E59: INCLUSÃO - APROPRIAÇÃO | F59: 2935 | G59: MAGDA MOFATTO | H59: DEPUTADO FEDERAL | I59: GO | J59: PL | K59: 52000 | L59: MINISTÉRIO DA DEFESA | M59: 52931 | N59: FUNDO NAVAL | O59: 05.125.6112.21BY.0001 | P59: DEFESA NACIONAL | Q59: NORMATIZAÇÃO E FISCALIZAÇÃO | R59: DEFESA NACIONAL | S59: FISCALIZAÇÃO DA NAVEGAÇÃO AQUAVIÁRIA | T59: NACIONAL | U59: NA | V59: NACIONAL | W59: F | X59: 4 | Y59: 99 | Z59: 0 | AA59: 6 | AB59: 1000 | AC59: 500000 | AD59: A CAPITANIA FLUVIAL DE BRASILIA (CFB), ORGANIZAÇÃO MILITAR DA MARINHA DO BRASIL, É RESPONSÁVEL PELA SEGURANÇA DA NAVEGAÇÃO E PREVENÇÃO DA POLUIÇÃO HÍDRICA NO DISTRITO FEDERAL E PARTE DE GOIÁS. COBRE DIVERSAS ÁREAS, COMO POR EXEMPLO O LAGO SERRA DA MESA (1.784KM*). LAGOS CORUMBÁ III E IV (250KM' JUNTOS) E O LAGO PARANOA (48KM'), ALÉM DE OUTRAS VIAS FLUVIAIS, ATENDENDO 46 MUNICÍPIOS DE GOIÁS E O DISTRITO FEDERAL._x000D_ A CFB BUSCA PRIORIZAR A FISCALIZAÇÃO VISANDO O TURISMO SEGURO, AS AÇÕES DE CONSCIENTIZAÇÃO SOBRE SEGURANÇA AQUAVIÁRIA, A SALVAGUARDA DA VIDA HUMANA E A PREVENÇÃO DA POLUIÇÃO HÍDRICA E NA FORMAÇÃO DE NOVOS AQUAVIÁRIOS EM CIDADES DISTANTES DOS CENTROS URBANOS._x000D_ NO INTUITO DO CUMPRIMENTO DE SUA MISSÃO, CONSIDERANDO AS DIFICULDADES ORÇAMENTÁRIAS VIGENTES, POR MEIO DESTA EMENDA PARLAMENTAR, NA AÇÃO 21BY - FISCALIZAÇÃO DA NAVEGAÇÃO AQUAVIÁRIA NA GND 4, NO EXERCÍCIO DE 2026. ESSES RECURSOS SERÃO DE SUMA IMPORTÂNCIA PARA FORTALECER E EXPANDIR A CAPACIDADE DE ATENDIMENTO DA CFB AOS CIDADÃOS, EM GOIÁS.
A60: 13 | B60: DEFESA | C60: 29690009 | D60: INDIVIDUAL | E60: INCLUSÃO - APROPRIAÇÃO | F60: 2969 | G60: WILDER MORAIS | H60: SENADOR | I60: GO | J60: PL | K60: 52000 | L60: MINISTÉRIO DA DEFESA | M60: 52931 | N60: FUNDO NAVAL | O60: 05.125.6112.21BY.0001 | P60: DEFESA NACIONAL | Q60: NORMATIZAÇÃO E FISCALIZAÇÃO | R60: DEFESA NACIONAL | S60: FISCALIZAÇÃO DA NAVEGAÇÃO AQUAVIÁRIA | T60: NACIONAL | U60: NA | V60: NACIONAL | W60: F | X60: 4 | Y60: 90 | Z60: 0 | AA60: 6 | AB60: 1000 | AC60: 700000 | AD60: A PRESENTE EMENDA VISA A EXECUÇÃO DE ATIVIDADES VOLTADAS À SEGURANÇA DA NAVEGAÇÃO AQUAVIÁRIA NAS ÁGUAS JURISDICIONAIS BRASILEIRAS (AJB), ATINENTES A FISCALIZAÇÃO, A VISTORIA E A INSPEÇÃO, ABRANGENDO: A) REALIZAÇÃO DE AÇÕES DE INSPEÇÃO NAVAL E VISTORIAS; FISCALIZAÇÃO DE EMBARCAÇÕES CIVIS; OPERAÇÃO E MANUTENÇÃO DA REDE DE COMUNICAÇÕES E CONTROLE DO TRÁFEGO MARÍTIMO; DESENVOLVIMENTO, ATUALIZAÇÃO, MANUTENÇÃO E OPERAÇÃO DO SISTEMA DE MONITORAMENTO DAS ATIVIDADES DO PETRÓLEO (SIMAP) NAS BACIAS PETROLÍFERAS BRASILEIRAS; E B) CONTRATAÇÃO DE SERVIÇOS E AQUISIÇÃO DE MATERIAIS, EQUIPAMENTOS, SISTEMAS, EMBARCAÇÕES, VIATURAS, INSTALAÇÕES E OUTROS MEIOS PARA EMPREGO NAS ATIVIDADES ELENCADAS, INCLUINDO A CAPACITAÇÃO TÉCNICA DE PESSOAL, A MANUTENÇÃO E O SUPORTE LOGÍSTICO CORRELATOS, EM LAGOS E RIOS DA REGIÃO CENTRO-OESTE.
A61: 13 | B61: DEFESA | C61: 29730022 | D61: INDIVIDUAL | E61: INCLUSÃO - APROPRIAÇÃO | F61: 2973 | G61: PAULÃO | H61: DEPUTADO FEDERAL | I61: AL | J61: PT | K61: 52000 | L61: MINISTÉRIO DA DEFESA | M61: 52131 | N61: COMANDO DA MARINHA | O61: 05.152.6112.219D.0001 | P61: DEFESA NACIONAL | Q61: DEFESA NAVAL | R61: DEFESA NACIONAL | S61: ADEQUAÇÃO DE ATIVOS DE INFRAESTRUTURA DAS ORGANIZAÇÕES MILITARES | T61: NACIONAL | U61: NA | V61: NACIONAL | W61: F | X61: 3 | Y61: 99 | Z61: 0 | AA61: 6 | AB61: 1000 | AC61: 500000 | AD61: A AÇÃO VISA ADEQUAR E MODERNIZAR A INFRAESTRUTURA DA CAPITANIA DOS PORTOS, GARANTINDO MELHORES CONDIÇÕES OPERACIONAIS, MAIOR SEGURANÇA E EFICIÊNCIA NAS ATIVIDADES DE FISCALIZAÇÃO, APOIO NÁUTICO E SERVIÇOS À POPULAÇÃO. O INVESTIMENTO CONTRIBUI PARA FORTALECER A ATUAÇÃO INSTITUCIONAL E APRIMORAR A GESTÃO DAS OPERAÇÕES MARÍTIMAS.
A62: 13 | B62: DEFESA | C62: 30420016 | D62: INDIVIDUAL | E62: INCLUSÃO - APROPRIAÇÃO | F62: 3042 | G62: ALTINEU CÔRTES | H62: DEPUTADO FEDERAL | I62: RJ | J62: PL | K62: 52000 | L62: MINISTÉRIO DA DEFESA | M62: 52131 | N62: COMANDO DA MARINHA | O62: 05.152.6112.219D.0001 | P62: DEFESA NACIONAL | Q62: DEFESA NAVAL | R62: DEFESA NACIONAL | S62: ADEQUAÇÃO DE ATIVOS DE INFRAESTRUTURA DAS ORGANIZAÇÕES MILITARES | T62: NACIONAL | U62: NA | V62: NACIONAL | W62: F | X62: 3 | Y62: 90 | Z62: 0 | AA62: 6 | AB62: 1000 | AC62: 360000 | AD62: A PROPOSTA VISA PROPORCIONAR MELHORES CONDIÇÕES DE CONFORTO, HIGIENE E DIGNIDADE AO EFETIVO DE PESSOAL DO BATALHÃO DE ARTILHARIA DE_x000D_ FUZILEIROS NAVAIS, POR MEIO DA REESTRUTURAÇÃO DE BANHEIROS, VESTIÁRIOS E ALOJAMENTOS UTILIZADOS PELOS MILITARES. DIANTE DA CRESCENTE_x000D_ PARTICIPAÇÃO DE MULHERES NA TROPA, DESTACA-SE A NECESSIDADE DE ADEQUAÇÃO DOS ESPAÇOS FÍSICOS ÀS DEMANDAS DO PÚBLICO FEMININO,_x000D_ ASSEGURANDO PRIVACIDADE, SALUBRIDADE E RESPEITO ÀS CONDIÇÕES DE GÊNERO._x000D_ A INICIATIVA CONTRIBUIRÁ PARA O BEM-ESTAR DA TROPA E A VALORIZAÇÃO DOS MILITARES QUE HABITAM OU UTILIZAM ESSAS DEPENDÊNCIAS, BEM COMO_x000D_ PARA A CONTINUIDADE DA POLÍTICA DE INCLUSÃO FEMININA NA FORÇA
A63: 13 | B63: DEFESA | C63: 30420016 | D63: INDIVIDUAL | E63: INCLUSÃO - APROPRIAÇÃO | F63: 3042 | G63: ALTINEU CÔRTES | H63: DEPUTADO FEDERAL | I63: RJ | J63: PL | K63: 52000 | L63: MINISTÉRIO DA DEFESA | M63: 52131 | N63: COMANDO DA MARINHA | O63: 05.152.6112.219D.0001 | P63: DEFESA NACIONAL | Q63: DEFESA NAVAL | R63: DEFESA NACIONAL | S63: ADEQUAÇÃO DE ATIVOS DE INFRAESTRUTURA DAS ORGANIZAÇÕES MILITARES | T63: NACIONAL | U63: NA | V63: NACIONAL | W63: F | X63: 4 | Y63: 90 | Z63: 0 | AA63: 6 | AB63: 1000 | AC63: 240000 | AD63: A PROPOSTA VISA PROPORCIONAR MELHORES CONDIÇÕES DE CONFORTO, HIGIENE E DIGNIDADE AO EFETIVO DE PESSOAL DO BATALHÃO DE ARTILHARIA DE_x000D_ FUZILEIROS NAVAIS, POR MEIO DA REESTRUTURAÇÃO DE BANHEIROS, VESTIÁRIOS E ALOJAMENTOS UTILIZADOS PELOS MILITARES. DIANTE DA CRESCENTE_x000D_ PARTICIPAÇÃO DE MULHERES NA TROPA, DESTACA-SE A NECESSIDADE DE ADEQUAÇÃO DOS ESPAÇOS FÍSICOS ÀS DEMANDAS DO PÚBLICO FEMININO,_x000D_ ASSEGURANDO PRIVACIDADE, SALUBRIDADE E RESPEITO ÀS CONDIÇÕES DE GÊNERO._x000D_ A INICIATIVA CONTRIBUIRÁ PARA O BEM-ESTAR DA TROPA E A VALORIZAÇÃO DOS MILITARES QUE HABITAM OU UTILIZAM ESSAS DEPENDÊNCIAS, BEM COMO_x000D_ PARA A CONTINUIDADE DA POLÍTICA DE INCLUSÃO FEMININA NA FORÇA
A64: 13 | B64: DEFESA | C64: 30450008 | D64: INDIVIDUAL | E64: INCLUSÃO - APROPRIAÇÃO | F64: 3045 | G64: ANDRÉ ABDON | H64: DEPUTADO FEDERAL | I64: AP | J64: PP | K64: 52000 | L64: MINISTÉRIO DA DEFESA | M64: 52121 | N64: COMANDO DO EXÉRCITO | O64: 05.153.6112.21A0.0016 | P64: DEFESA NACIONAL | Q64: DEFESA TERRESTRE | R64: DEFESA NACIONAL | S64: APRESTAMENTO DAS FORÇAS - MANUTENÇÃO DA PRONTIDÃO E DA CAPACIDADE OPERATIVA | T64: NO ESTADO DO AMAPÁ | U64: AP | V64: AMAPÁ | W64: F | X64: 4 | Y64: 90 | Z64: 0 | AA64: 6 | AB64: 1000 | AC64: 200000 | AD64: TEM A PRESENTE EMENDA, O OBJETIVO DE DOTAR O COMANDO DE FRONTEIRA AMAPÁ/34º BATALHÃO DE INFANTARIA DE SELVA, COM INVESTIMENTOS PARA A RENOVAÇÃO DE MOBILIA, CLIMATIZAÇÃO DE ALOJAMENTOS, ADQUIRIR FORNOS E FOGÕES INDUSTRIAIS E MATERIAIS DE USO PERMANENTE PARA O REFEITÓRIO, PROPORCIONANDO MELHORES CONDIÇÕES PARA REALIZAÇÃO DE AÇÕES CÍVICO-SOCIAIS E DE CONFORTO PARA A TROPA. | AE64: 34º BIS | AF64: Material permanente para alojamentos e ranchos
A65: 13 | B65: DEFESA | C65: 30450010 | D65: INDIVIDUAL | E65: INCLUSÃO - APROPRIAÇÃO | F65: 3045 | G65: ANDRÉ ABDON | H65: DEPUTADO FEDERAL | I65: AP | J65: PP | K65: 52000 | L65: MINISTÉRIO DA DEFESA | M65: 52931 | N65: FUNDO NAVAL | O65: 05.125.6112.21BY.0016 | P65: DEFESA NACIONAL | Q65: NORMATIZAÇÃO E FISCALIZAÇÃO | R65: DEFESA NACIONAL | S65: FISCALIZAÇÃO DA NAVEGAÇÃO AQUAVIÁRIA | T65: NO ESTADO DO AMAPÁ | U65: AP | V65: AMAPÁ | W65: F | X65: 4 | Y65: 90 | Z65: 0 | AA65: 6 | AB65: 1000 | AC65: 300000 | AD65: A PRESENTE EMENDA, TEM POR OBJETIVO DOTAR O ESTADO DO AMAPÁ, ATRAVÉS DA SUA CAPITANIA DOS PORTOS, COM INVESTIMENTOS PARA A MANUTENÇÃO DOS MEIOS - VIATURAS E EMBARCAÇÕES EMPREGADOS NAS AÇÕES DE FISCALIZAÇÃO DO TRÁFEGO AQUAVIÁRIO E NAS AULAS PRÁTICAS DOS CURSOS DE EPM. VALE RESSALTAR QUE O CPAP, DESEMPENHA A RELEVANTE FUNÇÃO DE AGENTE DA AUTORIDADE MARÍTIMA, SENDO RESPONSÁVEL POR ASSEGURAR A SALVAGUARDA DA VIDA HUMANA E A SEGURANÇA DA NAVEGAÇÃO EM MAR ABERTO E NAS HIDROVIAS INTERIORES. PREVENIR A POLUIÇÃO AMBIENTAL PROVENIENTE DE EMBARCAÇÕES E COMBATER O ESCALPELAMENTO; BEM COMO MINISTRAR CURSOS DE ENSINO PROFISSIONAL MARÍTIMO (EPM). RESSALTA-SE QUE SUA ÁREA DE JURISDIÇÃO COMPREENDE OS 16 MUNICÍPIOS DO ESTADO DO AMAPÁ, ABRANGENDO MAIS DE 142 MIL KM², ENTRE REGIÕES MARÍTIMAS E FLUVIAIS DE GRANDE IMPORTÂNCIA SOCIOECONÔMICA.
A66: 13 | B66: DEFESA | C66: 30510008 | D66: INDIVIDUAL | E66: ACRÉSCIMO - APROPRIAÇÃO | F66: 3051 | G66: BACELAR | H66: DEPUTADO FEDERAL | I66: BA | J66: PV | K66: 52000 | L66: MINISTÉRIO DA DEFESA | M66: 52121 | N66: COMANDO DO EXÉRCITO | O66: 05.122.0032.2000.0001 | P66: DEFESA NACIONAL | Q66: ADMINISTRAÇÃO GERAL | R66: PROGRAMA DE GESTÃO E MANUTENÇÃO DO PODER EXECUTIVO | S66: ADMINISTRAÇÃO DA UNIDADE | T66: NACIONAL | U66: NA | V66: NACIONAL | W66: F | X66: 3 | Y66: 90 | Z66: 0 | AA66: 6 | AB66: 1000 | AC66: 200000 | AD66: BENEFICIÁRIO PARA LANÇAMENTO NO SIOP - CNPJ: 00.394.452/0001-03 REALIZAR A RESTAURAÇÃO DO ACERVO HISTÓRICO DO SALÃO DE HONRA E ÁREAS CONTÍGUAS AO QUARTEL-GENERAL DA 6ª REGIÃO MILITAR, BEM COMO DO ESPAÇO CULTURAL QUE RECEBE INÚMERAS VISITAS. COMANDO DA 6ª REGIÃO MILITAR (CMDO 6ª RM), NO MUNICÍPIO DE SALVADOR - BA | AE66: Cmdo 6ª RM | AF66: Restauração de obras de arte e peças de valor histórico
A67: 13 | B67: DEFESA | C67: 30520009 | D67: INDIVIDUAL | E67: INCLUSÃO - APROPRIAÇÃO | F67: 3052 | G67: BALEIA ROSSI | H67: DEPUTADO FEDERAL | I67: SP | J67: MDB | K67: 52000 | L67: MINISTÉRIO DA DEFESA | M67: 52911 | N67: FUNDO AERONÁUTICO | O67: 05.363.6112.21GQ.0035 | P67: DEFESA NACIONAL | Q67: ENSINO PROFISSIONAL | R67: DEFESA NACIONAL | S67: FUNCIONAMENTO DOS ESTABELECIMENTOS DE ENSINO SUPERIOR MILITARES DO MINISTÉRIO DA DEFESA | T67: NO ESTADO DE SÃO PAULO | U67: SP | V67: SÃO PAULO | W67: F | X67: 4 | Y67: 90 | Z67: 0 | AA67: 6 | AB67: 1000 | AC67: 500000 | AD67: CNPJ PARA LANÇAMENTO NO SIOP: 00.394.429/0001-00 - COMANDO DA AERONÁUTICA_x000D_ OM BENEFICIADA: ACADEMIA DA FORÇA AÉREA_x000D_ OBJETO RESUMIDO: MODERNIZAÇÃO E ATUALIZAÇÃO DAS INSTALAÇÕES DA BIBLIOTECA DA AFA._x000D_ JUSTIFICATIVA:_x000D_ A FORÇA AÉREA BRASILEIRA (FAB), COMO INSTITUIÇÃO DE ESTADO, ATUA, ININTERRUPTAMENTE, NA DEFESA DA PÁTRIA, NA MANUTENÇÃO DA SOBERANIA DO NOSSO ESPAÇO AÉREO, NA PROTEÇÃO DE NOSSAS FRONTEIRAS E NA INTEGRAÇÃO DO TERRITÓRIO NACIONAL._x000D_ ADEMAIS, SUBSIDIARIAMENTE, A FAB CUMPRE MISSÕES HUMANITÁRIAS E DE REPATRIAÇÃO DE NACIONAIS, DE TRANSPORTE DE ÓRGÃOS E TECIDOS, BEM COMO CONTRIBUI COM O DESENVOLVIMENTO TECNOLÓGICO, GERANDO EMPREGOS E RIQUEZAS AO PAÍS._x000D_ PELO EXPOSTO, PARA CONTRIBUIR COM A FAB NO CUMPRIMENTO DE SUA MISSÃO CONSTITUCIONAL EM BENEFÍCIO DA SOCIEDADE BRASILEIRA, É NECESSÁRIO O APOIO AOS PROJETOS E ATIVIDADES SUPRAMENCIONADOS COM O APORTE DE RECURSOS DE EMENDAS PARLAMENTARES NA LEI ORÇAMENTÁRIA ANUAL (LOA) DE 2026.
A68: 13 | B68: DEFESA | C68: 30880002 | D68: INDIVIDUAL | E68: ACRÉSCIMO - APROPRIAÇÃO | F68: 3088 | G68: EDUARDO BOLSONARO | H68: DEPUTADO FEDERAL | I68: SP | J68: PL | K68: 52000 | L68: MINISTÉRIO DA DEFESA | M68: 52931 | N68: FUNDO NAVAL | O68: 05.152.6112.21A0.0001 | P68: DEFESA NACIONAL | Q68: DEFESA NAVAL | R68: DEFESA NACIONAL | S68: APRESTAMENTO DAS FORÇAS - MANUTENÇÃO DA PRONTIDÃO E DA CAPACIDADE OPERATIVA | T68: NACIONAL | U68: NA | V68: NACIONAL | W68: F | X68: 4 | Y68: 90 | Z68: 0 | AA68: 6 | AB68: 1000 | AC68: 300000 | AD68: COMANDO DO GRUPAMENTO DE PATRULHA NAVAL DO SUL-SUDESTE (COMGPTPATNAVSSE)_x000D_ CNPJ: 00.394.502/0521-01_x000D_ _x000D_ PROPOSTA VISA AMPLIAR A CAPACIDADE OPERACIONAL DO COMANDO DO GRUPAMENTO DE PATRULHA NAVAL DO SUL-SUDESTE, NA AQUISIÇÃO DE MATERIAL E MEIOS NECESSÁRIOS À CONDUÇÃO DAS ATIVIDADES EM PROVEITO DA SOCIEDADE, PERMITINDO O MONITORAMENTO E ATENDIMENTO DAS DEMANDAS DA POPULAÇÃO, EM ESPECIAL NO APOIO AO COMBATE A CRIMES TRANSFRONTEIRIÇOS NA ÁREA DO PORTO DE SANTOS, FORTALECENDO SIGNIFICATIVAMENTE A CAPACIDADE EM REALIZAR OPERAÇÕES NAVAIS, COM ESPECIAL ÊNFASE NAS OPERAÇÕES DE SOCORRO E SALVAMENTO; PATRULHA NAVAL; OPERAÇÕES DE DEFESA DE PORTO OU ÁREA MARÍTIMA RESTRITA, AÍ INCLUÍDOS TERMINAIS MARÍTIMOS E PLATAFORMAS DE EXPLORAÇÃO/EXPLOTAÇÃO; E FISCALIZAÇÃO DO CUMPRIMENTO DAS LEIS NAS ÁGUAS JURISDICIONAIS BRASILEIRAS, A FIM DE CONTRIBUIR PARA O CUMPRIMENTO DA MISSÃO DO COMANDO DO 8º DISTRITO NAVAL. FAZ-SE MISTER MENCIONAR A IMPORTÂNCIA ECONÔMICA DA REGIÃO DO PORTO DE SANTOS, RESPONSÁVEL PELA MOVIMENTAÇÃO DE APROXIMADAMENTE 25% DO COMÉRCIO EXTERIOR BRASILEIRO; DO CONSEQUENTE INCREMENTO DAS ATIVIDADES MARÍTIMAS; E DA PROXIMIDADE COM AS ATIVIDADES DA INDÚSTRIA DO PETRÓLEO NA BACIA DE SANTOS, AS QUAIS TORNAM AINDA MAIS RELEVANTE A ATUAÇÃO DESTE COMANDO, NA REGIÃO.
A69: 13 | B69: DEFESA | C69: 31600005 | D69: INDIVIDUAL | E69: INCLUSÃO - APROPRIAÇÃO | F69: 3160 | G69: CELSO RUSSOMANNO | H69: DEPUTADO FEDERAL | I69: SP | J69: REPUBLICANOS | K69: 52000 | L69: MINISTÉRIO DA DEFESA | M69: 52111 | N69: COMANDO DA AERONÁUTICA | O69: 05.301.0032.2E74.0035 | P69: DEFESA NACIONAL | Q69: ATENÇÃO BÁSICA | R69: PROGRAMA DE GESTÃO E MANUTENÇÃO DO PODER EXECUTIVO | S69: ESTRUTURAÇÃO E MODERNIZAÇÃO DE UNIDADES DE SAÚDE DAS FORÇAS ARMADAS | T69: NO ESTADO DE SÃO PAULO | U69: SP | V69: SÃO PAULO | W69: S | X69: 3 | Y69: 90 | Z69: 0 | AA69: 6 | AB69: 1000 | AC69: 500000 | AD69: ESTRUTURAÇÃO E MODERNIZAÇÃO DE UNIDADES DE SAÚDE DAS FORÇAS ARMARDAS.
A70: 13 | B70: DEFESA | C70: 31600015 | D70: INDIVIDUAL | E70: INCLUSÃO - APROPRIAÇÃO | F70: 3160 | G70: CELSO RUSSOMANNO | H70: DEPUTADO FEDERAL | I70: SP | J70: REPUBLICANOS | K70: 52000 | L70: MINISTÉRIO DA DEFESA | M70: 52121 | N70: COMANDO DO EXÉRCITO | O70: 05.153.6112.21A0.0035 | P70: DEFESA NACIONAL | Q70: DEFESA TERRESTRE | R70: DEFESA NACIONAL | S70: APRESTAMENTO DAS FORÇAS - MANUTENÇÃO DA PRONTIDÃO E DA CAPACIDADE OPERATIVA | T70: NO ESTADO DE SÃO PAULO | U70: SP | V70: SÃO PAULO | W70: F | X70: 4 | Y70: 90 | Z70: 0 | AA70: 6 | AB70: 1000 | AC70: 300000 | AD70: MELHORAR A ACOMODAÇÃO DE PESSOAL NOS REFEITÓRIOS DO CENTRO DE PREPARAÇÃO DE OFICIAIS DA RESERVA E COLÉGIO MILITAR DE SÃO PAULO, NA_x000D_ CIDADE DE SÃO PAULO/SP. | AE70: CPOR/SP | AF70: Material permanente para o refeitório
A71: 13 | B71: DEFESA | C71: 31600016 | D71: INDIVIDUAL | E71: INCLUSÃO - APROPRIAÇÃO | F71: 3160 | G71: CELSO RUSSOMANNO | H71: DEPUTADO FEDERAL | I71: SP | J71: REPUBLICANOS | K71: 52000 | L71: MINISTÉRIO DA DEFESA | M71: 52911 | N71: FUNDO AERONÁUTICO | O71: 05.363.6112.21GQ.0035 | P71: DEFESA NACIONAL | Q71: ENSINO PROFISSIONAL | R71: DEFESA NACIONAL | S71: FUNCIONAMENTO DOS ESTABELECIMENTOS DE ENSINO SUPERIOR MILITARES DO MINISTÉRIO DA DEFESA | T71: NO ESTADO DE SÃO PAULO | U71: SP | V71: SÃO PAULO | W71: F | X71: 4 | Y71: 90 | Z71: 0 | AA71: 6 | AB71: 1000 | AC71: 500000 | AD71: CNPJ PARA LANÇAMENTO NO SIOP: 00.394.429/0001-00 - COMANDO DA AERONÁUTICA_x000D_ OM BENEFICIADA: ACADEMIA DA FORÇA AÉREA_x000D_ OBJETO RESUMIDO: MODERNIZAÇÃO DO LABORATÓRIO DE INFORMÁTICA DA DIVISÃO DE ENSINO._x000D_ JUSTIFICATIVA:_x000D_ A FORÇA AÉREA BRASILEIRA (FAB), COMO INSTITUIÇÃO DE ESTADO, ATUA, ININTERRUPTAMENTE, NA DEFESA DA PÁTRIA, NA MANUTENÇÃO DA SOBERANIA DO NOSSO ESPAÇO AÉREO, NA PROTEÇÃO DE NOSSAS FRONTEIRAS E NA INTEGRAÇÃO DO TERRITÓRIO NACIONAL._x000D_ ADEMAIS, SUBSIDIARIAMENTE, A FAB CUMPRE MISSÕES HUMANITÁRIAS E DE REPATRIAÇÃO DE NACIONAIS, DE TRANSPORTE DE ÓRGÃOS E TECIDOS, BEM COMO CONTRIBUI COM O DESENVOLVIMENTO TECNOLÓGICO, GERANDO EMPREGOS E RIQUEZAS AO PAÍS._x000D_ PELO EXPOSTO, PARA CONTRIBUIR COM A FAB NO CUMPRIMENTO DE SUA MISSÃO CONSTITUCIONAL EM BENEFÍCIO DA SOCIEDADE BRASILEIRA, É NECESSÁRIO O APOIO AOS PROJETOS E ATIVIDADES SUPRAMENCIONADOS COM O APORTE DE RECURSOS DE EMENDAS PARLAMENTARES NA LEI ORÇAMENTÁRIA ANUAL (LOA) DE 2026.
A72: 13 | B72: DEFESA | C72: 32390007 | D72: INDIVIDUAL | E72: ACRÉSCIMO - APROPRIAÇÃO | F72: 3239 | G72: JOÃO LEÃO | H72: DEPUTADO FEDERAL | I72: BA | J72: PP | K72: 52000 | L72: MINISTÉRIO DA DEFESA | M72: 52121 | N72: COMANDO DO EXÉRCITO | O72: 05.122.0032.2000.0001 | P72: DEFESA NACIONAL | Q72: ADMINISTRAÇÃO GERAL | R72: PROGRAMA DE GESTÃO E MANUTENÇÃO DO PODER EXECUTIVO | S72: ADMINISTRAÇÃO DA UNIDADE | T72: NACIONAL | U72: NA | V72: NACIONAL | W72: F | X72: 4 | Y72: 90 | Z72: 0 | AA72: 6 | AB72: 1000 | AC72: 500000 | AD72: BENEFICIÁRIO PARA LANÇAMENTO NO SIOP - CNPJ: 00.394.452/0001-03_x000D_ PERMITIR A REALIZAÇÃO DE DIVERSAS ATIVIDADES EM ALTURA, COMO MANUTENÇÃO E RECUPERAÇÃO DE INSTALAÇÕES, OBRAS E SERVIÇOS DE TELECOMUNICAÇÕES PELO COMANDO DA 6ª REGIÃO MILITAR, ALÉM DE APOIAR AS ENTIDADES CIVIS QUE DEMANDEM APOIO._x000D_ _x000D_ COMANDO DA 6ª REGIÃO MILITAR (CMDO 6ª RM), NO MUNICÍPIO DE SALVADOR - BA | AE72: Cmdo 6ª RM | AF72: Plataforma de trabalhos aéreos e outros materiais
A73: 13 | B73: DEFESA | C73: 32620010 | D73: INDIVIDUAL | E73: ACRÉSCIMO - APROPRIAÇÃO | F73: 3262 | G73: JOSÉ ROCHA | H73: DEPUTADO FEDERAL | I73: BA | J73: UNIÃO | K73: 52000 | L73: MINISTÉRIO DA DEFESA | M73: 52133 | N73: SECRETARIA DA COMISSÃO INTERMINISTERIAL PARA OS RECURSOS DO MAR | O73: 05.571.6113.2345.0001 | P73: DEFESA NACIONAL | Q73: DESENVOLVIMENTO CIENTÍFICO | R73: OCEANO, ZONA COSTEIRA E ANTÁRTICA | S73: APOIO LOGÍSTICO À PESQUISA CIENTÍFICA NA ANTÁRTICA | T73: NACIONAL | U73: NA | V73: NACIONAL | W73: F | X73: 3 | Y73: 90 | Z73: 0 | AA73: 6 | AB73: 1000 | AC73: 250000 | AD73: SECRETARIA DA COMISSÃO INTERMINISTERIAL PARA OS RECURSOS DO MAR - SECIRM_x000D_ CNPJ: 00.394.502/0165-71_x000D_ _x000D_ PROVER APOIO E SUPORTE LOGÍSTICO ÀS ATIVIDADES CIENTÍFICAS BRASILEIRAS REALIZADAS NO CONTINENTE ANTÁRTICO, PELO PROGRAMA ANTÁRTICO BRASILEIRO (PROANTAR), CORROBORANDO COM A PRESENÇA DO ESTADO BRASILEIRO NA REALIZAÇÃO DE RENOMADAS PESQUISAS A BORDO DOS NAVIOS DA MARINHA DO BRASIL, NAS ESTAÇÃO ANTÁRTICA COMANDANTE FERRAZ E ACAMPAMENTOS NO CONTINENTE, NA PRODUÇÃO DE CONHECIMENTOS, INCENTIVO À PESQUISA E FOMENTO À PARTICIPAÇÃO DE PESQUISADORES E INSTITUIÇÕES NACIONAIS NA COMPREENSÃO DOS FENÔMENOS QUE ALI OCORREM E QUE TENHAM REPERCUSSÃO GLOBAL E, PRINCIPALMENTE, NO PAÍS.
A74: 13 | B74: DEFESA | C74: 32620010 | D74: INDIVIDUAL | E74: ACRÉSCIMO - APROPRIAÇÃO | F74: 3262 | G74: JOSÉ ROCHA | H74: DEPUTADO FEDERAL | I74: BA | J74: UNIÃO | K74: 52000 | L74: MINISTÉRIO DA DEFESA | M74: 52133 | N74: SECRETARIA DA COMISSÃO INTERMINISTERIAL PARA OS RECURSOS DO MAR | O74: 05.571.6113.2345.0001 | P74: DEFESA NACIONAL | Q74: DESENVOLVIMENTO CIENTÍFICO | R74: OCEANO, ZONA COSTEIRA E ANTÁRTICA | S74: APOIO LOGÍSTICO À PESQUISA CIENTÍFICA NA ANTÁRTICA | T74: NACIONAL | U74: NA | V74: NACIONAL | W74: F | X74: 4 | Y74: 90 | Z74: 0 | AA74: 6 | AB74: 1000 | AC74: 50000 | AD74: SECRETARIA DA COMISSÃO INTERMINISTERIAL PARA OS RECURSOS DO MAR - SECIRM_x000D_ CNPJ: 00.394.502/0165-71_x000D_ _x000D_ PROVER APOIO E SUPORTE LOGÍSTICO ÀS ATIVIDADES CIENTÍFICAS BRASILEIRAS REALIZADAS NO CONTINENTE ANTÁRTICO, PELO PROGRAMA ANTÁRTICO BRASILEIRO (PROANTAR), CORROBORANDO COM A PRESENÇA DO ESTADO BRASILEIRO NA REALIZAÇÃO DE RENOMADAS PESQUISAS A BORDO DOS NAVIOS DA MARINHA DO BRASIL, NAS ESTAÇÃO ANTÁRTICA COMANDANTE FERRAZ E ACAMPAMENTOS NO CONTINENTE, NA PRODUÇÃO DE CONHECIMENTOS, INCENTIVO À PESQUISA E FOMENTO À PARTICIPAÇÃO DE PESQUISADORES E INSTITUIÇÕES NACIONAIS NA COMPREENSÃO DOS FENÔMENOS QUE ALI OCORREM E QUE TENHAM REPERCUSSÃO GLOBAL E, PRINCIPALMENTE, NO PAÍS.
A75: 13 | B75: DEFESA | C75: 32680001 | D75: INDIVIDUAL | E75: ACRÉSCIMO - APROPRIAÇÃO | F75: 3268 | G75: LAURA CARNEIRO | H75: DEPUTADO FEDERAL | I75: RJ | J75: PSD | K75: 52000 | L75: MINISTÉRIO DA DEFESA | M75: 52931 | N75: FUNDO NAVAL | O75: 05.122.0032.2000.0001 | P75: DEFESA NACIONAL | Q75: ADMINISTRAÇÃO GERAL | R75: PROGRAMA DE GESTÃO E MANUTENÇÃO DO PODER EXECUTIVO | S75: ADMINISTRAÇÃO DA UNIDADE | T75: NACIONAL | U75: NA | V75: NACIONAL | W75: F | X75: 4 | Y75: 90 | Z75: 0 | AA75: 6 | AB75: 1000 | AC75: 150000 | AD75: CENTRO DE EDUCAÇÃO FÍSICA ALMIRANTE ADALBERTO NUNES (CEFAN)_x000D_ CNPJ: 00.394.502/0129-08_x000D_ _x000D_ O CEFAN SEMPRE PROCUROU BUSCAR AMENIZAR A VULNERABILIDADE SOCIAL DAS CRIANÇAS, JOVENS, ADOLESCENTES E PESSOAS COM DEFICIÊNCIA, POR MEIO DA PRÁTICA DE ESPORTES E DA REALIZAÇÃO DE ATIVIDADES COGNITIVAS. ENTRETANTO, PARA ATENDER O AUMENTO SIGNIFICATIVO NA DEMANDA ANTERIORMENTE CITADA, APENAS A EXCELENTE CAPACITAÇÃO DOS PROFISSIONAIS QUE TRABALHAM COM O PROGRAMA FORÇAS NO ESPORTE (PROFESP) E O PROGRAMA PARALÍMPICO DA MARINHA (PARAPROLIM), NÃO ASSEGURARÁ A MANUTENÇÃO DAS CONDIÇÕES DAS ATIVIDADES REALIZADAS. SENDO ASSIM, A PRESENTE PROPOSTA DE EMENDA PARLAMENTAR TEM COMO OBJETIVO DESTINAR RECURSOS FINANCEIROS PARA O CEFAN, A FIM DE POSSIBILITAR A AQUISIÇÃO DE UNIFORMES E MATERIAIS ESPORTIVOS PARA O PROFESP, VISANDO ATENDER O AUMENTO DO INGRESSO DE PARTICIPANTES NO REFERIDO PROGRAMA SOCIAL, TENTANDO, DESTA FORMA, COLABORAR NA MELHORIA DA QUALIDADE DE VIDA DESSAS PESSOAS.
A76: 13 | B76: DEFESA | C76: 32680002 | D76: INDIVIDUAL | E76: ACRÉSCIMO - APROPRIAÇÃO | F76: 3268 | G76: LAURA CARNEIRO | H76: DEPUTADO FEDERAL | I76: RJ | J76: PSD | K76: 52000 | L76: MINISTÉRIO DA DEFESA | M76: 52931 | N76: FUNDO NAVAL | O76: 05.122.0032.2000.0001 | P76: DEFESA NACIONAL | Q76: ADMINISTRAÇÃO GERAL | R76: PROGRAMA DE GESTÃO E MANUTENÇÃO DO PODER EXECUTIVO | S76: ADMINISTRAÇÃO DA UNIDADE | T76: NACIONAL | U76: NA | V76: NACIONAL | W76: F | X76: 4 | Y76: 90 | Z76: 0 | AA76: 6 | AB76: 1000 | AC76: 150000 | AD76: CENTRO DE INSTRUÇÃO ALMIRANTE SYLVIO DE CAMARGO (CIASC)_x000D_ CNPJ: 00.394.502/0092-81_x000D_ _x000D_ O CIASC ESTÁ COMPLETANDO SETENTA ANOS EM 2025, E SUA ARQUITETURA É EXTREMAMENTE PECULIAR, BASEADA EM RECURSOS INSTRUCIONAIS DO ENSINO. NESSE CONTEXTO ENCONTRA-SE UM LAGO PROJETADO E DE BELEZA ÍMPAR, PORÉM NECESSITANDO DE REVITALIZAÇÃO E DE UM ESTUDO PAISAGÍSTICO, COM A SUBSEQUENTE IMPLEMENTAÇÃO. DURANTE TODO ESSE TRABALHO, OS JOVENS DO PROFESP TERÃO UM CONTATO DIRETO COM O TRABALHO DESENVOLVIDO, PERMITINDO UM APRENDIZADO SEM PRECEDENTES EM GESTÃO AMBIENTAL E PAISAGISMO.
A77: 13 | B77: DEFESA | C77: 32990001 | D77: INDIVIDUAL | E77: INCLUSÃO - APROPRIAÇÃO | F77: 3299 | G77: MENDONÇA FILHO | H77: DEPUTADO FEDERAL | I77: PE | J77: PL | K77: 52000 | L77: MINISTÉRIO DA DEFESA | M77: 52121 | N77: COMANDO DO EXÉRCITO | O77: 05.122.0032.2000.0026 | P77: DEFESA NACIONAL | Q77: ADMINISTRAÇÃO GERAL | R77: PROGRAMA DE GESTÃO E MANUTENÇÃO DO PODER EXECUTIVO | S77: ADMINISTRAÇÃO DA UNIDADE | T77: NO ESTADO DE PERNAMBUCO | U77: PE | V77: PERNAMBUCO | W77: F | X77: 4 | Y77: 90 | Z77: 0 | AA77: 6 | AB77: 1000 | AC77: 300000 | AD77: A REFERIDA EMENDA TEM COMO FINALIDADE DESTINAR RECURSOS PARA ADEQUAÇÃO DAS INSTALAÇÕES DO COMANDO MILITAR DO NORDESTE. | AE77: Cmdo CMNE | AF77: Adequação de instalações
A78: 13 | B78: DEFESA | C78: 33320008 | D78: INDIVIDUAL | E78: ACRÉSCIMO - APROPRIAÇÃO | F78: 3332 | G78: RICARDO BARROS | H78: DEPUTADO FEDERAL | I78: PR | J78: PP | K78: 52000 | L78: MINISTÉRIO DA DEFESA | M78: 52932 | N78: FUNDO DE DESENVOLVIMENTO DO ENSINO PROFISSIONAL MARÍTIMO | O78: 05.363.6111.2510.0001 | P78: DEFESA NACIONAL | Q78: ENSINO PROFISSIONAL | R78: COOPERAÇÃO DA DEFESA PARA O DESENVOLVIMENTO NACIONAL | S78: PRESTAÇÃO DE ENSINO PROFISSIONAL MARÍTIMO | T78: NACIONAL | U78: NA | V78: NACIONAL | W78: F | X78: 4 | Y78: 90 | Z78: 0 | AA78: 6 | AB78: 1000 | AC78: 600000 | AD78: DELEGACIA FLUVIAL DE GUAÍRA-PR - ESTRUTURAÇÃO PARA PRESTAÇÃO DE ENSINO PROFISSIONAL MARÍTIMO
A79: 13 | B79: DEFESA | C79: 35300012 | D79: INDIVIDUAL | E79: ACRÉSCIMO - APROPRIAÇÃO | F79: 3530 | G79: DAMIÃO FELICIANO | H79: DEPUTADO FEDERAL | I79: PB | J79: UNIÃO | K79: 52000 | L79: MINISTÉRIO DA DEFESA | M79: 52931 | N79: FUNDO NAVAL | O79: 05.122.0032.2000.0001 | P79: DEFESA NACIONAL | Q79: ADMINISTRAÇÃO GERAL | R79: PROGRAMA DE GESTÃO E MANUTENÇÃO DO PODER EXECUTIVO | S79: ADMINISTRAÇÃO DA UNIDADE | T79: NACIONAL | U79: NA | V79: NACIONAL | W79: F | X79: 3 | Y79: 90 | Z79: 0 | AA79: 6 | AB79: 1000 | AC79: 200000 | AD79: CAPITANIA DOS PORTOS DA PARAÍBA_x000D_ CNPJ: 00.394.502/0037-55_x000D_ _x000D_ A PRESENTE PROPOSTA DE EMENDA PARLAMENTAR TEM O PROPÓSITO DE GARANTIR A MANUTENÇÃO DAS INSTALAÇÕES, EM ESPECIAL A REFORMA DO TELHADO (SUBSTITUIÇÃO DE MADEIRAS INFESTADAS POR CUPINS, CALHAS DETERIORADAS E RETELHAMENTO COMPLETO) TENDO EM VISTAS OS POTENCIAIS RISCOS DE ACIDENTES FACE AOS DESGASTES ESTRUTURAIS (RACHADURAS E INFILTRAÇÕES COMPROMETEDORAS) AGRAVADAS PELAS FORTES CHUVAS RECENTEMENTE, QUE POR SE TRATAR DE UMA CONSTRUÇÃO SE ENCONTRA EM FUNCIONAMENTO DESDE O ANO DE 1939, NECESSITA DE UMA REFORMA URGENTE.
A80: 13 | B80: DEFESA | C80: 35390006 | D80: INDIVIDUAL | E80: INCLUSÃO - APROPRIAÇÃO | F80: 3539 | G80: LUCIANO BIVAR | H80: DEPUTADO FEDERAL | I80: PE | J80: MDB | K80: 52000 | L80: MINISTÉRIO DA DEFESA | M80: 52121 | N80: COMANDO DO EXÉRCITO | O80: 05.301.0032.2E74.1695 | P80: DEFESA NACIONAL | Q80: ATENÇÃO BÁSICA | R80: PROGRAMA DE GESTÃO E MANUTENÇÃO DO PODER EXECUTIVO | S80: ESTRUTURAÇÃO E MODERNIZAÇÃO DE UNIDADES DE SAÚDE DAS FORÇAS ARMADAS | T80: NO MUNICÍPIO DE RECIFE - PE | U80: PE | V80: RECIFE | W80: S | X80: 4 | Y80: 90 | Z80: 0 | AA80: 6 | AB80: 1000 | AC80: 300000 | AD80: BENEFICIÁRIO PARA LANÇAMENTO NO SIOP - CNPJ: 00.394.452/0001-03_x000D_ AUMENTAR AS CHANCES DE UM TRATAMENTO EFICAZ, AO TRANSMITIR IMAGENS EM TEMPO REAL COM ALTA DEFINIÇÃO, PERMITINDO DIAGNÓSTICOS MAIS PRECISOS E DETALHADOS, POR MEIO DE UM PROCEDIMENTO MENOS INVASIVO E COM MENOR RISCO DE TRAUMA._x000D_ _x000D_ HOSPITAL MILITAR DE ÁREA DE RECIFE (HMAR), NO MUNICÍPIO DE RECIFE - PE. | AE80: HMAR | AF80: Videogastroscópio
A81: 13 | B81: DEFESA | C81: 35390007 | D81: INDIVIDUAL | E81: INCLUSÃO - APROPRIAÇÃO | F81: 3539 | G81: LUCIANO BIVAR | H81: DEPUTADO FEDERAL | I81: PE | J81: MDB | K81: 52000 | L81: MINISTÉRIO DA DEFESA | M81: 52111 | N81: COMANDO DA AERONÁUTICA | O81: 05.301.0032.2E74.0026 | P81: DEFESA NACIONAL | Q81: ATENÇÃO BÁSICA | R81: PROGRAMA DE GESTÃO E MANUTENÇÃO DO PODER EXECUTIVO | S81: ESTRUTURAÇÃO E MODERNIZAÇÃO DE UNIDADES DE SAÚDE DAS FORÇAS ARMADAS | T81: NO ESTADO DE PERNAMBUCO | U81: PE | V81: PERNAMBUCO | W81: S | X81: 4 | Y81: 90 | Z81: 0 | AA81: 6 | AB81: 1000 | AC81: 200000 | AD81: CNPJ PARA LANÇAMENTO NO SIOP: 00.394.429/0001-00 - COMANDO DA AERONÁUTICA_x000D_ OM BENEFICIADA: HOSPITAL DE AERONÁUTICA DE RECIFE_x000D_ OBJETO RESUMIDO: AQUISIÇÃO DE EQUIPAMENTO DE RAIO X MÓVEL._x000D_ JUSTIFICATIVA:_x000D_ A FORÇA AÉREA BRASILEIRA (FAB), COMO INSTITUIÇÃO DE ESTADO, ATUA, ININTERRUPTAMENTE, NA DEFESA DA PÁTRIA, NA MANUTENÇÃO DA SOBERANIA DO NOSSO ESPAÇO AÉREO, NA PROTEÇÃO DE NOSSAS FRONTEIRAS E NA INTEGRAÇÃO DO TERRITÓRIO NACIONAL._x000D_ ADEMAIS, SUBSIDIARIAMENTE, A FAB CUMPRE MISSÕES HUMANITÁRIAS E DE REPATRIAÇÃO DE NACIONAIS, DE TRANSPORTE DE ÓRGÃOS E TECIDOS, BEM COMO CONTRIBUI COM O DESENVOLVIMENTO TECNOLÓGICO, GERANDO EMPREGOS E RIQUEZAS AO PAÍS._x000D_ PELO EXPOSTO, PARA CONTRIBUIR COM A FAB NO CUMPRIMENTO DE SUA MISSÃO CONSTITUCIONAL EM BENEFÍCIO DA SOCIEDADE BRASILEIRA, É NECESSÁRIO O APOIO AOS PROJETOS E ATIVIDADES SUPRAMENCIONADOS COM O APORTE DE RECURSOS DE EMENDAS PARLAMENTARES NA LEI ORÇAMENTÁRIA ANUAL (LOA) DE 2026.
A82: 13 | B82: DEFESA | C82: 35390008 | D82: INDIVIDUAL | E82: ACRÉSCIMO - APROPRIAÇÃO | F82: 3539 | G82: LUCIANO BIVAR | H82: DEPUTADO FEDERAL | I82: PE | J82: MDB | K82: 52000 | L82: MINISTÉRIO DA DEFESA | M82: 52931 | N82: FUNDO NAVAL | O82: 05.122.0032.2000.0001 | P82: DEFESA NACIONAL | Q82: ADMINISTRAÇÃO GERAL | R82: PROGRAMA DE GESTÃO E MANUTENÇÃO DO PODER EXECUTIVO | S82: ADMINISTRAÇÃO DA UNIDADE | T82: NACIONAL | U82: NA | V82: NACIONAL | W82: F | X82: 4 | Y82: 90 | Z82: 0 | AA82: 6 | AB82: 1000 | AC82: 200000 | AD82: HOSPITAL NAVAL DE RECIFE (HNRE)_x000D_ CNPJ: 00.394.502/0066-90_x000D_ _x000D_ A PRESENTE PROPOSTA DE EMENDA PARLAMENTAR TEM COMO OBJETIVO A AQUISIÇÃO DE UMA VIATURA ADMINISTRATIVA PARA O HOSPITAL NAVAL DE RECIFE, DESTINADA A APOIAR O TRANSPORTE DE MATERIAIS E DE PESSOAL NAS ATIVIDADES OPERACIONAIS E ASSISTENCIAIS. A NOVA VIATURA PROPORCIONARÁ MAIOR MOBILIDADE LOGÍSTICA, OTIMIZAÇÃO DOS RECURSOS E APRIMORAMENTO DOS SERVIÇOS DE SAÚDE OFERECIDOS PELA MARINHA À COMUNIDADE MILITAR E SEUS DEPENDENTES.
A83: 13 | B83: DEFESA | C83: 36300001 | D83: INDIVIDUAL | E83: ACRÉSCIMO - APROPRIAÇÃO | F83: 3630 | G83: ALBERTO FRAGA | H83: DEPUTADO FEDERAL | I83: DF | J83: PL | K83: 52000 | L83: MINISTÉRIO DA DEFESA | M83: 52131 | N83: COMANDO DA MARINHA | O83: 05.152.6112.219D.0001 | P83: DEFESA NACIONAL | Q83: DEFESA NAVAL | R83: DEFESA NACIONAL | S83: ADEQUAÇÃO DE ATIVOS DE INFRAESTRUTURA DAS ORGANIZAÇÕES MILITARES | T83: NACIONAL | U83: NA | V83: NACIONAL | W83: F | X83: 4 | Y83: 90 | Z83: 0 | AA83: 6 | AB83: 1000 | AC83: 150000 | AD83: 3º BATALHÃO DE PROTEÇÃO E DEFESA NUCLEAR, BIOLÓGICA, QUÍMICA E RADIOLÓGICA_x000D_ CNPJ: 00.394.502/0147-90_x000D_ _x000D_ O 3º BATALHÃO DE PROTEÇÃO E DEFESA NUCLEAR, BIOLÓGICA, QUÍMICA E RADIOLÓGICA É UMA ORGANIZAÇÃO MILITAR QUE TEM COMO PROPÓSITO DE CONTRIBUIR PARA O PREPARO E APLICAÇÃO DO PODER NAVAL, NA ÁREA SOB JURISDIÇÃO DO COMANDO DO 7º DISTRITO NAVAL (COM7ºDN) EM BRASÍLIA. A PRESENTE PROPOSTA DE EMENDA PARLAMENTAR VISA A REESTRUTURAR A SEGURANÇA ORGÂNICA DO 3ºBTLPROTDEFNBQR, COMPREENDENDO A REFORMA DE GRADIS, INSTALAÇÃO DE PORTÕES ELÉTRICOS, INSTALAÇÃO DE SISTEMA DE CFTV, AQUISIÇÃO DE BARREIRA FÍSICAS, ETC. ESTE PROJETO INCREMENTA A SEGURANÇA, PERMITINDO A PROTEÇÃO DE ATIVOS, PESSOAL E INSTALAÇÕES SEGURANÇA DA ORGANIZAÇÃO MILITAR. O POSTO DE VIGILÂNCIA E O SISTEMA DE CIRCUITO FECHADO DE TELEVISÃO (CFTV) DESEMPENHAM PAPÉIS VITAIS NO MONITORAMENTO DAS INSTALAÇÕES, DETECÇÃO DE COMPORTAMENTOS SUSPEITOS E PREVENÇÃO DE INCIDENTES. CONTUDO, COM O PASSAR DO TEMPO, TANTO AS CONDIÇÕES ESTRUTURAIS QUANTO A EVOLUÇÃO DAS TECNOLOGIAS DE SEGURANÇA EXIGEM UMA REAVALIAÇÃO PERIÓDICA REESTRUTURAÇÃO DESSES SISTEMAS. COMPREENDE A AQUISIÇÃO DE RADIOCOMUNICADORES PARA AS ATIVIDADES DO DO PELOTÃO DE CONTROLE DE DISTÚRBIOS, MISSÃO INSTITUCIONAL DO 3ºBTLPROTDEFNBQR, QUE GARANTE A SEGURANÇA ORGÂNICA DAS INSTALAÇÕES DA MB EM BRASÍLIA. A PRESENTE PROPOSTA DE EMENDA PARLAMENTAR VISA A OTIMIZAR A COMUNICAÇÃO EM EVENTUAIS SITUAÇÕES DE EMERGÊNCIA.
A84: 13 | B84: DEFESA | C84: 36300006 | D84: INDIVIDUAL | E84: ACRÉSCIMO - APROPRIAÇÃO | F84: 3630 | G84: ALBERTO FRAGA | H84: DEPUTADO FEDERAL | I84: DF | J84: PL | K84: 52000 | L84: MINISTÉRIO DA DEFESA | M84: 52131 | N84: COMANDO DA MARINHA | O84: 05.152.6112.219D.0001 | P84: DEFESA NACIONAL | Q84: DEFESA NAVAL | R84: DEFESA NACIONAL | S84: ADEQUAÇÃO DE ATIVOS DE INFRAESTRUTURA DAS ORGANIZAÇÕES MILITARES | T84: NACIONAL | U84: NA | V84: NACIONAL | W84: F | X84: 4 | Y84: 90 | Z84: 0 | AA84: 6 | AB84: 1000 | AC84: 1800000 | AD84: CAPITANIA FLUVIAL DE BRASÍLIA_x000D_ CNPJ: 03.811.661/0001-95_x000D_ _x000D_ A PRESENTE EMENDA VISA A CONSTRUÇÃO DA NOVA SEDE DA CAPITANIA FLUVIAL DE BRASÍLIA.
A85: 13 | B85: DEFESA | C85: 36920011 | D85: INDIVIDUAL | E85: ACRÉSCIMO - APROPRIAÇÃO | F85: 3692 | G85: JOAQUIM PASSARINHO | H85: DEPUTADO FEDERAL | I85: PA | J85: PL | K85: 52000 | L85: MINISTÉRIO DA DEFESA | M85: 52931 | N85: FUNDO NAVAL | O85: 05.125.6112.21BY.0001 | P85: DEFESA NACIONAL | Q85: NORMATIZAÇÃO E FISCALIZAÇÃO | R85: DEFESA NACIONAL | S85: FISCALIZAÇÃO DA NAVEGAÇÃO AQUAVIÁRIA | T85: NACIONAL | U85: NA | V85: NACIONAL | W85: F | X85: 4 | Y85: 90 | Z85: 0 | AA85: 6 | AB85: 1000 | AC85: 700000 | AD85: CAPITANIA DOS PORTOS DA AMAZONIA ORIENTAL_x000D_ CNPJ: 11.340.225/0001-03_x000D_ _x000D_ A PRESENTE SOLICITAÇÃO VISA OBTER RECURSOS, POR MEIO DE EMENDA PARLAMENTAR, PARA A AQUISIÇÃO DE UMA LANCHA DE FISCALIZAÇÃO A SER_x000D_ EMPREGADA NAS AÇÕES DE SEGURANÇA E CONTROLE DO TRÁFEGO AQUAVIÁRIO NA REGIÃO DE AFUÁ, NO ARQUIPÉLAGO DO MARAJÓ, E EM OUTROS MUNICÍPIOS_x000D_ RIBEIRINHOS DO ESTADO DO PARÁ QUE COMPARTILHAM ESSA COMPLEXA MALHA HÍDRICA._x000D_ A LANCHA É UM ATIVO OPERACIONAL ESSENCIAL E ESTRATÉGICO PARA:_x000D_ I - COMBATE A ILÍCITOS FLUVIAIS ("RATOS D ÁGUA"): REPRIMIR ROUBOS E FURTOS A EMBARCAÇÕES, GARANTINDO A SEGURANÇA DE PASSAGEIROS E DO TRANSPORTE DE MERCADORIAS;_x000D_ II - REPRESSÃO AO CRIME AMBIENTAL: COIBIR O TRANSPORTE ILEGAL E PREDATÓRIO DE MADEIRA E OUTROS PRODUTOS EXTRAÍDOS ILEGALMENTE, COMBATENDO O DESMATAMENTO E O CONTRABANDO, E PROTEGENDO OS RECURSOS NATURAIS AMAZÔNICOS;_x000D_ III - FISCALIZAÇÃO DO TRÁFEGO AQUAVIÁRIO: IDENTIFICAR E APREENDER EMBARCAÇÕES ILEGAIS OU EM CONDIÇÕES IRREGULARES, MELHORANDO A ORDEM PÚBLICA E_x000D_ PREVENINDO ACIDENTES AQUAVIÁRIOS._x000D_ SOLICITA-SE A DESTINAÇÃO DA EMENDA PARLAMENTAR PARA A CÉLERE AQUISIÇÃO DA LANCHA, UMA MEDIDA FUNDAMENTAL PARA A SEGURANÇA E O DESENVOLVIMENTO ORDENADO DAS COMUNIDADES RIBEIRINHAS DO PARÁ.
A86: 13 | B86: DEFESA | C86: 36940010 | D86: INDIVIDUAL | E86: INCLUSÃO - APROPRIAÇÃO | F86: 3694 | G86: JORGE SOLLA | H86: DEPUTADO FEDERAL | I86: BA | J86: PT | K86: 52000 | L86: MINISTÉRIO DA DEFESA | M86: 52931 | N86: FUNDO NAVAL | O86: 05.152.6112.21A0.0029 | P86: DEFESA NACIONAL | Q86: DEFESA NAVAL | R86: DEFESA NACIONAL | S86: APRESTAMENTO DAS FORÇAS - MANUTENÇÃO DA PRONTIDÃO E DA CAPACIDADE OPERATIVA | T86: NO ESTADO DA BAHIA | U86: BA | V86: BAHIA | W86: F | X86: 4 | Y86: 99 | Z86: 0 | AA86: 6 | AB86: 1000 | AC86: 300000 | AD86: JUSTIFICATIVA DO OBJETO: A INCORPORAÇÃO DE NOVOS MEIOS E A REVITALIZAÇÃO DOS MEIOS ANTIGOS, COM EQUIPAMENTOS, CONTRIBUIRÁ PARA A ELEVAÇÃO DA FROTA E DA_x000D_ CAPACIDADE DE AÇÃO DA AGBJLAPA, INCREMENTANDO A SENSAÇÃO DE SEGURANÇA DA NAVEGAÇÃO PARA A SOCIEDADE BAIANA E CONTRIBUINDO PARA A GERAÇÃO DE_x000D_ EMPREGOS E DIVISAS, POR MEIO DO FOMENTO À ECONOMIA AZUL E DO TURISMO NÁUTICO EM TODOS OS 91 (NOVENTA E UM) MUNICÍPIOS SOB SUA JURISDIÇÃO, QUE EQUIVALE A_x000D_ CERCA DE 228.769,6 KM2, NO ESTADO DA BAHIA, INCLUSO CERCA DE 527 KM DE EXTENSÃO NAVEGÁVEL DO RIO SÃO FRANCISCO, COLABORANDO COM A PRONTIDÃO E_x000D_ EFICIÊNCIA DAS ATIVIDADES REALIZADAS PELA ORGANIZAÇÃO MILITAR, A SABER: AÇÕES DE BUSCA E SALVAMENTO, FISCALIZAÇÃO DO TRÁFEGO AQUAVIÁRIO, ENSINO_x000D_ PROFISSIONAL MARÍTIMO, ATENDIMENTO AO PÚBLICO E TREINAMENTO DE AGENTES PÚBLICOS. A AGBJLAPA REALIZA AINDA AÇÕES CÍVICOS SOCIAIS EM PROL DAS_x000D_ COMUNIDADES RIBEIRINHAS DO BACIA DO SÃO FRANCISCO. DESSA FORMA, HÁ UMA GRANDE NECESSIDADE DA MARINHA DO BRASIL ESTAR PRESENTE NAS DIVERSAS REGIÕES, COM_x000D_ CAPACIDADE DE OPERAR, TANTO EM ESTRADAS PAVIMENTADAS OU DE TERRA, OU POR MEIOS NÁUTICOS, PARA TRANSPORTAR MILITARES E CARGAS, ALÉM DE REBOCAR EMBARCAÇÕES_x000D_ COM A FINALIDADE DE CUMPRIR SUA MISSÃO DE PROVER A SEGURANÇA DA NAVEGAÇÃO, SALVAGUARDA DA VIDA HUMANA NOS RIOS E ÁGUAS INTERIORES E PREVENÇÃO DA_x000D_ POLUIÇÃO HÍDRICA, COM RELEVANTE PAPEL NO ORDENAMENTO AQUAVIÁRIO, NO SALVAMENTO DE VIDAS EM PERIGO E NA MANUTENÇÃO DE UM MEIO AMBIENTE RICO E_x000D_ SUSTENTÁVEL.
A87: 13 | B87: DEFESA | C87: 37130006 | D87: INDIVIDUAL | E87: INCLUSÃO - APROPRIAÇÃO | F87: 3713 | G87: MARCELO ÁLVARO ANTÔNIO | H87: DEPUTADO FEDERAL | I87: MG | J87: PL | K87: 52000 | L87: MINISTÉRIO DA DEFESA | M87: 52911 | N87: FUNDO AERONÁUTICO | O87: 05.363.6112.21GN.0031 | P87: DEFESA NACIONAL | Q87: ENSINO PROFISSIONAL | R87: DEFESA NACIONAL | S87: FUNCIONAMENTO DE ESTABELECIMENTOS DE ENSINO PROFISSIONAL MILITARES DO MINISTÉRIO DA DEFESA | T87: NO ESTADO DE MINAS GERAIS | U87: MG | V87: MINAS GERAIS | W87: F | X87: 4 | Y87: 90 | Z87: 0 | AA87: 6 | AB87: 1000 | AC87: 2000000 | AD87: CNPJ PARA LANÇAMENTO NO SIOP: 00.394.429/0001-00 - COMANDO DA AERONÁUTICA_x000D_ OM BENEFICIADA: CENTRO DE INSTRUÇÃO E ADAPTAÇÃO DA AERONÁUTICA_x000D_ OBJETO RESUMIDO: ADEQUAÇÃO DAS INSTALAÇÕES DO CIAAR E DA GUARNIÇÃO DE AERONÁUTICA DE LAGOA SANTA. (PARCIAL)_x000D_ JUSTIFICATIVA:_x000D_ A FORÇA AÉREA BRASILEIRA (FAB), COMO INSTITUIÇÃO DE ESTADO, ATUA, ININTERRUPTAMENTE, NA DEFESA DA PÁTRIA, NA MANUTENÇÃO DA SOBERANIA DO NOSSO ESPAÇO AÉREO, NA PROTEÇÃO DE NOSSAS FRONTEIRAS E NA INTEGRAÇÃO DO TERRITÓRIO NACIONAL._x000D_ ADEMAIS, SUBSIDIARIAMENTE, A FAB CUMPRE MISSÕES HUMANITÁRIAS E DE REPATRIAÇÃO DE NACIONAIS, DE TRANSPORTE DE ÓRGÃOS E TECIDOS, BEM COMO CONTRIBUI COM O DESENVOLVIMENTO TECNOLÓGICO, GERANDO EMPREGOS E RIQUEZAS AO PAÍS._x000D_ PELO EXPOSTO, PARA CONTRIBUIR COM A FAB NO CUMPRIMENTO DE SUA MISSÃO CONSTITUCIONAL EM BENEFÍCIO DA SOCIEDADE BRASILEIRA, É NECESSÁRIO O APOIO AOS PROJETOS E ATIVIDADES SUPRAMENCIONADOS COM O APORTE DE RECURSOS DE EMENDAS PARLAMENTARES NA LEI ORÇAMENTÁRIA ANUAL (LOA) DE 2026.
A88: 13 | B88: DEFESA | C88: 37240005 | D88: INDIVIDUAL | E88: INCLUSÃO - APROPRIAÇÃO | F88: 3724 | G88: MARCOS SOARES | H88: DEPUTADO FEDERAL | I88: RJ | J88: PSDB | K88: 52000 | L88: MINISTÉRIO DA DEFESA | M88: 52121 | N88: COMANDO DO EXÉRCITO | O88: 05.153.6112.219D.0001 | P88: DEFESA NACIONAL | Q88: DEFESA TERRESTRE | R88: DEFESA NACIONAL | S88: ADEQUAÇÃO DE ATIVOS DE INFRAESTRUTURA DAS ORGANIZAÇÕES MILITARES | T88: NACIONAL | U88: NA | V88: NACIONAL | W88: F | X88: 4 | Y88: 90 | Z88: 0 | AA88: 6 | AB88: 1000 | AC88: 600000 | AD88: OFERECER UMA ÁREA DE LAZER E APOIO AOS BANHISTAS/USUÁRIOS DA PRAIA DA RESTINGA DA MARAMBAIA, LOCALIZADA EM BARRA DE GUARATIBA._x000D_ CENTRO DE AVALIAÇÕES DO EXÉRCITO (CAEX), NO MUNICÍPIO DO RIO DE JANEIRO-RJ | AE88: CAEx | AF88: Construção de área de lazer e apoio aos banhistas
A89: 13 | B89: DEFESA | C89: 37560012 | D89: INDIVIDUAL | E89: INCLUSÃO - APROPRIAÇÃO | F89: 3756 | G89: ROSANGELA GOMES | H89: DEPUTADO FEDERAL | I89: RJ | J89: PRB | K89: 52000 | L89: MINISTÉRIO DA DEFESA | M89: 52931 | N89: FUNDO NAVAL | O89: 05.125.6112.21BY.0033 | P89: DEFESA NACIONAL | Q89: NORMATIZAÇÃO E FISCALIZAÇÃO | R89: DEFESA NACIONAL | S89: FISCALIZAÇÃO DA NAVEGAÇÃO AQUAVIÁRIA | T89: NO ESTADO DO RIO DE JANEIRO | U89: RJ | V89: RIO DE JANEIRO | W89: F | X89: 4 | Y89: 99 | Z89: 0 | AA89: 6 | AB89: 1000 | AC89: 250000 | AD89: A DESTINAÇÃO DE RECURSOS PARA A AÇÃO 21BY – FISCALIZAÇÃO DA NAVEGAÇÃO AQUAVIÁRIA TEM COMO OBJETIVO FORTALECER AS ATIVIDADES DE MONITORAMENTO, CONTROLE E SEGURANÇA REALIZADAS NOS RIOS, LAGOS, HIDROVIAS E DEMAIS VIAS AQUÁTICAS DO ESTADO DO RIO DE JANEIRO
A90: 13 | B90: DEFESA | C90: 37660016 | D90: INDIVIDUAL | E90: INCLUSÃO - APROPRIAÇÃO | F90: 3766 | G90: SÓSTENES CAVALCANTE | H90: DEPUTADO FEDERAL | I90: RJ | J90: PL | K90: 52000 | L90: MINISTÉRIO DA DEFESA | M90: 52131 | N90: COMANDO DA MARINHA | O90: 05.152.6112.219D.0001 | P90: DEFESA NACIONAL | Q90: DEFESA NAVAL | R90: DEFESA NACIONAL | S90: ADEQUAÇÃO DE ATIVOS DE INFRAESTRUTURA DAS ORGANIZAÇÕES MILITARES | T90: NACIONAL | U90: NA | V90: NACIONAL | W90: F | X90: 3 | Y90: 99 | Z90: 0 | AA90: 6 | AB90: 1000 | AC90: 250000 | AD90: ADEQUAÇÃO, CONSERVAÇÃO E RECUPERAÇÃO DE ATIVOS DAS UNIDADES MILITARES COM A FINALIDADE DE ESTABELECER UMA ADEQUADA INFRAESTRUTURA OPERACIONAL E DE APOIO AO PESSOAL, ENVOLVENDO OBRAS DE AMPLIAÇÃO (PEQUENAS CONSTRUÇÕES) RECUPERAÇÃO, REPARAÇÃO, REFORMA, ADEQUAÇÃO, ADAPTAÇÃO DE INSTALAÇÕES EM ORGANIZAÇÕES MILITARES EXISTENTES, ABRANGENDO, AINDA, A OBTENÇÃO E INSTALAÇÃO DE EQUIPAMENTOS FIXOS. INCLUI AQUISIÇÃO DE DIÁRIAS, PASSAGENS, MEIOS E SERVIÇOS NECESSÁRIOS A ESTUDOS, PROJETOS E FISCALIZAÇÃO DAS OBRAS.
A91: 13 | B91: DEFESA | C91: 37660018 | D91: INDIVIDUAL | E91: INCLUSÃO - APROPRIAÇÃO | F91: 3766 | G91: SÓSTENES CAVALCANTE | H91: DEPUTADO FEDERAL | I91: RJ | J91: PL | K91: 52000 | L91: MINISTÉRIO DA DEFESA | M91: 52931 | N91: FUNDO NAVAL | O91: 05.152.6112.21A0.0001 | P91: DEFESA NACIONAL | Q91: DEFESA NAVAL | R91: DEFESA NACIONAL | S91: APRESTAMENTO DAS FORÇAS - MANUTENÇÃO DA PRONTIDÃO E DA CAPACIDADE OPERATIVA | T91: NACIONAL | U91: NA | V91: NACIONAL | W91: F | X91: 4 | Y91: 90 | Z91: 0 | AA91: 6 | AB91: 1000 | AC91: 100000 | AD91: O PROGRAMA FORÇAS NO ESPORTE (PROFESP) TEM, COMO CONTEÚDO PROGRAMÁTICO, PALESTRA EM SALA DE AULA E PRÁTICAS ESPORTIVAS. NESSE CONTEXTO, A AQUISIÇÃO DE ITENS PARA MODERNIZAÇÃO DAS INSTALAÇÕES E MATERIAIS ESPORTIVOS É IMPERATIVA PARA O BOM ANDAMENTO DO PROGRAMA E NO CUMPRIMENTO DE SUA MISSÃO COM A SOCIEDADE.
A92: 13 | B92: DEFESA | C92: 37660019 | D92: INDIVIDUAL | E92: INCLUSÃO - APROPRIAÇÃO | F92: 3766 | G92: SÓSTENES CAVALCANTE | H92: DEPUTADO FEDERAL | I92: RJ | J92: PL | K92: 52000 | L92: MINISTÉRIO DA DEFESA | M92: 52121 | N92: COMANDO DO EXÉRCITO | O92: 05.153.6112.219D.0001 | P92: DEFESA NACIONAL | Q92: DEFESA TERRESTRE | R92: DEFESA NACIONAL | S92: ADEQUAÇÃO DE ATIVOS DE INFRAESTRUTURA DAS ORGANIZAÇÕES MILITARES | T92: NACIONAL | U92: NA | V92: NACIONAL | W92: F | X92: 3 | Y92: 90 | Z92: 0 | AA92: 6 | AB92: 1000 | AC92: 200000 | AD92: BENEFICIÁRIO PARA LANÇAMENTO NO SIOP - CNPJ 00.394.452/0001-03_x000D_ MELHORAR AS ESTRUTURAS E SALAS DE ENSAIO PARA MELHOR ATENDER AS MISSÕES DE APOIO AO COMANDO MILITAR DO PLANALTO, SEJAM ELAS MILITARES OU DE APOIO AO PODERES EXECUTIVO, JUDICIÁRIO E LEGISLATIVO._x000D_ BATALHÃO DE POLÍCIA DO EXÉRCITO DE BRASÍLIA (BPEB), NO MUNICÍPIO DE BRASÍLIA -DF | AE92: BPEB | AF92: Reforma das instalações da Banda de Música
A93: 13 | B93: DEFESA | C93: 37660021 | D93: INDIVIDUAL | E93: INCLUSÃO - APROPRIAÇÃO | F93: 3766 | G93: SÓSTENES CAVALCANTE | H93: DEPUTADO FEDERAL | I93: RJ | J93: PL | K93: 52000 | L93: MINISTÉRIO DA DEFESA | M93: 52121 | N93: COMANDO DO EXÉRCITO | O93: 05.301.0032.2E74.0001 | P93: DEFESA NACIONAL | Q93: ATENÇÃO BÁSICA | R93: PROGRAMA DE GESTÃO E MANUTENÇÃO DO PODER EXECUTIVO | S93: ESTRUTURAÇÃO E MODERNIZAÇÃO DE UNIDADES DE SAÚDE DAS FORÇAS ARMADAS | T93: NACIONAL | U93: NA | V93: NACIONAL | W93: S | X93: 3 | Y93: 99 | Z93: 0 | AA93: 6 | AB93: 1000 | AC93: 120000 | AD93: APOIO A ESTRUTURAÇÃO, APARELHAMENTO E MODERNIZAÇÃO DO SETOR DE SAÚDE DOS ÓRGÃOS DA ADMINISTRAÇÃO FEDERAL, COMPREENDENDO INVESTIMENTOS EM OBRAS, EQUIPAMENTOS E MATERIAL DE CONSUMO, VISANDO A MELHORIA NO ATENDIMENTO AOS USUÁRIOS DOS SERVIÇOS DE SAÚDE PRESTADOS DIRETAMENTE PELAS FORÇAS ARMADAS | AE93: BPEB | AF93: Equipamentos e materiais veterinários
A94: 13 | B94: DEFESA | C94: 37660021 | D94: INDIVIDUAL | E94: INCLUSÃO - APROPRIAÇÃO | F94: 3766 | G94: SÓSTENES CAVALCANTE | H94: DEPUTADO FEDERAL | I94: RJ | J94: PL | K94: 52000 | L94: MINISTÉRIO DA DEFESA | M94: 52121 | N94: COMANDO DO EXÉRCITO | O94: 05.301.0032.2E74.0001 | P94: DEFESA NACIONAL | Q94: ATENÇÃO BÁSICA | R94: PROGRAMA DE GESTÃO E MANUTENÇÃO DO PODER EXECUTIVO | S94: ESTRUTURAÇÃO E MODERNIZAÇÃO DE UNIDADES DE SAÚDE DAS FORÇAS ARMADAS | T94: NACIONAL | U94: NA | V94: NACIONAL | W94: S | X94: 4 | Y94: 99 | Z94: 0 | AA94: 6 | AB94: 1000 | AC94: 90000 | AD94: APOIO A ESTRUTURAÇÃO, APARELHAMENTO E MODERNIZAÇÃO DO SETOR DE SAÚDE DOS ÓRGÃOS DA ADMINISTRAÇÃO FEDERAL, COMPREENDENDO INVESTIMENTOS EM OBRAS, EQUIPAMENTOS E MATERIAL DE CONSUMO, VISANDO A MELHORIA NO ATENDIMENTO AOS USUÁRIOS DOS SERVIÇOS DE SAÚDE PRESTADOS DIRETAMENTE PELAS FORÇAS ARMADAS | AE94: BPEB | AF94: Equipamentos e materiais veterinários
A95: 13 | B95: DEFESA | C95: 37660024 | D95: INDIVIDUAL | E95: INCLUSÃO - APROPRIAÇÃO | F95: 3766 | G95: SÓSTENES CAVALCANTE | H95: DEPUTADO FEDERAL | I95: RJ | J95: PL | K95: 52000 | L95: MINISTÉRIO DA DEFESA | M95: 52931 | N95: FUNDO NAVAL | O95: 05.152.6112.21A0.0001 | P95: DEFESA NACIONAL | Q95: DEFESA NAVAL | R95: DEFESA NACIONAL | S95: APRESTAMENTO DAS FORÇAS - MANUTENÇÃO DA PRONTIDÃO E DA CAPACIDADE OPERATIVA | T95: NACIONAL | U95: NA | V95: NACIONAL | W95: F | X95: 3 | Y95: 99 | Z95: 0 | AA95: 6 | AB95: 1000 | AC95: 100000 | AD95: PREPARAÇÃO OPERATIVA DA FORÇA, COMPREENDENDO, ENTRE OUTRAS, AS ATIVIDADES DE PLANEJAMENTO, ORGANIZAÇÃO E ARTICULAÇÃO, INSTRUÇÃO E ADESTRAMENTO, DESENVOLVIMENTO DE DOUTRINA E PESQUISAS ESPECÍFICAS, INTELIGÊNCIA E ESTRUTURAÇÃO DA FORÇA, DE SUA LOGÍSTICA E MOBILIZAÇÃO. INCLUI AQUISIÇÃO E MANUTENÇÃO DE BENS (MATERIAIS, EQUIPAMENTO E INSUMOS), CONTRATAÇÃO DE SERVIÇOS E INSTRUÇÃO E ADESTRAMENTO DE PESSOAL, PARA O APRIMORAMENTO DA EFICIÊNCIA OPERACIONAL.
A96: 13 | B96: DEFESA | C96: 37660024 | D96: INDIVIDUAL | E96: INCLUSÃO - APROPRIAÇÃO | F96: 3766 | G96: SÓSTENES CAVALCANTE | H96: DEPUTADO FEDERAL | I96: RJ | J96: PL | K96: 52000 | L96: MINISTÉRIO DA DEFESA | M96: 52931 | N96: FUNDO NAVAL | O96: 05.152.6112.21A0.0001 | P96: DEFESA NACIONAL | Q96: DEFESA NAVAL | R96: DEFESA NACIONAL | S96: APRESTAMENTO DAS FORÇAS - MANUTENÇÃO DA PRONTIDÃO E DA CAPACIDADE OPERATIVA | T96: NACIONAL | U96: NA | V96: NACIONAL | W96: F | X96: 4 | Y96: 99 | Z96: 0 | AA96: 6 | AB96: 1000 | AC96: 102007 | AD96: PREPARAÇÃO OPERATIVA DA FORÇA, COMPREENDENDO, ENTRE OUTRAS, AS ATIVIDADES DE PLANEJAMENTO, ORGANIZAÇÃO E ARTICULAÇÃO, INSTRUÇÃO E ADESTRAMENTO, DESENVOLVIMENTO DE DOUTRINA E PESQUISAS ESPECÍFICAS, INTELIGÊNCIA E ESTRUTURAÇÃO DA FORÇA, DE SUA LOGÍSTICA E MOBILIZAÇÃO. INCLUI AQUISIÇÃO E MANUTENÇÃO DE BENS (MATERIAIS, EQUIPAMENTO E INSUMOS), CONTRATAÇÃO DE SERVIÇOS E INSTRUÇÃO E ADESTRAMENTO DE PESSOAL, PARA O APRIMORAMENTO DA EFICIÊNCIA OPERACIONAL.
A97: 13 | B97: DEFESA | C97: 37660025 | D97: INDIVIDUAL | E97: INCLUSÃO - APROPRIAÇÃO | F97: 3766 | G97: SÓSTENES CAVALCANTE | H97: DEPUTADO FEDERAL | I97: RJ | J97: PL | K97: 52000 | L97: MINISTÉRIO DA DEFESA | M97: 52931 | N97: FUNDO NAVAL | O97: 05.122.0032.2000.0001 | P97: DEFESA NACIONAL | Q97: ADMINISTRAÇÃO GERAL | R97: PROGRAMA DE GESTÃO E MANUTENÇÃO DO PODER EXECUTIVO | S97: ADMINISTRAÇÃO DA UNIDADE | T97: NACIONAL | U97: NA | V97: NACIONAL | W97: F | X97: 4 | Y97: 90 | Z97: 0 | AA97: 6 | AB97: 1000 | AC97: 100000 | AD97: CENTRO DE INSTRUÇÃO ALMIRANTE GRAÇA ARANHA (CIAGA)_x000D_ CNPJ: 00.394.502/0094-43_x000D_ A AQUISIÇÃO DE NOVOS MATERIAIS DIDÁTICOS, POSSIBILITARÁ AOS FUTUROS OFICIAIS DA MARINHA MERCANTE DESENVOLVER HABILIDADES PRÁTICAS VOLTADAS_x000D_ À SOLUÇÃO DE PROBLEMAS REAIS DA ÁREA MARÍTIMA, AMPLIANDO A QUALIDADE DO PROCESSO DE ENSINO APRENDIZAGEM E FORTALECENDO A_x000D_ INFRAESTRUTURA DE ENSINO PRÁTICO DA MARINHA DO BRASIL.
A98: 13 | B98: DEFESA | C98: 37710007 | D98: INDIVIDUAL | E98: INCLUSÃO - APROPRIAÇÃO | F98: 3771 | G98: TONINHO WANDSCHEER | H98: DEPUTADO FEDERAL | I98: PR | J98: PP | K98: 52000 | L98: MINISTÉRIO DA DEFESA | M98: 52111 | N98: COMANDO DA AERONÁUTICA | O98: 05.122.0032.2000.0041 | P98: DEFESA NACIONAL | Q98: ADMINISTRAÇÃO GERAL | R98: PROGRAMA DE GESTÃO E MANUTENÇÃO DO PODER EXECUTIVO | S98: ADMINISTRAÇÃO DA UNIDADE | T98: NO ESTADO DO PARANÁ | U98: PR | V98: PARANÁ | W98: F | X98: 3 | Y98: 90 | Z98: 0 | AA98: 6 | AB98: 1000 | AC98: 100000 | AD98: A EMENDA VISA ATENDER 350 CRIANÇAS DO PROGRAMA FORÇAS NO ESPORTE (PROFESP).
A99: 13 | B99: DEFESA | C99: 37710009 | D99: INDIVIDUAL | E99: INCLUSÃO - APROPRIAÇÃO | F99: 3771 | G99: TONINHO WANDSCHEER | H99: DEPUTADO FEDERAL | I99: PR | J99: PP | K99: 52000 | L99: MINISTÉRIO DA DEFESA | M99: 52121 | N99: COMANDO DO EXÉRCITO | O99: 05.153.6112.21A0.0041 | P99: DEFESA NACIONAL | Q99: DEFESA TERRESTRE | R99: DEFESA NACIONAL | S99: APRESTAMENTO DAS FORÇAS - MANUTENÇÃO DA PRONTIDÃO E DA CAPACIDADE OPERATIVA | T99: NO ESTADO DO PARANÁ | U99: PR | V99: PARANÁ | W99: F | X99: 4 | Y99: 90 | Z99: 0 | AA99: 6 | AB99: 1000 | AC99: 368000 | AD99: ADQUIRIR NOVOS INSTRUMENTOS, MELHORANDO AS CONDIÇÕES PARA OS ENSAIOS E APRESENTAÇÕES DA BANCA DE MÚSICA DA UNIDADE. | AE99: 34º BI Mec | AF99: Instrumentos Musicais para a Banda de Música
A100: 13 | B100: DEFESA | C100: 37710011 | D100: INDIVIDUAL | E100: INCLUSÃO - APROPRIAÇÃO | F100: 3771 | G100: TONINHO WANDSCHEER | H100: DEPUTADO FEDERAL | I100: PR | J100: PP | K100: 52000 | L100: MINISTÉRIO DA DEFESA | M100: 52131 | N100: COMANDO DA MARINHA | O100: 05.301.0032.2E74.0041 | P100: DEFESA NACIONAL | Q100: ATENÇÃO BÁSICA | R100: PROGRAMA DE GESTÃO E MANUTENÇÃO DO PODER EXECUTIVO | S100: ESTRUTURAÇÃO E MODERNIZAÇÃO DE UNIDADES DE SAÚDE DAS FORÇAS ARMADAS | T100: NO ESTADO DO PARANÁ | U100: PR | V100: PARANÁ | W100: S | X100: 4 | Y100: 90 | Z100: 0 | AA100: 6 | AB100: 1000 | AC100: 1000000 | AD100: CONSTRUÇÃO DE PRÉDIO PARA ALOJAMENTO DE MILITARES E ALUNOS_x000D_ A CAPITANIA FLUVIAL DO RIO PARANÁ, POR INTERMÉDIO DO ÓRGÃO DE FORMAÇÃO DE RESERVA DA MARINHA, POSSUI A ATRIBUIÇÃO DE FORMAR APROXIMADAMENTE 200 ALUNOS ANUALMENTE, DENTRE CONSCRITOS DO SERVIÇO MILITAR OBRIGATÓRIO E PRAÇAS TEMPORÁRIOS DO SERVIÇO MILITAR VOLUNTÁRIO. SEU OBJETIVO É OFERECER QUALIFICAÇÃO TÉCNICO-PROFISSIONAL MILITAR, PERMITINDO AOS ALUNOS UMA FORMAÇÃO MILITAR SÓLIDA. ALÉM DISSO, A PARTIR DE 2026 O ALISTAMENTO PASSARÁ A RECEBER AS VOLUNTÁRIAS DO SEXO FEMININO PARA PRESTAÇÃO DO SERVIÇO MILITAR. DESSA FORMA, PARA QUE A FORMAÇÃO SEJA REALIZADA COM AMPLITUDE E QUALIDADE, FAZ-SE NECESSÁRIA A CONSTRUÇÃO DE INSTALAÇÕES QUE COMPORTEM ADEQUADAMENTE O RECEBIMENTO DOS ALUNOS, EXISTINDO UM TERRENO ADJACENTE A ESTA CAPITANIA RECEBIDO EM DOAÇÃO EM 2019 DA PREFEITURA DE FOZ DO IGUAÇU, VISANDO A FORMAÇÃO DOS ALUNOS. ASSIM, A CONSTRUÇÃO VISA MELHOR ATENDER OS ALUNOS QUE SERÃO FORMADOS PELO ÓRGÃO DE FORMAÇÃO DE RESERVISTAS DA MARINHA DA CAPITANIA FLUVIAL DO RIO PARANÁ. O NOVO PRÉDIO TAMBÉM ATENDERÁ A NECESSIDADE DE ALOJAMENTO ADEQUADO AOS MILITARES LOTADOS NA CAPITANIA E AO CONSTANTE FLUXO DE MILITARES QUE PERIODICAMENTE SÃO DESTACADOS NA CFRP PARA APOIO A OPERAÇÕES QUE OCORREM ANUALMENTE, COMO A OPERAÇÃO NAVEGUE SEGURO, E OUTRAS OPERAÇÕES QUE SE DÃO DE MODO INTERMITENTE COMO A OPERAÇÃO ÁGATA E AÇÕES DE GARANTIA DA LEI E DA ORDEM NA REGIÃO DA TRÍPLICE FRONTEIRA.
...

Sheet 2025
A1: Setor (Cod) | B1: Setor | C1: Emenda | D1: Emenda (Modalidade) | E1: Emenda (Tipo) | F1: Autor (Cod) | G1: Autor | H1: Autor (Tipo) | I1: Autor (UF) | J1: Partido | K1: Órgão (Cod) | L1: Órgão | M1: UO (Cod) | N1: UO | O1: Funcional | P1: Função | Q1: Subfunção | R1: Programa | S1: Ação | T1: Subtítulo | U1: UF | V1: Localidade | W1: Esfera (Cod) | X1: GND (Cod) | Y1: Mod. Aplic. (Cod) | Z1: ID Uso (Cod) | AA1: Identificador Primário (Cod) | AB1: Fonte (Cod) | AC1: Valor Solicitado | AD1: Emenda (Justificativa) | AE1: OM | AF1: Objeto
A2: 13 | B2: DEFESA | C2: 12710006 | D2: INDIVIDUAL | E2: INCLUSÃO - APROPRIAÇÃO | F2: 1271 | G2: LUIZ COUTO | H2: DEPUTADO FEDERAL | I2: PB | J2: PT | K2: 52000 | L2: MINISTÉRIO DA DEFESA | M2: 52931 | N2: FUNDO NAVAL | O2: 05.125.6112.21BY.0001 | P2: DEFESA NACIONAL | Q2: NORMATIZAÇÃO E FISCALIZAÇÃO | R2: DEFESA NACIONAL | S2: FISCALIZAÇÃO DA NAVEGAÇÃO AQUAVIÁRIA | T2: NACIONAL | U2: NA | V2: NACIONAL | W2: F | X2: 4 | Y2: 90 | Z2: 0 | AA2: 6 | AB2: 1000 | AC2: 250000 | AD2: CAPITANIA DOS PORTOS DA PARAÍBA - CPPB_x000D_ CNPJ: 00394502/0037-55_x000D_ A PRESENTE PROPOSTA DE EMENDA VISA À AQUISIÇÃO DE VIATURA PARA REALIZAR AÇÕES DE FISCALIZAÇÃO DO TRÁFICO AQUAVIÁRIA E DE APOIO AO ENSINO PROFISSIONAL MARITO, PERMITINDO A CAPITANIA DOS PORTOS DA PARAÍBA REALIZAR EM TODA EXTENSÃO DO LITORAL PARAIBANO.
A3: 13 | B3: DEFESA | C3: 14070006 | D3: INDIVIDUAL | E3: INCLUSÃO - APROPRIAÇÃO | F3: 1407 | G3: ODAIR CUNHA | H3: DEPUTADO FEDERAL | I3: MG | J3: PT | K3: 52000 | L3: MINISTÉRIO DA DEFESA | M3: 52931 | N3: FUNDO NAVAL | O3: 05.125.6112.21BY.0031 | P3: DEFESA NACIONAL | Q3: NORMATIZAÇÃO E FISCALIZAÇÃO | R3: DEFESA NACIONAL | S3: FISCALIZAÇÃO DA NAVEGAÇÃO AQUAVIÁRIA | T3: NO ESTADO DE MINAS GERAIS | U3: MG | V3: MINAS GERAIS | W3: F | X3: 4 | Y3: 90 | Z3: 0 | AA3: 6 | AB3: 1000 | AC3: 400000 | AD3: A AQUISIÇÃO DE NOVOS MEIOS TAIS COMO VIATURAS PICK-UP, COM REBOQUE E MOTO AQUÁTICA (230 HP), COM CARRETINHA, AMPLIAM A_x000D_ POSSIBILIDADE DE ATUAÇÃO DA CFMG NOS SEUS MUNICÍPIOS DA ÁREA DE JURISDIÇÃO TRAZENDO BENEFÍCIOS PARA A SEGURANÇA DA NAVEGAÇÃO E SALVAGUARDA DA_x000D_ VIDA HUMANA DOS CIDADÃOS NO ESTADO DE MINAS GERAIS.
A4: 13 | B4: DEFESA | C4: 14510001 | D4: INDIVIDUAL | E4: INCLUSÃO - APROPRIAÇÃO | F4: 1451 | G4: VANDER LOUBET | H4: DEPUTADO FEDERAL | I4: MS | J4: PT | K4: 52000 | L4: MINISTÉRIO DA DEFESA | M4: 52131 | N4: COMANDO DA MARINHA | O4: 05.152.6112.219D.5259 | P4: DEFESA NACIONAL | Q4: DEFESA NAVAL | R4: DEFESA NACIONAL | S4: ADEQUAÇÃO DE ATIVOS DE INFRAESTRUTURA DAS ORGANIZAÇÕES MILITARES | T4: NO MUNICÍPIO DE PORTO MURTINHO - MS | U4: MS | V4: PORTO MURTINHO | W4: F | X4: 4 | Y4: 90 | Z4: 0 | AA4: 6 | AB4: 1000 | AC4: 300000 | AD4: REESTRUTURAÇÃO DE MODERNIZAÇÃO DA AGÊNCIA FLUVIAL DE PORTO MURTINHO - MS (6O. COMANDO DA MARINHA DO BRASIL - LADÁRIO - MS), 2 VEÍCULOS.
A5: 13 | B5: DEFESA | C5: 15270012 | D5: INDIVIDUAL | E5: INCLUSÃO - APROPRIAÇÃO | F5: 1527 | G5: CARLOS SAMPAIO | H5: DEPUTADO FEDERAL | I5: SP | J5: PSD | K5: 52000 | L5: MINISTÉRIO DA DEFESA | M5: 52111 | N5: COMANDO DA AERONÁUTICA | O5: 05.122.0032.2000.0035 | P5: DEFESA NACIONAL | Q5: ADMINISTRAÇÃO GERAL | R5: PROGRAMA DE GESTÃO E MANUTENÇÃO DO PODER EXECUTIVO | S5: ADMINISTRAÇÃO DA UNIDADE | T5: NO ESTADO DE SÃO PAULO | U5: SP | V5: SÃO PAULO | W5: F | X5: 4 | Y5: 99 | Z5: 0 | AA5: 6 | AB5: 1000 | AC5: 200000 | AD5: A PRESENTE EMENDA TEM POR OBJETIVO A LIBERAÇÃO DE RECURSOS FINANCEIROS PARA AQUISIÇÃO DE MATERIAL INSTITUCIONAL PARA A AERONÁUTICA NO ESTADO DE SÃO PAULO
A6: 13 | B6: DEFESA | C6: 15680018 | D6: INDIVIDUAL | E6: INCLUSÃO - APROPRIAÇÃO | F6: 1568 | G6: GILBERTO NASCIMENTO | H6: DEPUTADO FEDERAL | I6: SP | J6: PSD | K6: 52000 | L6: MINISTÉRIO DA DEFESA | M6: 52911 | N6: FUNDO AERONÁUTICO | O6: 05.364.6112.21GQ.0035 | P6: DEFESA NACIONAL | Q6: ENSINO SUPERIOR | R6: DEFESA NACIONAL | S6: FUNCIONAMENTO DOS ESTABELECIMENTOS DE ENSINO SUPERIOR MILITARES DO MINISTÉRIO DA DEFESA | T6: NO ESTADO DE SÃO PAULO | U6: SP | V6: SÃO PAULO | W6: F | X6: 3 | Y6: 90 | Z6: 0 | AA6: 6 | AB6: 1000 | AC6: 150000 | AD6: CNPJ PARA LANÇAMENTO NO SIOP: 00.394.429/0001-00 - COMANDO DA AERONÁUTICA_x000D_ UNIDADE BENEFICIADA: ACADEMIA DA FORÇA AÉREA - AFA_x000D_ OBJETO RESUMIDO: READEQUAÇÃO DE SEÇÕES ADMINISTRATIVAS DO CORPO DE CADETES.
A7: 13 | B7: DEFESA | C7: 15680019 | D7: INDIVIDUAL | E7: INCLUSÃO - APROPRIAÇÃO | F7: 1568 | G7: GILBERTO NASCIMENTO | H7: DEPUTADO FEDERAL | I7: SP | J7: PSD | K7: 52000 | L7: MINISTÉRIO DA DEFESA | M7: 52121 | N7: COMANDO DO EXÉRCITO | O7: 05.301.0032.2E74.3928 | P7: DEFESA NACIONAL | Q7: ATENÇÃO BÁSICA | R7: PROGRAMA DE GESTÃO E MANUTENÇÃO DO PODER EXECUTIVO | S7: ESTRUTURAÇÃO E MODERNIZAÇÃO DE UNIDADES DE SAÚDE DAS FORÇAS ARMADAS | T7: NO MUNICÍPIO DE SÃO PAULO - SP | U7: SP | V7: SÃO PAULO | W7: S | X7: 4 | Y7: 90 | Z7: 0 | AA7: 6 | AB7: 1000 | AC7: 580000 | AD7: BENEFICIÁRIO PARA LANÇAMENTO NO SIOP - CNPJ: 00.394.452/0001-03_x000D_ POSSIBILITAR A REALIZAÇÃO DE EXAME BEIRA-LEITO EM PACIENTES ACAMADOS NO HOSPITAL MILITAR DE ÁREA DE SÃO PAULO/SP, SENDO DE FUNDAMENTAL IMPORTÂNCIA PARA A CONTINUIDADE DO TRATAMENTO. | AE7: HMASP | AF7: Aquisição de aparelho de ecocardiograma de alta resolução, com transdutor adulto 3D, transdutor pediátrico 3D, fetal 2D, convexo 2D.
A8: 13 | B8: DEFESA | C8: 15680020 | D8: INDIVIDUAL | E8: ACRÉSCIMO - APROPRIAÇÃO | F8: 1568 | G8: GILBERTO NASCIMENTO | H8: DEPUTADO FEDERAL | I8: SP | J8: PSD | K8: 52000 | L8: MINISTÉRIO DA DEFESA | M8: 52133 | N8: SECRETARIA DA COMISSÃO INTERMINISTERIAL PARA OS RECURSOS DO MAR | O8: 05.571.6113.2345.0001 | P8: DEFESA NACIONAL | Q8: DESENVOLVIMENTO CIENTÍFICO | R8: OCEANO, ZONA COSTEIRA E ANTÁRTICA | S8: APOIO LOGÍSTICO À PESQUISA CIENTÍFICA NA ANTÁRTICA | T8: NACIONAL | U8: NA | V8: NACIONAL | W8: F | X8: 3 | Y8: 90 | Z8: 0 | AA8: 6 | AB8: 1000 | AC8: 300000 | AD8: SECRETARIA DA COMISSÃO INTERMINISTERIAL PARA OS RECURSOS DO MAR - SECIRM_x000D_ CNPJ: 00.394.502/0165-71_x000D_ _x000D_ PROVER APOIO E SUPORTE LOGÍSTICO ÀS ATIVIDADES CIENTÍFICAS BRASILEIRAS REALIZADAS NO CONTINENTE ANTÁRTICO, PELO PROGRAMA ANTÁRTICO BRASILEIRO (PROANTAR), CORROBORANDO COM A PRESENÇA DO ESTADO BRASILEIRO NA REALIZAÇÃO DE RENOMADAS PESQUISAS A BORDO DOS NAVIOS DA MARINHA DO BRASIL, NAS ESTAÇÃO ANTÁRTICA COMANDANTE FERRAZ E ACAMPAMENTOS NO CONTINENTE, NA PRODUÇÃO DE CONHECIMENTOS, INCENTIVO À PESQUISA E FOMENTO À PARTICIPAÇÃO DE PESQUISADORES E INSTITUIÇÕES NACIONAIS NA COMPREENSÃO DOS FENÔMENOS QUE ALI OCORREM E QUE TENHAM REPERCUSSÃO GLOBAL E, PRINCIPALMENTE, NO PAÍS.
A9: 13 | B9: DEFESA | C9: 15680020 | D9: INDIVIDUAL | E9: ACRÉSCIMO - APROPRIAÇÃO | F9: 1568 | G9: GILBERTO NASCIMENTO | H9: DEPUTADO FEDERAL | I9: SP | J9: PSD | K9: 52000 | L9: MINISTÉRIO DA DEFESA | M9: 52133 | N9: SECRETARIA DA COMISSÃO INTERMINISTERIAL PARA OS RECURSOS DO MAR | O9: 05.571.6113.2345.0001 | P9: DEFESA NACIONAL | Q9: DESENVOLVIMENTO CIENTÍFICO | R9: OCEANO, ZONA COSTEIRA E ANTÁRTICA | S9: APOIO LOGÍSTICO À PESQUISA CIENTÍFICA NA ANTÁRTICA | T9: NACIONAL | U9: NA | V9: NACIONAL | W9: F | X9: 4 | Y9: 90 | Z9: 0 | AA9: 6 | AB9: 1000 | AC9: 100000 | AD9: SECRETARIA DA COMISSÃO INTERMINISTERIAL PARA OS RECURSOS DO MAR - SECIRM_x000D_ CNPJ: 00.394.502/0165-71_x000D_ _x000D_ PROVER APOIO E SUPORTE LOGÍSTICO ÀS ATIVIDADES CIENTÍFICAS BRASILEIRAS REALIZADAS NO CONTINENTE ANTÁRTICO, PELO PROGRAMA ANTÁRTICO BRASILEIRO (PROANTAR), CORROBORANDO COM A PRESENÇA DO ESTADO BRASILEIRO NA REALIZAÇÃO DE RENOMADAS PESQUISAS A BORDO DOS NAVIOS DA MARINHA DO BRASIL, NAS ESTAÇÃO ANTÁRTICA COMANDANTE FERRAZ E ACAMPAMENTOS NO CONTINENTE, NA PRODUÇÃO DE CONHECIMENTOS, INCENTIVO À PESQUISA E FOMENTO À PARTICIPAÇÃO DE PESQUISADORES E INSTITUIÇÕES NACIONAIS NA COMPREENSÃO DOS FENÔMENOS QUE ALI OCORREM E QUE TENHAM REPERCUSSÃO GLOBAL E, PRINCIPALMENTE, NO PAÍS.
A10: 13 | B10: DEFESA | C10: 16190006 | D10: INDIVIDUAL | E10: INCLUSÃO - APROPRIAÇÃO | F10: 1619 | G10: ÁTILA LINS | H10: DEPUTADO FEDERAL | I10: AM | J10: PSD | K10: 52000 | L10: MINISTÉRIO DA DEFESA | M10: 52931 | N10: FUNDO NAVAL | O10: 05.152.6112.21A0.0013 | P10: DEFESA NACIONAL | Q10: DEFESA NAVAL | R10: DEFESA NACIONAL | S10: APRESTAMENTO DAS FORÇAS - MANUTENÇÃO DA PRONTIDÃO E DA CAPACIDADE OPERATIVA | T10: NO ESTADO DO AMAZONAS | U10: AM | V10: AMAZONAS | W10: F | X10: 3 | Y10: 90 | Z10: 0 | AA10: 6 | AB10: 1000 | AC10: 500000 | AD10: RECUPERAÇÃO DO TELHADO DO PRÉDIO DA DIVISÃO DE ENSINO PROFISSIONAL MARÍTIMO DA CFT, QUE ENCONTRA-SE EM ESTADO AVANÇADO DE DETERIORAÇÃO. DESSA FORMA, TAIS INVESTIMENTOS NA INFRAESTRUTURA DA ORGANIZAÇÃO MILITAR CONTRIBUIRÃO PARA MELHORAR OS SERVIÇOS À POPULAÇÃO, FACILITARÃO AS MANOBRAS DE LANÇAMENTO DAS EMBARCAÇÕES EMPREGADAS NOS CURSOS DO ENSINO PROFISSIONAL MARÍTIMO E NAS INSPEÇÕES NAVAIS, PARTICULARMENTE NO PERÍODO DE SECA.
A11: 13 | B11: DEFESA | C11: 18670012 | D11: INDIVIDUAL | E11: ACRÉSCIMO - APROPRIAÇÃO | F11: 1867 | G11: LUIZ CARLOS HAULY | H11: DEPUTADO FEDERAL | I11: PR | J11: PODE | K11: 52000 | L11: MINISTÉRIO DA DEFESA | M11: 52932 | N11: FUNDO DE DESENVOLVIMENTO DO ENSINO PROFISSIONAL MARÍTIMO | O11: 05.363.6111.2510.0001 | P11: DEFESA NACIONAL | Q11: ENSINO PROFISSIONAL | R11: COOPERAÇÃO DA DEFESA PARA O DESENVOLVIMENTO NACIONAL | S11: PRESTAÇÃO DE ENSINO PROFISSIONAL MARÍTIMO | T11: NACIONAL | U11: NA | V11: NACIONAL | W11: F | X11: 4 | Y11: 90 | Z11: 0 | AA11: 6 | AB11: 1000 | AC11: 150000 | AD11: DELEGACIA FLUVIAL DE GUAÍRA - DELGUAIRA_x000D_ CNPJ: 00.394.502/0349-87_x000D_ _x000D_ A DELEGACIA FLUVIAL DE GUAÍRA POSSUI UMA ÁREA DE JURISDIÇÃO QUE ABRANGE 166 MUNICÍPIOS DO NORTE E DO OESTE DO ESTADO DO PARANÁ E TEM COMO PRINCIPAIS MALHAS HÍDRICAS OS RIOS PARANÁ, PARANAPANEMA, TIBAGI, IVAÍ E PIQUIRI, ALÉM DO LAGO IGAPÓ, EM LONDRINA. SÃO REALIZADOS, EM MÉDIA, 5 CURSOS ESPECIAIS PARA TRIPULANTES DO SERVIÇO PÚBLICO (ETSP), EM QUE SE FAZ NECESSÁRIA AULAS PRÁTICAS SOBRE CONDUÇÃO DE MOTO AQUÁTICA, COM A FORMAÇÃO DE CERCA DE 150 ALUNOS/ANO. ATUALMENTE, A DELEGACIA POSSUI DUAS MOTO AQUÁTICAS, JÁ BASTANTE USADAS, PARA EMPREGO TANTO EM AÇÕES DE FISCALIZAÇÃO, QUANTO DE INSTRUÇÃO E BUSCA E SALVAMENTO. A AQUISIÇÃO DE UMA NOVA EMBARCAÇÃO AMPLIARIA A CAPACIDADE DE ATENDIMENTO AOS CURSOS PROGRAMADOS, BEM COMO ÀS AÇÕES DE FISCALIZAÇÃO DO TRÁFEGO AQUAVIÁRIO E BUSCA E SALVAMENTO NA GRANDE MALHA HÍDRICA PRESENTE NA JURISDIÇÃO DA DELEGACIA FLUVIAL DE GUAÍRA.
A12: 13 | B12: DEFESA | C12: 18670014 | D12: INDIVIDUAL | E12: ACRÉSCIMO - APROPRIAÇÃO | F12: 1867 | G12: LUIZ CARLOS HAULY | H12: DEPUTADO FEDERAL | I12: PR | J12: PODE | K12: 52000 | L12: MINISTÉRIO DA DEFESA | M12: 52931 | N12: FUNDO NAVAL | O12: 05.125.6112.21BY.0001 | P12: DEFESA NACIONAL | Q12: NORMATIZAÇÃO E FISCALIZAÇÃO | R12: DEFESA NACIONAL | S12: FISCALIZAÇÃO DA NAVEGAÇÃO AQUAVIÁRIA | T12: NACIONAL | U12: NA | V12: NACIONAL | W12: F | X12: 4 | Y12: 90 | Z12: 0 | AA12: 6 | AB12: 1000 | AC12: 350000 | AD12: DELEGACIA FLUVIAL DE GUAÍRA - DELGUAIRA_x000D_ CNPJ: 00.394.502/0349-87_x000D_ _x000D_ A VIATURA VISA ATENDER A DEMANDA DE TRABALHO NA ÁREA DE JURISDIÇÃO DA DELEGACIA FLUVIAL GUAÍRA, QUE ABRANGE 166 MUNICÍPIOS DO NORTE E DO OESTE DO ESTADO DO PARANÁ E TEM COMO PRINCIPAIS MALHAS HÍDRICAS OS RIOS PARANÁ, PARANAPANEMA, TIBAGI, IVAÍ E PIQUIRI, ALÉM DO LAGO IGAPÓ, EM LONDRINA. TAMBÉM, CABE DESTACAR QUE A AQUISIÇÃO DE UMA VIATURA NOVA, ALÉM DE PROVER UM MELHOR ATENDIMENTO À COMUNIDADE NÁUTICA LOCAL, CONTRIBUIRÁ COM A RENOVAÇÃO DA FROTA ATUAL, COMPOSTA POR VEÍCULOS COM ALTA QUILOMETRAGEM, QUE EXIGEM GASTOS EXPRESSIVOS DE MANUTENÇÃO E QUE ENCONTRAM-SE COM A VIDA ÚTIL VENCIDA, EM VIRTUDE DOS DESLOCAMENTOS CONSTANTES PARA O POSTO AVANÇADO EM LONDRINA.
A13: 13 | B13: DEFESA | C13: 18670017 | D13: INDIVIDUAL | E13: ACRÉSCIMO - APROPRIAÇÃO | F13: 1867 | G13: LUIZ CARLOS HAULY | H13: DEPUTADO FEDERAL | I13: PR | J13: PODE | K13: 52000 | L13: MINISTÉRIO DA DEFESA | M13: 52932 | N13: FUNDO DE DESENVOLVIMENTO DO ENSINO PROFISSIONAL MARÍTIMO | O13: 05.363.6111.2510.0001 | P13: DEFESA NACIONAL | Q13: ENSINO PROFISSIONAL | R13: COOPERAÇÃO DA DEFESA PARA O DESENVOLVIMENTO NACIONAL | S13: PRESTAÇÃO DE ENSINO PROFISSIONAL MARÍTIMO | T13: NACIONAL | U13: NA | V13: NACIONAL | W13: F | X13: 4 | Y13: 90 | Z13: 0 | AA13: 6 | AB13: 1000 | AC13: 500000 | AD13: DELEGACIA FLUVIAL DE GUAÍRA - DELGUAIRA_x000D_ CNPJ: 00.394.502/0349-87_x000D_ _x000D_ A CONSTRUÇÃO VISA ATENDER A DEMANDA DE TRABALHO DA DELEGACIA FLUVIAL GUAÍRA, NO QUE TANGE AO ENSINO PROFISSIONAL MARÍTIMO. A DELEGACIA NÃO DISPÕE DE UMA SALA DE AULA/AUDITÓRIO ADEQUADO PARA MINISTRAR OS CURSOS DE FORMAÇÃO FLUVIÁRIOS, PESCADORES E PROFISSIONAIS DAS FORÇAS DE SEGURANÇA. COM ISSO, O PROJETO PRIORIZA ATENDER UM MAIOR NÚMERO POSSÍVEL DE AQUAVIÁRIOS PERTENCENTES À COMUNIDADE LOCAL, BEM COMO ATENDER AS NECESSIDADES DE AMPLIAÇÃO DE ALOJAMENTOS PARA A TRIPULAÇÃO DA DELEGACIA NA PARTE SUPERIOR. O RECURSO INDICADO PELO DEPUTADO FEDERAL LUIZ CARLOS HAULY, CONTEMPLARIA AS SEGUINTES FASES DA CONSTRUÇÃO: 1 -TERRAPLANAGEM: PREPARAÇÃO DO TERRENO PARA NIVELAMENTO E REMOÇÃO DE MATERIAIS INADEQUADOS, 2 - FUNDAÇÕES: ESCAVAÇÃO PARA FUNDAÇÕES PROFUNDAS (SAPATAS CORRIDAS, ESTACAS) OU RASAS (VIGAS BALDRAMES) E CONCRETAGEM DAS FUNDAÇÕES COM O USO DE FORMAS E ARMAÇÃO, 3 - ESTRUTURAÇÃO VERTICAL: CONSTRUÇÃO DE PILARES E VIGAS CONFORME PROJETO ESTRUTURAL E UTILIZAÇÃO DE FORMAS PARA CONCRETAGEM DAS ESTRUTURAS, 4 - LAJES: INSTALAÇÃO DE FORMAS PARA LAJES ENTRE OS ANDARES E CONCRETAGEM DAS LAJES COM O USO DE BOMBAS DE CONCRETO, 5 - ALVENARIA E INSTALAÇÕES: LEVANTAMENTO DE PAREDES EXTERNAS E INTERNAS, UTILIZANDO TIJOLOS, BLOCOS OU OUTROS MATERIAIS CONFORME PROJETO.
A14: 13 | B14: DEFESA | C14: 20830008 | D14: INDIVIDUAL | E14: INCLUSÃO - APROPRIAÇÃO | F14: 2083 | G14: ANDRÉ FIGUEIREDO | H14: DEPUTADO FEDERAL | I14: CE | J14: PDT | K14: 52000 | L14: MINISTÉRIO DA DEFESA | M14: 52931 | N14: FUNDO NAVAL | O14: 05.125.6112.21BY.0023 | P14: DEFESA NACIONAL | Q14: NORMATIZAÇÃO E FISCALIZAÇÃO | R14: DEFESA NACIONAL | S14: FISCALIZAÇÃO DA NAVEGAÇÃO AQUAVIÁRIA | T14: NO ESTADO DO CEARÁ | U14: CE | V14: CEARÁ | W14: F | X14: 4 | Y14: 90 | Z14: 0 | AA14: 6 | AB14: 1000 | AC14: 100000 | AD14: AUXILIAR A CAPITANIA DOS PORTOS NO CEARA A DESENVOLVER SUAS ATIVIDADES DE PROTEÇÃO E FISCALIZAÇÃO
A15: 13 | B15: DEFESA | C15: 20830012 | D15: INDIVIDUAL | E15: INCLUSÃO - APROPRIAÇÃO | F15: 2083 | G15: ANDRÉ FIGUEIREDO | H15: DEPUTADO FEDERAL | I15: CE | J15: PDT | K15: 52000 | L15: MINISTÉRIO DA DEFESA | M15: 52121 | N15: COMANDO DO EXÉRCITO | O15: 05.153.6112.21A0.0023 | P15: DEFESA NACIONAL | Q15: DEFESA TERRESTRE | R15: DEFESA NACIONAL | S15: APRESTAMENTO DAS FORÇAS - MANUTENÇÃO DA PRONTIDÃO E DA CAPACIDADE OPERATIVA | T15: NO ESTADO DO CEARÁ | U15: CE | V15: CEARÁ | W15: F | X15: 3 | Y15: 90 | Z15: 0 | AA15: 6 | AB15: 1000 | AC15: 100000 | AD15: MELHORAR AS INSTALAÇÕES DO NÚCLEO DE PREPARAÇÃO DE OFICIAIS DA RESERVA 23º BATALHÃO DE CAÇADORES, BEM COMO ADQUIRIR MOBILIARIA VOLTADA PARA A MODERNIZAÇÃO DE ENSINO | AE15: 23º BC | AF15: Melhorar as instalações do NPOR
A16: 13 | B16: DEFESA | C16: 22100001 | D16: INDIVIDUAL | E16: INCLUSÃO - APROPRIAÇÃO | F16: 2210 | G16: ESPERIDIÃO AMIN | H16: SENADOR | I16: SC | J16: PP | K16: 52000 | L16: MINISTÉRIO DA DEFESA | M16: 52111 | N16: COMANDO DA AERONÁUTICA | O16: 05.122.0032.2000.0042 | P16: DEFESA NACIONAL | Q16: ADMINISTRAÇÃO GERAL | R16: PROGRAMA DE GESTÃO E MANUTENÇÃO DO PODER EXECUTIVO | S16: ADMINISTRAÇÃO DA UNIDADE | T16: NO ESTADO DE SANTA CATARINA | U16: SC | V16: SANTA CATARINA | W16: F | X16: 3 | Y16: 90 | Z16: 0 | AA16: 6 | AB16: 1000 | AC16: 200000 | AD16: CNPJ PARA LANÇAMENTO NO SIOP: 00.394.429/0001-00 - COMANDO DA AERONÁUTICA_x000D_ _x000D_ UNIDADE BENEFICIADA: BASE AÉREA DE FLORIANÓPOLIS - BAFL_x000D_ _x000D_ CUSTEIO PARA ATENDER 120 CRIANÇAS NO PROGRAMA FORÇAS NO ESPORTE (PROFESP)._x000D_ HOTEL DE FORMAÇÃO
A17: 13 | B17: DEFESA | C17: 22100001 | D17: INDIVIDUAL | E17: INCLUSÃO - APROPRIAÇÃO | F17: 2210 | G17: ESPERIDIÃO AMIN | H17: SENADOR | I17: SC | J17: PP | K17: 52000 | L17: MINISTÉRIO DA DEFESA | M17: 52111 | N17: COMANDO DA AERONÁUTICA | O17: 05.122.0032.2000.0042 | P17: DEFESA NACIONAL | Q17: ADMINISTRAÇÃO GERAL | R17: PROGRAMA DE GESTÃO E MANUTENÇÃO DO PODER EXECUTIVO | S17: ADMINISTRAÇÃO DA UNIDADE | T17: NO ESTADO DE SANTA CATARINA | U17: SC | V17: SANTA CATARINA | W17: F | X17: 4 | Y17: 90 | Z17: 0 | AA17: 6 | AB17: 1000 | AC17: 300000 | AD17: CNPJ PARA LANÇAMENTO NO SIOP: 00.394.429/0001-00 - COMANDO DA AERONÁUTICA_x000D_ _x000D_ UNIDADE BENEFICIADA: BASE AÉREA DE FLORIANÓPOLIS - BAFL_x000D_ _x000D_ CUSTEIO PARA ATENDER 120 CRIANÇAS NO PROGRAMA FORÇAS NO ESPORTE (PROFESP)._x000D_ HOTEL DE FORMAÇÃO
A18: 13 | B18: DEFESA | C18: 22100002 | D18: INDIVIDUAL | E18: ACRÉSCIMO - APROPRIAÇÃO | F18: 2210 | G18: ESPERIDIÃO AMIN | H18: SENADOR | I18: SC | J18: PP | K18: 52000 | L18: MINISTÉRIO DA DEFESA | M18: 52131 | N18: COMANDO DA MARINHA | O18: 05.152.6112.219D.0001 | P18: DEFESA NACIONAL | Q18: DEFESA NAVAL | R18: DEFESA NACIONAL | S18: ADEQUAÇÃO DE ATIVOS DE INFRAESTRUTURA DAS ORGANIZAÇÕES MILITARES | T18: NACIONAL | U18: NA | V18: NACIONAL | W18: F | X18: 3 | Y18: 90 | Z18: 0 | AA18: 6 | AB18: 1000 | AC18: 700000 | AD18: CAPITANIA DOS PORTOS DE SANTA CATARINA - CPSC_x000D_ CNPJ: 00.394.502/0048-08_x000D_ _x000D_ A PRESENTE PROPOSTA TEM COMO OBJETIVOS:_x000D_ 1 - RECUPERAR PARTE DO FORTE SANTA BÁRBARA, DA CASA DE APOIO E DO AUDITÓRIO AMAZÔNIA AZUL, ALÉM DE ADAPTAR O MUSEU DE ARQUEOLOGIA SUBAQUÁTICA._x000D_ O FORTE SANTA BÁRBARA ABRIGA O CENTRO CULTURAL DA MARINHA EM SANTA CATARINA, SENDO ESTE UM IMPORTANTE ATRATIVO CULTURAL, TURÍSTICO E EDUCACIONAL, QUE BUSCA DISSEMINAR A MENTALIDADE MARÍTIMA E OFERECENDO UMA OPÇÃO CULTURAL E DE LAZER PARA A POPULAÇÃO CATARINENSE. DESDE SUA ABERTURA EM 2016, O CENTRO RECEBEU MAIS DE 28.000 VISITANTES E DESEMPENHA UM PAPEL SIGNIFICATIVO NA DIVULGAÇÃO DA HISTÓRIA, DA MENTALIDADE MARÍTIMA E DAS TRADIÇÕES MARINHEIRAS. NO ENTANTO, AS EDIFICAÇÕES DO CENTRO ESTÃO BASTANTE DEGRADADAS E HÁ UMA FALTA DE ACESSIBILIDADE ADEQUADA PARA PESSOAS COM NECESSIDADES ESPECIAIS. A REVITALIZAÇÃO PERMITIRÁ A PRESERVAÇÃO DO PATRIMÔNIO HISTÓRICO E CULTURAL, GARANTIRÁ A INTEGRIDADE E A SEGURANÇA DOS VISITANTES, ESTIMULARÁ O TURISMO E FOMENTARÁ A ECONOMIA LOCAL._x000D_ 2 - RECUPERAR E REVITALIZAR AS INSTALAÇÕES DO CASARÃO DA ILHA DO ARVOREDO E SUAS ADJACÊNCIAS, ALÉM DA MANUTENÇÃO DOS SINAIS NÁUTICOS._x000D_ CONSIDERANDO A IMPORTÂNCIA DOS AUXÍLIOS À NAVEGAÇÃO PARA O DESENVOLVIMENTO DAS ATIVIDADES MARÍTIMAS, É NECESSÁRIO GARANTIR O PLENO FUNCIONAMENTO DOS DIVERSOS FARÓIS E FAROLETES AO LONGO DA COSTA CATARINENSE, QUE CONFEREM SEGURANÇA À NAVEGAÇÃO PARA A COMUNIDADE MARÍTIMA. O INVESTIMENTO VISA ASSEGURAR A CONTINUIDADE E A EFICÁCIA DESSES DISPOSITIVOS DE SEGURANÇA.
A19: 13 | B19: DEFESA | C19: 22100002 | D19: INDIVIDUAL | E19: ACRÉSCIMO - APROPRIAÇÃO | F19: 2210 | G19: ESPERIDIÃO AMIN | H19: SENADOR | I19: SC | J19: PP | K19: 52000 | L19: MINISTÉRIO DA DEFESA | M19: 52131 | N19: COMANDO DA MARINHA | O19: 05.152.6112.219D.0001 | P19: DEFESA NACIONAL | Q19: DEFESA NAVAL | R19: DEFESA NACIONAL | S19: ADEQUAÇÃO DE ATIVOS DE INFRAESTRUTURA DAS ORGANIZAÇÕES MILITARES | T19: NACIONAL | U19: NA | V19: NACIONAL | W19: F | X19: 4 | Y19: 90 | Z19: 0 | AA19: 6 | AB19: 1000 | AC19: 650000 | AD19: CAPITANIA DOS PORTOS DE SANTA CATARINA - CPSC_x000D_ CNPJ: 00.394.502/0048-08_x000D_ _x000D_ A PRESENTE PROPOSTA TEM COMO OBJETIVOS:_x000D_ 1 - RECUPERAR PARTE DO FORTE SANTA BÁRBARA, DA CASA DE APOIO E DO AUDITÓRIO AMAZÔNIA AZUL, ALÉM DE ADAPTAR O MUSEU DE ARQUEOLOGIA SUBAQUÁTICA._x000D_ O FORTE SANTA BÁRBARA ABRIGA O CENTRO CULTURAL DA MARINHA EM SANTA CATARINA, SENDO ESTE UM IMPORTANTE ATRATIVO CULTURAL, TURÍSTICO E EDUCACIONAL, QUE BUSCA DISSEMINAR A MENTALIDADE MARÍTIMA E OFERECENDO UMA OPÇÃO CULTURAL E DE LAZER PARA A POPULAÇÃO CATARINENSE. DESDE SUA ABERTURA EM 2016, O CENTRO RECEBEU MAIS DE 28.000 VISITANTES E DESEMPENHA UM PAPEL SIGNIFICATIVO NA DIVULGAÇÃO DA HISTÓRIA, DA MENTALIDADE MARÍTIMA E DAS TRADIÇÕES MARINHEIRAS. NO ENTANTO, AS EDIFICAÇÕES DO CENTRO ESTÃO BASTANTE DEGRADADAS E HÁ UMA FALTA DE ACESSIBILIDADE ADEQUADA PARA PESSOAS COM NECESSIDADES ESPECIAIS. A REVITALIZAÇÃO PERMITIRÁ A PRESERVAÇÃO DO PATRIMÔNIO HISTÓRICO E CULTURAL, GARANTIRÁ A INTEGRIDADE E A SEGURANÇA DOS VISITANTES, ESTIMULARÁ O TURISMO E FOMENTARÁ A ECONOMIA LOCAL._x000D_ 2 - RECUPERAR E REVITALIZAR AS INSTALAÇÕES DO CASARÃO DA ILHA DO ARVOREDO E SUAS ADJACÊNCIAS, ALÉM DA MANUTENÇÃO DOS SINAIS NÁUTICOS._x000D_ CONSIDERANDO A IMPORTÂNCIA DOS AUXÍLIOS À NAVEGAÇÃO PARA O DESENVOLVIMENTO DAS ATIVIDADES MARÍTIMAS, É NECESSÁRIO GARANTIR O PLENO FUNCIONAMENTO DOS DIVERSOS FARÓIS E FAROLETES AO LONGO DA COSTA CATARINENSE, QUE CONFEREM SEGURANÇA À NAVEGAÇÃO PARA A COMUNIDADE MARÍTIMA. O INVESTIMENTO VISA ASSEGURAR A CONTINUIDADE E A EFICÁCIA DESSES DISPOSITIVOS DE SEGURANÇA.
A20: 13 | B20: DEFESA | C20: 22100004 | D20: INDIVIDUAL | E20: ACRÉSCIMO - APROPRIAÇÃO | F20: 2210 | G20: ESPERIDIÃO AMIN | H20: SENADOR | I20: SC | J20: PP | K20: 52000 | L20: MINISTÉRIO DA DEFESA | M20: 52121 | N20: COMANDO DO EXÉRCITO | O20: 05.153.6112.20XE.0001 | P20: DEFESA NACIONAL | Q20: DEFESA TERRESTRE | R20: DEFESA NACIONAL | S20: MANUTENÇÃO E MODERNIZAÇÃO DE SISTEMAS DE COMANDO E CONTROLE DO EXÉRCITO | T20: NACIONAL | U20: NA | V20: NACIONAL | W20: F | X20: 4 | Y20: 90 | Z20: 0 | AA20: 6 | AB20: 1000 | AC20: 300000 | AD20: BENEFICIÁRIO PARA LANÇAMENTO NO SIOP - CNPJ: 00.394.452/0001-03_x000D_ MELHORAR O SISTEMA DE SEGURANÇA DO 63º BATALHÃO DE INFANTARIA, EM FLORIANÓPOLIS/SC. | AE20: 63º BI | AF20: Aquisição de equipamentos de vigilância
A21: 13 | B21: DEFESA | C21: 22630009 | D21: INDIVIDUAL | E21: INCLUSÃO - APROPRIAÇÃO | F21: 2263 | G21: JADER BARBALHO | H21: SENADOR | I21: PA | J21: MDB | K21: 52000 | L21: MINISTÉRIO DA DEFESA | M21: 52121 | N21: COMANDO DO EXÉRCITO | O21: 05.368.6112.21GP.0269 | P21: DEFESA NACIONAL | Q21: EDUCAÇÃO BÁSICA | R21: DEFESA NACIONAL | S21: FUNCIONAMENTO DOS ESTABELECIMENTOS DE EDUCAÇÃO BÁSICA MILITARES DO MINISTÉRIO DA DEFESA | T21: NO MUNICÍPIO DE BELÉM - PA | U21: PA | V21: BELÉM | W21: F | X21: 3 | Y21: 90 | Z21: 0 | AA21: 6 | AB21: 1000 | AC21: 500000 | AD21: ATENDER ÀS NECESSIDADES DOS ALUNOS E DO CORPO PERMANENTE PARA MOBILIAR AS SALAS DE AULA COM EQUIPAMENTOS AUDIOVISUAIS, ALÉM DE REALIZAR A MANUTENÇÃO EM MOBILIÁRIO, DO COLÉGIO MILITAR DE BELÉM/PA, DANIFICADO PELO USO._x000D_ BENEFICIÁRIO PARA LANÇAMENTO NO SIOP - CNPJ: 00.394.452/0001-03 | AE21: CMBel | AF21: Mobiliar as salas de aula com equipamentos audiovisuais, além de realizar a manutenção em mobiliário.
A22: 13 | B22: DEFESA | C22: 22630010 | D22: INDIVIDUAL | E22: INCLUSÃO - APROPRIAÇÃO | F22: 2263 | G22: JADER BARBALHO | H22: SENADOR | I22: PA | J22: MDB | K22: 52000 | L22: MINISTÉRIO DA DEFESA | M22: 52911 | N22: FUNDO AERONÁUTICO | O22: 05.368.6112.21GP.0015 | P22: DEFESA NACIONAL | Q22: EDUCAÇÃO BÁSICA | R22: DEFESA NACIONAL | S22: FUNCIONAMENTO DOS ESTABELECIMENTOS DE EDUCAÇÃO BÁSICA MILITARES DO MINISTÉRIO DA DEFESA | T22: NO ESTADO DO PARÁ | U22: PA | V22: PARÁ | W22: F | X22: 3 | Y22: 90 | Z22: 0 | AA22: 6 | AB22: 1000 | AC22: 500000 | AD22: EMENDA DESTINADA PARA A READEQUAÇÃO DO AUDITÓRIO "OLÍVIA BASTOS" DO COLÉGIO TENENTE RÊGO BARROS_x000D_ _x000D_ CNPJ PARA LANÇAMENTO NO SIOP: 00.394.429/0001-00 - COMANDO DA AERONÁUTICA_x000D_ UNIDADE BENEFICIADA: COLÉGIO TENENTE RÊGO BARROS - CTRB
A23: 13 | B23: DEFESA | C23: 22630012 | D23: INDIVIDUAL | E23: INCLUSÃO - APROPRIAÇÃO | F23: 2263 | G23: JADER BARBALHO | H23: SENADOR | I23: PA | J23: MDB | K23: 52000 | L23: MINISTÉRIO DA DEFESA | M23: 52931 | N23: FUNDO NAVAL | O23: 05.125.6112.21BY.0015 | P23: DEFESA NACIONAL | Q23: NORMATIZAÇÃO E FISCALIZAÇÃO | R23: DEFESA NACIONAL | S23: FISCALIZAÇÃO DA NAVEGAÇÃO AQUAVIÁRIA | T23: NO ESTADO DO PARÁ | U23: PA | V23: PARÁ | W23: F | X23: 4 | Y23: 90 | Z23: 0 | AA23: 6 | AB23: 1000 | AC23: 500000 | AD23: EMENDA PARA AQUISIÇÃO DE MEIOS (LANÇHAS E VIATURAS) E EQUIPAMENTOS UTILIZADOS NO RESGATE DE PESSOAS QUE TENHAM DESAPARECIDO NAS ÁGUAS DOS RIOS OU DO MAR, NO ESTADO DO PARÁ._x000D_ BENEFICIÁRIO: COMANDO DA MARINHA (CAPITANIA DOS PORTOS DA AMAZÔNIA ORIENTAL)_x000D_ CNPJ: 11.340.225/0001-03
A24: 13 | B24: DEFESA | C24: 24290002 | D24: INDIVIDUAL | E24: ACRÉSCIMO - APROPRIAÇÃO | F24: 2429 | G24: LÁZARO BOTELHO | H24: DEPUTADO FEDERAL | I24: TO | J24: PP | K24: 52000 | L24: MINISTÉRIO DA DEFESA | M24: 52131 | N24: COMANDO DA MARINHA | O24: 05.152.6112.219D.0001 | P24: DEFESA NACIONAL | Q24: DEFESA NAVAL | R24: DEFESA NACIONAL | S24: ADEQUAÇÃO DE ATIVOS DE INFRAESTRUTURA DAS ORGANIZAÇÕES MILITARES | T24: NACIONAL | U24: NA | V24: NACIONAL | W24: F | X24: 4 | Y24: 90 | Z24: 0 | AA24: 6 | AB24: 1000 | AC24: 300000 | AD24: CAPITANIA FLUVIAL DO ARAGUAIA-TOCANTINS - CFAT_x000D_ CNPJ: 00.394.502/0109-64_x000D_ NECESSIDADE DE ORGANIZAÇÃO DAS EMBARCAÇÕES DA CAPITANIA FLUVIAL DO ARAGUAIA TOCANTINS EM ESTRUTURA ADEQUADA, INCLUINDO AS EMBARCAÇÕES UTILIZADAS NO STA E AS DO PROGRAMA FORÇAS DO ESPORTE.
A25: 13 | B25: DEFESA | C25: 24410003 | D25: INDIVIDUAL | E25: INCLUSÃO - APROPRIAÇÃO | F25: 2441 | G25: JOSÉ AIRTON FÉLIX CIRILO | H25: DEPUTADO FEDERAL | I25: CE | J25: PT | K25: 52000 | L25: MINISTÉRIO DA DEFESA | M25: 52131 | N25: COMANDO DA MARINHA | O25: 05.152.6112.219D. | P25: DEFESA NACIONAL | Q25: DEFESA NAVAL | R25: DEFESA NACIONAL | S25: ADEQUAÇÃO DE ATIVOS DE INFRAESTRUTURA DAS ORGANIZAÇÕES MILITARES | T25: REFORMA DO TELHADO DA CAPITANIA DOS PORTOS EM ARACATI - NO ESTADO DO CEARÁ | U25: CE | V25: CEARÁ | W25: F | X25: 4 | Y25: 90 | Z25: 0 | AA25: 6 | AB25: 1000 | AC25: 100000 | AD25: ADEQUAÇÃO DE ATIVOS DE INFRAESTRUTURA DAS ORGANIZAÇÕES MILITARES - REFORMA DO TELHADO DA CAPITANIA DOS PORTOS DE ARACATI
A26: 13 | B26: DEFESA | C26: 24680024 | D26: INDIVIDUAL | E26: INCLUSÃO - APROPRIAÇÃO | F26: 2468 | G26: LÍDICE DA MATA | H26: DEPUTADO FEDERAL | I26: BA | J26: PSB | K26: 52000 | L26: MINISTÉRIO DA DEFESA | M26: 52131 | N26: COMANDO DA MARINHA | O26: 05.152.6112.219D.0029 | P26: DEFESA NACIONAL | Q26: DEFESA NAVAL | R26: DEFESA NACIONAL | S26: ADEQUAÇÃO DE ATIVOS DE INFRAESTRUTURA DAS ORGANIZAÇÕES MILITARES | T26: NO ESTADO DA BAHIA | U26: BA | V26: BAHIA | W26: F | X26: 4 | Y26: 99 | Z26: 0 | AA26: 6 | AB26: 1000 | AC26: 100000 | AD26: ESSA EMENDA VIS A ADEQUAÇÃO DE ATIVOS DE INFRAESTRUTURA DAS ORGANIZAÇÕES MILITARES.
A27: 13 | B27: DEFESA | C27: 24710008 | D27: INDIVIDUAL | E27: ACRÉSCIMO - APROPRIAÇÃO | F27: 2471 | G27: SÉRGIO BRITO | H27: DEPUTADO FEDERAL | I27: BA | J27: PSD | K27: 52000 | L27: MINISTÉRIO DA DEFESA | M27: 52121 | N27: COMANDO DO EXÉRCITO | O27: 05.153.6112.219D.0001 | P27: DEFESA NACIONAL | Q27: DEFESA TERRESTRE | R27: DEFESA NACIONAL | S27: ADEQUAÇÃO DE ATIVOS DE INFRAESTRUTURA DAS ORGANIZAÇÕES MILITARES | T27: NACIONAL | U27: NA | V27: NACIONAL | W27: F | X27: 4 | Y27: 90 | Z27: 0 | AA27: 6 | AB27: 1000 | AC27: 500000 | AD27: BENEFICIÁRIO PARA LANÇAMENTO NO SIOP - CNPJ: 00.394.452/0001-03_x000D_ CONCLUIR A REFORMA DAS INSTALAÇÕES DO 4º BATALHÃO DE ENGENHARIA DE CONSTRUÇÃO, EM BARREIRAS/BA, PARTICULARMENTE AS OFICINAS MECÂNICAS, PERMITINDO MELHORAR A FORMAÇÃO DE MILITARES E DE MÃO DE OBRA ESPECIALIZADA PARA O SERVIÇO MILITAR E PARA A SOCIEDADE._x000D_ ALÉM DE MELHORAR O REFEITÓRIO DE SUBTENENTES E SARGENTOS E OUTRAS INSTALAÇÕES PARA MELHOR ATENDER AO PÚBLICO INTERNO. | AE27: 4º BEC | AF27: Concluir a reforma das oficinas mecânicas e melhorar o refeitório de subtenentes e sargentos e outras instalações.
A28: 13 | B28: DEFESA | C28: 24820007 | D28: INDIVIDUAL | E28: ACRÉSCIMO - APROPRIAÇÃO | F28: 2482 | G28: LUIZ FERNANDO FARIA | H28: DEPUTADO FEDERAL | I28: MG | J28: PSD | K28: 52000 | L28: MINISTÉRIO DA DEFESA | M28: 52121 | N28: COMANDO DO EXÉRCITO | O28: 05.153.6112.21A0.0001 | P28: DEFESA NACIONAL | Q28: DEFESA TERRESTRE | R28: DEFESA NACIONAL | S28: APRESTAMENTO DAS FORÇAS - MANUTENÇÃO DA PRONTIDÃO E DA CAPACIDADE OPERATIVA | T28: NACIONAL | U28: NA | V28: NACIONAL | W28: F | X28: 4 | Y28: 90 | Z28: 0 | AA28: 6 | AB28: 1000 | AC28: 450000 | AD28: BENEFICIÁRIO PARA LANÇAMENTO NO SIOP - CNPJ: 00.394.452/0001-03_x000D_ APOIAR O TRANSPORTE DOS MILITARES DO 4º ESQUADRÃO DE CAVALARIA MECANIZADO, EM SANTOS DUMONT/MG, PARA A REALIZAÇÃO DE AÇÕES CÍVICO-SOCIAIS (ACISO) OU EM AÇÕES JUNTO À DEFESA CIVIL E ÀS AUTORIDADES CIVIS QUE NECESSITEM DE APOIO, ALÉM DE APOIAR CRIANÇAS PERTENCENTES A PROJETOS SOCIAIS. | AE28: 4º Esqd C Mec | AF28: Aquisição de Vtr van 16 lugares
A29: 13 | B29: DEFESA | C29: 25170004 | D29: INDIVIDUAL | E29: INCLUSÃO - APROPRIAÇÃO | F29: 2517 | G29: VINICIUS CARVALHO | H29: DEPUTADO FEDERAL | I29: SP | J29: REPUBLICANOS | K29: 52000 | L29: MINISTÉRIO DA DEFESA | M29: 52131 | N29: COMANDO DA MARINHA | O29: 05.152.6112.219D. | P29: DEFESA NACIONAL | Q29: DEFESA NAVAL | R29: DEFESA NACIONAL | S29: ADEQUAÇÃO DE ATIVOS DE INFRAESTRUTURA DAS ORGANIZAÇÕES MILITARES | T29: 89321 - DELEGACIA FLUVIAL DE PRESIDENTE EPITÁCIO -CNPJ 00.394.502/0433-82 - NO ESTADO DE SÃO PAULO | U29: SP | V29: SÃO PAULO | W29: F | X29: 3 | Y29: 90 | Z29: 0 | AA29: 6 | AB29: 1000 | AC29: 160000 | AD29: CONTRATAÇÃO DO SERVIÇO DE REFORMA DO GRUPO DE ATENDIMENTO AO PÚBLICO (GAP) E PÁTIO INTERNO. AQUISIÇÃO DE MOBILIÁRIO EM GERAL, COMPUTADORES E SEUS PERIFÉRICOS EM PROVEITO DAS ATIVIDADES DE SEGURANÇA DO TRAFICO AQUAVIÁRIO E ENSINO PROFISSIONAL MARÍTIMO. A MODERNIZAÇÃO DA INSTALAÇÃO PERMITIRÁ QUE O PÚBLICO ATENDIDO, NÃO ESTEJA SUJEITO ÀS INTEMPÉRIES QUE A REGIÃO PROPORCIONA , BEM COMO UM ATENDIMENTO MAIS ADEQUADO. ALÉM DISSO REFORÇARÁ A SEGURANÇA ORGÂNICA, LIMITANDO TOTALMENTE O ACESSO DE PESSOAS ESTRANHAS
A30: 13 | B30: DEFESA | C30: 25170004 | D30: INDIVIDUAL | E30: INCLUSÃO - APROPRIAÇÃO | F30: 2517 | G30: VINICIUS CARVALHO | H30: DEPUTADO FEDERAL | I30: SP | J30: REPUBLICANOS | K30: 52000 | L30: MINISTÉRIO DA DEFESA | M30: 52131 | N30: COMANDO DA MARINHA | O30: 05.152.6112.219D. | P30: DEFESA NACIONAL | Q30: DEFESA NAVAL | R30: DEFESA NACIONAL | S30: ADEQUAÇÃO DE ATIVOS DE INFRAESTRUTURA DAS ORGANIZAÇÕES MILITARES | T30: 89321 - DELEGACIA FLUVIAL DE PRESIDENTE EPITÁCIO -CNPJ 00.394.502/0433-82 - NO ESTADO DE SÃO PAULO | U30: SP | V30: SÃO PAULO | W30: F | X30: 4 | Y30: 90 | Z30: 0 | AA30: 6 | AB30: 1000 | AC30: 240000 | AD30: CONTRATAÇÃO DO SERVIÇO DE REFORMA DO GRUPO DE ATENDIMENTO AO PÚBLICO (GAP) E PÁTIO INTERNO. AQUISIÇÃO DE MOBILIÁRIO EM GERAL, COMPUTADORES E SEUS PERIFÉRICOS EM PROVEITO DAS ATIVIDADES DE SEGURANÇA DO TRAFICO AQUAVIÁRIO E ENSINO PROFISSIONAL MARÍTIMO. A MODERNIZAÇÃO DA INSTALAÇÃO PERMITIRÁ QUE O PÚBLICO ATENDIDO, NÃO ESTEJA SUJEITO ÀS INTEMPÉRIES QUE A REGIÃO PROPORCIONA , BEM COMO UM ATENDIMENTO MAIS ADEQUADO. ALÉM DISSO REFORÇARÁ A SEGURANÇA ORGÂNICA, LIMITANDO TOTALMENTE O ACESSO DE PESSOAS ESTRANHAS
A31: 13 | B31: DEFESA | C31: 26010005 | D31: INDIVIDUAL | E31: INCLUSÃO - APROPRIAÇÃO | F31: 2601 | G31: MÁRCIO MARINHO | H31: DEPUTADO FEDERAL | I31: BA | J31: REPUBLICANOS | K31: 52000 | L31: MINISTÉRIO DA DEFESA | M31: 52131 | N31: COMANDO DA MARINHA | O31: 05.152.6112.219D.0029 | P31: DEFESA NACIONAL | Q31: DEFESA NAVAL | R31: DEFESA NACIONAL | S31: ADEQUAÇÃO DE ATIVOS DE INFRAESTRUTURA DAS ORGANIZAÇÕES MILITARES | T31: NO ESTADO DA BAHIA | U31: BA | V31: BAHIA | W31: F | X31: 3 | Y31: 90 | Z31: 0 | AA31: 6 | AB31: 1000 | AC31: 170000 | AD31: A REFERIDA EMENDA VISA ATENDER ÀS DEMANDAS DA DIVISÃO DE VETERANOS E PENSIONISTAS E DO NÚCLEO DE ASSISTÊNCIA SOCIAL QUE SÃO RESPONSÁVEIS PELA ASSISTÊNCIA INTEGRADA E CADASTRAMENTO ANUAL DE VETERANOS , PENSIONISTAS E SERVIDORES CIVIS.
A32: 13 | B32: DEFESA | C32: 26010005 | D32: INDIVIDUAL | E32: INCLUSÃO - APROPRIAÇÃO | F32: 2601 | G32: MÁRCIO MARINHO | H32: DEPUTADO FEDERAL | I32: BA | J32: REPUBLICANOS | K32: 52000 | L32: MINISTÉRIO DA DEFESA | M32: 52131 | N32: COMANDO DA MARINHA | O32: 05.152.6112.219D.0029 | P32: DEFESA NACIONAL | Q32: DEFESA NAVAL | R32: DEFESA NACIONAL | S32: ADEQUAÇÃO DE ATIVOS DE INFRAESTRUTURA DAS ORGANIZAÇÕES MILITARES | T32: NO ESTADO DA BAHIA | U32: BA | V32: BAHIA | W32: F | X32: 4 | Y32: 90 | Z32: 0 | AA32: 6 | AB32: 1000 | AC32: 230000 | AD32: A REFERIDA EMENDA VISA ATENDER ÀS DEMANDAS DA DIVISÃO DE VETERANOS E PENSIONISTAS E DO NÚCLEO DE ASSISTÊNCIA SOCIAL QUE SÃO RESPONSÁVEIS PELA ASSISTÊNCIA INTEGRADA E CADASTRAMENTO ANUAL DE VETERANOS , PENSIONISTAS E SERVIDORES CIVIS.
A33: 13 | B33: DEFESA | C33: 26010007 | D33: INDIVIDUAL | E33: INCLUSÃO - APROPRIAÇÃO | F33: 2601 | G33: MÁRCIO MARINHO | H33: DEPUTADO FEDERAL | I33: BA | J33: REPUBLICANOS | K33: 52000 | L33: MINISTÉRIO DA DEFESA | M33: 52131 | N33: COMANDO DA MARINHA | O33: 05.301.0032.2E74.0029 | P33: DEFESA NACIONAL | Q33: ATENÇÃO BÁSICA | R33: PROGRAMA DE GESTÃO E MANUTENÇÃO DO PODER EXECUTIVO | S33: ESTRUTURAÇÃO E MODERNIZAÇÃO DE UNIDADES DE SAÚDE DAS FORÇAS ARMADAS | T33: NO ESTADO DA BAHIA | U33: BA | V33: BAHIA | W33: S | X33: 4 | Y33: 90 | Z33: 0 | AA33: 6 | AB33: 1000 | AC33: 600000 | AD33: A PRESENTE EMENDA TEM POR OBJETO AQUISIÇÃO DE EQUIPAMENTOS DE SAÚDE PARA O SETOR DE ONCOLOGIA E A REVITALIZAÇÃO DO SISTEMA DE REFRIGERAÇÃO PARA O HOSPITAL NAVAL DE SALVADOR.
A34: 13 | B34: DEFESA | C34: 26860002 | D34: INDIVIDUAL | E34: INCLUSÃO - APROPRIAÇÃO | F34: 2686 | G34: ANTÔNIA LÚCIA | H34: DEPUTADO FEDERAL | I34: AC | J34: REPUBLICANOS | K34: 52000 | L34: MINISTÉRIO DA DEFESA | M34: 52121 | N34: COMANDO DO EXÉRCITO | O34: 05.153.6112.21A0. | P34: DEFESA NACIONAL | Q34: DEFESA TERRESTRE | R34: DEFESA NACIONAL | S34: APRESTAMENTO DAS FORÇAS - MANUTENÇÃO DA PRONTIDÃO E DA CAPACIDADE OPERATIVA | T34: COMANDO DE FRONTEIRA ACRE - 4º BATALHÃO DE INFANTARIA DE SELVA (CMDO FRON ACRE / 4º BIS) - NO ESTADO DO ACRE | U34: AC | V34: ACRE | W34: F | X34: 4 | Y34: 90 | Z34: 0 | AA34: 6 | AB34: 1000 | AC34: 300000 | AD34: A PRESENTE EMENTA DESTINA RECURSOS PARA A AQUISIÇÃO DE INSTRUMENTOS MUSICAIS DA BANDA DE MÚSICA QUE DESENVOLVE DIVERSAS ATIVIDADES INTERNAS E EXTERNAS COMO CERIMÔNIAS CÍVICAS DO ESTADO, DOS MUNICÍPIOS E DE ESCOLAS PÚBLICAS. | AE34: 4º BIS | AF34: Aquisição de instrumentos musicais
A35: 13 | B35: DEFESA | C35: 27010004 | D35: INDIVIDUAL | E35: INCLUSÃO - APROPRIAÇÃO | F35: 2701 | G35: DOMINGOS NETO | H35: DEPUTADO FEDERAL | I35: CE | J35: PSD | K35: 52000 | L35: MINISTÉRIO DA DEFESA | M35: 52121 | N35: COMANDO DO EXÉRCITO | O35: 05.153.6112.219D.0023 | P35: DEFESA NACIONAL | Q35: DEFESA TERRESTRE | R35: DEFESA NACIONAL | S35: ADEQUAÇÃO DE ATIVOS DE INFRAESTRUTURA DAS ORGANIZAÇÕES MILITARES | T35: NO ESTADO DO CEARÁ | U35: CE | V35: CEARÁ | W35: F | X35: 3 | Y35: 90 | Z35: 0 | AA35: 6 | AB35: 1000 | AC35: 380000 | AD35: A PRESENTE EMENDA VISA PROMOVER MELHORIAS DAS INSTALAÇÕES NO COLÉGIO MILITAR DE FORTALEZA. | AE35: CMF | AF35: Promover melhorias das instalações
A36: 13 | B36: DEFESA | C36: 27110011 | D36: INDIVIDUAL | E36: ACRÉSCIMO - APROPRIAÇÃO | F36: 2711 | G36: AGUINALDO RIBEIRO | H36: DEPUTADO FEDERAL | I36: PB | J36: PP | K36: 52000 | L36: MINISTÉRIO DA DEFESA | M36: 52931 | N36: FUNDO NAVAL | O36: 05.125.6112.21BY.0001 | P36: DEFESA NACIONAL | Q36: NORMATIZAÇÃO E FISCALIZAÇÃO | R36: DEFESA NACIONAL | S36: FISCALIZAÇÃO DA NAVEGAÇÃO AQUAVIÁRIA | T36: NACIONAL | U36: NA | V36: NACIONAL | W36: F | X36: 3 | Y36: 90 | Z36: 0 | AA36: 6 | AB36: 1000 | AC36: 200000 | AD36: CAPITANIA DOS PORTOS DA PARAÍBA - CPPB_x000D_ CNPJ: 00.394.502/0037-55_x000D_ _x000D_ A CAPITANIA DOS PORTOS DA PARAÍBA É RESPONSÁVEL POR FAZER CUMPRIR AS LEGISLAÇÕES NACIONAIS E INTERNACIONAIS QUE REGULAM O TRÁFEGO MARÍTIMO, FLUVIAL E LACUSTRE, NO QUE TANGE À SALVAGUARDA DA VIDA HUMANA NO MAR, À SEGURANÇA DA NAVEGAÇÃO E A PREVENÇÃO DA POLUIÇÃO HÍDRICA PROVOCADA POR EMBARCAÇÕES NO MAR ABERTO E NAS ÁREAS INTERIORES. DESSA FORMA, A PRESENTE PROPOSTA DE EMENDA PARLAMENTAR GARANTIRÁ AS MANUTENÇÕES DOS MEIOS E INSTALAÇÕES, A FIM DE ASSEGURAR O DESEMPENHO NAS ATIVIDADES DE FISCALIZAÇÃO AO LONGO DOS 138KM DE LITORAL E 134 BARRAGENS E AÇÚDES DO INTERIOR DO ESTADO, BEM COMO AMPLIAR A CAPACIDADE DE LEVAR O ENSINO PROFISSIONAL MARÍTIMO ÀS CERCA DE 78 COLÔNIAS DE PESCA EXISTENTES NA PARAÍBA.
A37: 13 | B37: DEFESA | C37: 27150013 | D37: INDIVIDUAL | E37: INCLUSÃO - APROPRIAÇÃO | F37: 2715 | G37: RUY CARNEIRO | H37: DEPUTADO FEDERAL | I37: PB | J37: PODE | K37: 52000 | L37: MINISTÉRIO DA DEFESA | M37: 52121 | N37: COMANDO DO EXÉRCITO | O37: 05.301.0032.2E74.1436 | P37: DEFESA NACIONAL | Q37: ATENÇÃO BÁSICA | R37: PROGRAMA DE GESTÃO E MANUTENÇÃO DO PODER EXECUTIVO | S37: ESTRUTURAÇÃO E MODERNIZAÇÃO DE UNIDADES DE SAÚDE DAS FORÇAS ARMADAS | T37: NO MUNICÍPIO DE JOÃO PESSOA - PB | U37: PB | V37: JOÃO PESSOA | W37: S | X37: 4 | Y37: 90 | Z37: 0 | AA37: 6 | AB37: 1000 | AC37: 100000 | AD37: BENEFICIÁRIO PARA LANÇAMENTO NO SIOP - CNPJ: 00.394.452/0001-03_x000D_ MELHORAR O APOIO DE SAÚDE AOS MILITARES DO HOSPITAL DE GUARNIÇÃO DE JOÃO PESSOA, EM JOÃO PESSOA/PB, E SEUS DEPENDENTES, EM CASO DE TRANSPORTE DE PACIENTES EM ESTADO GRAVE. | AE37: HGuJP | AF37: 1 (uma) viatura administrativa
A38: 13 | B38: DEFESA | C38: 27150015 | D38: INDIVIDUAL | E38: INCLUSÃO - APROPRIAÇÃO | F38: 2715 | G38: RUY CARNEIRO | H38: DEPUTADO FEDERAL | I38: PB | J38: PODE | K38: 52000 | L38: MINISTÉRIO DA DEFESA | M38: 52931 | N38: FUNDO NAVAL | O38: 05.125.6112.21BY.0025 | P38: DEFESA NACIONAL | Q38: NORMATIZAÇÃO E FISCALIZAÇÃO | R38: DEFESA NACIONAL | S38: FISCALIZAÇÃO DA NAVEGAÇÃO AQUAVIÁRIA | T38: NO ESTADO DA PARAÍBA | U38: PB | V38: PARAÍBA | W38: F | X38: 4 | Y38: 90 | Z38: 0 | AA38: 6 | AB38: 1000 | AC38: 100000 | AD38: CAPITANIA DOS PORTOS DA PARAIBA- CPPB_x000D_ CNPJ: 00.394.502/0037-55_x000D_ A PRESENTE EMENDA TEM COMO OBJETIVO CONTRIBUIR COM A AQUISIÇÃO DE EMBARCAÇÕES PARA REALIZAÇÃO DE FISCALIZAÇÃO DO TRAFEGO AQUAVIÁRIO,_x000D_ BEM COMO DE SOCORRO E SALVAMENTO NO MAR, PERMITINDO ASSIM QUE A CAPITANIA DOS PORTOS DA PARAÍBA POSSA REALIZAR TAIS AÇÕES EM TODA A_x000D_ EXTENSÃO DO LITORAL PARAIBANO.
A39: 13 | B39: DEFESA | C39: 27180014 | D39: INDIVIDUAL | E39: INCLUSÃO - APROPRIAÇÃO | F39: 2718 | G39: AUGUSTO COUTINHO | H39: DEPUTADO FEDERAL | I39: PE | J39: REPUBLICANOS | K39: 52000 | L39: MINISTÉRIO DA DEFESA | M39: 52931 | N39: FUNDO NAVAL | O39: 05.125.6112.21BY.0026 | P39: DEFESA NACIONAL | Q39: NORMATIZAÇÃO E FISCALIZAÇÃO | R39: DEFESA NACIONAL | S39: FISCALIZAÇÃO DA NAVEGAÇÃO AQUAVIÁRIA | T39: NO ESTADO DE PERNAMBUCO | U39: PE | V39: PERNAMBUCO | W39: F | X39: 4 | Y39: 90 | Z39: 0 | AA39: 6 | AB39: 1000 | AC39: 200000 | AD39: ESTA PROPOSTA DE EMENDA VISA A AQUISIÇÃO DE EQUIPAMENTOS PARA MELHOR DESEMPENHAR ATIVIDADES DE FISCALIZAÇÃO DA NAVEGAÇÃO AQUAVIÁRIA NO ESTADO DE PERNAMBUCO.
A40: 13 | B40: DEFESA | C40: 27180017 | D40: INDIVIDUAL | E40: INCLUSÃO - APROPRIAÇÃO | F40: 2718 | G40: AUGUSTO COUTINHO | H40: DEPUTADO FEDERAL | I40: PE | J40: REPUBLICANOS | K40: 52000 | L40: MINISTÉRIO DA DEFESA | M40: 52121 | N40: COMANDO DO EXÉRCITO | O40: 05.153.6112.219D.0026 | P40: DEFESA NACIONAL | Q40: DEFESA TERRESTRE | R40: DEFESA NACIONAL | S40: ADEQUAÇÃO DE ATIVOS DE INFRAESTRUTURA DAS ORGANIZAÇÕES MILITARES | T40: NO ESTADO DE PERNAMBUCO | U40: PE | V40: PERNAMBUCO | W40: F | X40: 4 | Y40: 90 | Z40: 0 | AA40: 6 | AB40: 1000 | AC40: 200000 | AD40: A REFERIDA EMENDA SERÁ UTILIZADA PARA ADEQUAÇÃO DE ATIVOS DE INFRAESTRUTURA DE ORGANIZAÇÕES DO CPOR - CENTRO DE PREPARAÇÃO DE OFICIAIS DA RESERVA DO ESTADO DE PERNAMBUCO. | AE40: CPOR/R | AF40: Reparar as fiações, disjuntores e redimensionar toda a rede elétrica nas instalações da OM.
A41: 13 | B41: DEFESA | C41: 27240002 | D41: INDIVIDUAL | E41: INCLUSÃO - APROPRIAÇÃO | F41: 2724 | G41: PASTOR EURICO | H41: DEPUTADO FEDERAL | I41: PE | J41: PL | K41: 52000 | L41: MINISTÉRIO DA DEFESA | M41: 52121 | N41: COMANDO DO EXÉRCITO | O41: 05.153.6112.21A0.0026 | P41: DEFESA NACIONAL | Q41: DEFESA TERRESTRE | R41: DEFESA NACIONAL | S41: APRESTAMENTO DAS FORÇAS - MANUTENÇÃO DA PRONTIDÃO E DA CAPACIDADE OPERATIVA | T41: NO ESTADO DE PERNAMBUCO | U41: PE | V41: PERNAMBUCO | W41: F | X41: 4 | Y41: 90 | Z41: 0 | AA41: 6 | AB41: 1000 | AC41: 300000 | AD41: ESTA EMENDA TEM O OBJETIVO DE MELHORAR O ATENDIMENTO MÉDICO E ATENDER ÀS DEMANDAS DE TRANSPORTE DE USUÁRIOS DO HMAR. | AE41: HMAR | AF41: Aquisição de Vtr van
A42: 13 | B42: DEFESA | C42: 27240009 | D42: INDIVIDUAL | E42: INCLUSÃO - APROPRIAÇÃO | F42: 2724 | G42: PASTOR EURICO | H42: DEPUTADO FEDERAL | I42: PE | J42: PL | K42: 52000 | L42: MINISTÉRIO DA DEFESA | M42: 52111 | N42: COMANDO DA AERONÁUTICA | O42: 05.301.0032.2E74.0026 | P42: DEFESA NACIONAL | Q42: ATENÇÃO BÁSICA | R42: PROGRAMA DE GESTÃO E MANUTENÇÃO DO PODER EXECUTIVO | S42: ESTRUTURAÇÃO E MODERNIZAÇÃO DE UNIDADES DE SAÚDE DAS FORÇAS ARMADAS | T42: NO ESTADO DE PERNAMBUCO | U42: PE | V42: PERNAMBUCO | W42: S | X42: 4 | Y42: 90 | Z42: 0 | AA42: 6 | AB42: 1000 | AC42: 237992 | AD42: ESTA EMENDA TEM COMO OBJETIVO ALOCAR RECURSOS FEDERAIS PARA ESTRUTURAÇÃO E MODERNIZAÇÃO DE UNIDADES DE SAÚDE DAS FORÇAS ARMADAS.
A43: 13 | B43: DEFESA | C43: 27240011 | D43: INDIVIDUAL | E43: INCLUSÃO - APROPRIAÇÃO | F43: 2724 | G43: PASTOR EURICO | H43: DEPUTADO FEDERAL | I43: PE | J43: PL | K43: 52000 | L43: MINISTÉRIO DA DEFESA | M43: 52121 | N43: COMANDO DO EXÉRCITO | O43: 05.153.6112.219D.0026 | P43: DEFESA NACIONAL | Q43: DEFESA TERRESTRE | R43: DEFESA NACIONAL | S43: ADEQUAÇÃO DE ATIVOS DE INFRAESTRUTURA DAS ORGANIZAÇÕES MILITARES | T43: NO ESTADO DE PERNAMBUCO | U43: PE | V43: PERNAMBUCO | W43: F | X43: 3 | Y43: 90 | Z43: 0 | AA43: 6 | AB43: 1000 | AC43: 300000 | AD43: ESTA EMENDA TEM O OBJETIVO DE ALOCAR RECURSOS NO COMANDO DA MARINHA PARA QUE SEJAM INVESTIDOS NA INFRAESTRUTURA DA ESCOLA DE APRENDIZES DE MARINHEIRO DE PERNAMBUCO.
A44: 13 | B44: DEFESA | C44: 27370016 | D44: INDIVIDUAL | E44: INCLUSÃO - APROPRIAÇÃO | F44: 2737 | G44: ANTONIO BRITO | H44: DEPUTADO FEDERAL | I44: BA | J44: PSD | K44: 52000 | L44: MINISTÉRIO DA DEFESA | M44: 52131 | N44: COMANDO DA MARINHA | O44: 05.301.0032.2E74.0029 | P44: DEFESA NACIONAL | Q44: ATENÇÃO BÁSICA | R44: PROGRAMA DE GESTÃO E MANUTENÇÃO DO PODER EXECUTIVO | S44: ESTRUTURAÇÃO E MODERNIZAÇÃO DE UNIDADES DE SAÚDE DAS FORÇAS ARMADAS | T44: NO ESTADO DA BAHIA | U44: BA | V44: BAHIA | W44: S | X44: 3 | Y44: 99 | Z44: 0 | AA44: 6 | AB44: 1000 | AC44: 500000 | AD44: A PRESENTE EMENDA VISA A REVITALIZAÇÃO DAS INSTALAÇÕES DO HOSPITAL NAVAL DE SALVADOR, COM O OBJETIVO DO APRIMORAMENTO DOS SERVIÇOS PRESTADOS AOS USUÁRIOS DO SISTEMA DE SAÚDE DA MARINHA, MILITARES E DEPENDENTES.
A45: 13 | B45: DEFESA | C45: 27420005 | D45: INDIVIDUAL | E45: ACRÉSCIMO - APROPRIAÇÃO | F45: 2742 | G45: FÉLIX MENDONÇA JÚNIOR | H45: DEPUTADO FEDERAL | I45: BA | J45: PDT | K45: 52000 | L45: MINISTÉRIO DA DEFESA | M45: 52931 | N45: FUNDO NAVAL | O45: 05.152.6112.21A0.0001 | P45: DEFESA NACIONAL | Q45: DEFESA NAVAL | R45: DEFESA NACIONAL | S45: APRESTAMENTO DAS FORÇAS - MANUTENÇÃO DA PRONTIDÃO E DA CAPACIDADE OPERATIVA | T45: NACIONAL | U45: NA | V45: NACIONAL | W45: F | X45: 4 | Y45: 90 | Z45: 0 | AA45: 6 | AB45: 1000 | AC45: 500000 | AD45: CAPITANIA DOS PORTOS DA BAHIA - CPBA_x000D_ CNPJ: 00.394.502/0029-45_x000D_ _x000D_ A CPBA É RESPONSÁVEL DIRETAMENTE POR 187 MUNICÍPIOS E, INDIRETAMENTE, POR MAIS OUTROS 92 MUNICÍPIOS, NAS REGIÕES ABRANGIDAS POR SUAS DELEGACIAS SUBORDINADAS EM ILHÉUS E PORTO SEGURO, DEVENDO FAZER CUMPRIR AS LEGISLAÇÕES NACIONAIS E INTERNACIONAIS QUE REGULAM O TRÁFEGO MARÍTIMO, FLUVIAL E LACUSTRE, NO QUE TANGE À SALVAGUARDA DA VIDA HUMANA NO MAR, À SEGURANÇA DA NAVEGAÇÃO E À PREVENÇÃO DA POLUIÇÃO HÍDRICA NO MAR ABERTO E NAS HIDROVIAS INTERIORES, REALIZANDO AINDA, A FORMAÇÃO DE AQUAVIÁRIOS E PORTUÁRIOS EM NOSSA ÁREA DE JURISDIÇÃO, COM RELEVANTE PAPEL NO ORDENAMENTO AQUAVIÁRIO, NO SALVAMENTO DE VIDAS EM PERIGO E NA MANUTENÇÃO DE UM MEIO AMBIENTE RICO E SUSTENTÁVEL. A INCORPORAÇÃO DE NOVOS MEIOS E EQUIPAMENTOS PERMITIRÁ À CPBA INTENSIFICAR AS ATIVIDADES DE FISCALIZAÇÃO, CONTRIBUINDO NÃO SOMENTE PARA A SALVAGUARDA DA VIDA HUMANA NO MAR E ÁGUAS INTERIORES, MAS TAMBÉM PARA GERAÇÃO DE EMPREGOS E DIVISAS DOS MUNICÍPIOS DA BAHIA, POR MEIO DO FOMENTO À ECONOMIA AZUL, UMA VEZ QUE ESSAS AÇÕES TRAZEM UMA SENSAÇÃO DE SEGURANÇA NO MAR, PRODUZINDO UMA EXPERIÊNCIA POSITIVA PARA O TURISMO E ATIVIDADES NÁUTICAS, ALÉM DE SALVAR VIDAS.
A46: 13 | B46: DEFESA | C46: 27420006 | D46: INDIVIDUAL | E46: ACRÉSCIMO - APROPRIAÇÃO | F46: 2742 | G46: FÉLIX MENDONÇA JÚNIOR | H46: DEPUTADO FEDERAL | I46: BA | J46: PDT | K46: 52000 | L46: MINISTÉRIO DA DEFESA | M46: 52121 | N46: COMANDO DO EXÉRCITO | O46: 05.153.6112.21A0.0001 | P46: DEFESA NACIONAL | Q46: DEFESA TERRESTRE | R46: DEFESA NACIONAL | S46: APRESTAMENTO DAS FORÇAS - MANUTENÇÃO DA PRONTIDÃO E DA CAPACIDADE OPERATIVA | T46: NACIONAL | U46: NA | V46: NACIONAL | W46: F | X46: 4 | Y46: 90 | Z46: 0 | AA46: 6 | AB46: 1000 | AC46: 500000 | AD46: BENEFICIÁRIO PARA LANÇAMENTO NO SIOP - CNPJ: 00.394.452/0001-03_x000D_ ESTA EMENDA OBJETIVA À AQUISIÇÃO DE UM MICRO ÔNIBUS OU UMA VAN PARA O TRANSPORTE DOS MILITARES DA 6ª REGIÃO MILITAR, EM SALVADOR/BA, COM VISTAS À REALIZAÇÃO DE AÇÕES CÍVICO-SOCIAIS (ACISO) OU EM AÇÕES JUNTO À DEFESA CIVIL E ÀS AUTORIDADES CIVIS QUE NECESSITEM DE APOIO, ALÉM DE POSSIBILITAR O DESLOCAMENTO DE ESTUDANTES DA REDE PÚBLICA DE ENSINO QUE VISITAM OS ESPAÇOS CULTURAIS EXISTENTES NA ÁREA DA 6ª REGIÃO MILITAR.. | AE46: Cmdo 6ª RM | AF46: Aquisição de um micro-ônibus ou uma Vtr van para o transporte de militares
A47: 13 | B47: DEFESA | C47: 29690007 | D47: INDIVIDUAL | E47: ACRÉSCIMO - APROPRIAÇÃO | F47: 2969 | G47: WILDER MORAIS | H47: SENADOR | I47: GO | J47: PL | K47: 52000 | L47: MINISTÉRIO DA DEFESA | M47: 52121 | N47: COMANDO DO EXÉRCITO | O47: 05.153.6112.21A0.0001 | P47: DEFESA NACIONAL | Q47: DEFESA TERRESTRE | R47: DEFESA NACIONAL | S47: APRESTAMENTO DAS FORÇAS - MANUTENÇÃO DA PRONTIDÃO E DA CAPACIDADE OPERATIVA | T47: NACIONAL | U47: NA | V47: NACIONAL | W47: F | X47: 4 | Y47: 90 | Z47: 0 | AA47: 6 | AB47: 1000 | AC47: 1000000 | AD47: BENEFICIÁRIO PARA LANÇAMENTO NO SIOP - CNPJ: 00.394.452/0001-03_x000D_ APOIAR O TRANSPORTE DOS MILITARES DO COMANDO DE OPERAÇÕES ESPECIAIS, EM GOIÂNIA/GO, PARA A REALIZAÇÃO DE AÇÕES CÍVICO-SOCIAIS (ACISO) OU EM AÇÕES JUNTO À DEFESA CIVIL E ÀS AUTORIDADES CIVIS QUE NECESSITEM DE APOIO. | AE47: COPESP | AF47: Aquisição de 2 (dois) veículos tipo van e 1 (um) veículo tipo caminhonete
A48: 13 | B48: DEFESA | C48: 29730022 | D48: INDIVIDUAL | E48: INCLUSÃO - APROPRIAÇÃO | F48: 2973 | G48: PAULÃO | H48: DEPUTADO FEDERAL | I48: AL | J48: PT | K48: 52000 | L48: MINISTÉRIO DA DEFESA | M48: 52931 | N48: FUNDO NAVAL | O48: 05.125.6112.21BY.0027 | P48: DEFESA NACIONAL | Q48: NORMATIZAÇÃO E FISCALIZAÇÃO | R48: DEFESA NACIONAL | S48: FISCALIZAÇÃO DA NAVEGAÇÃO AQUAVIÁRIA | T48: NO ESTADO DE ALAGOAS | U48: AL | V48: ALAGOAS | W48: F | X48: 4 | Y48: 90 | Z48: 0 | AA48: 6 | AB48: 1000 | AC48: 350000 | AD48: FISCALIZAÇÃO DA NAVEGAÇÃO AQUAVIÁRIA - NO ESTADO DE ALAGOAS
A49: 13 | B49: DEFESA | C49: 30200014 | D49: INDIVIDUAL | E49: INCLUSÃO - APROPRIAÇÃO | F49: 3020 | G49: AFONSO MOTTA | H49: DEPUTADO FEDERAL | I49: RS | J49: PDT | K49: 52000 | L49: MINISTÉRIO DA DEFESA | M49: 52131 | N49: COMANDO DA MARINHA | O49: 05.152.6112.219D.0043 | P49: DEFESA NACIONAL | Q49: DEFESA NAVAL | R49: DEFESA NACIONAL | S49: ADEQUAÇÃO DE ATIVOS DE INFRAESTRUTURA DAS ORGANIZAÇÕES MILITARES | T49: NO ESTADO DO RIO GRANDE DO SUL | U49: RS | V49: RIO GRANDE DO SUL | W49: F | X49: 4 | Y49: 90 | Z49: 0 | AA49: 6 | AB49: 1000 | AC49: 200000 | AD49: A PROPOSTA TEM COMO OBJETIVO A INSTALAÇÃO DE USINA DE GERAÇÃO DE ENERGIA ELÉTRICA BENEFICIANDO A POLICLÍNICA NAVAL DE RIO GRANDE , LOCALIZADO NO MUNICÍPIO DO RIO GRANDE DO SUL .
A50: 13 | B50: DEFESA | C50: 30520010 | D50: INDIVIDUAL | E50: ACRÉSCIMO - APROPRIAÇÃO | F50: 3052 | G50: BALEIA ROSSI | H50: DEPUTADO FEDERAL | I50: SP | J50: MDB | K50: 52000 | L50: MINISTÉRIO DA DEFESA | M50: 52932 | N50: FUNDO DE DESENVOLVIMENTO DO ENSINO PROFISSIONAL MARÍTIMO | O50: 05.363.6111.2510.0001 | P50: DEFESA NACIONAL | Q50: ENSINO PROFISSIONAL | R50: COOPERAÇÃO DA DEFESA PARA O DESENVOLVIMENTO NACIONAL | S50: PRESTAÇÃO DE ENSINO PROFISSIONAL MARÍTIMO | T50: NACIONAL | U50: NA | V50: NACIONAL | W50: F | X50: 4 | Y50: 90 | Z50: 0 | AA50: 6 | AB50: 1000 | AC50: 750000 | AD50: CAPITANIA FLUVIAL DO TIETÊ-PARANÁ - CFTP_x000D_ CNPJ: 00.394.502/0356-06_x000D_ _x000D_ É VALIDO DESTACAR QUE, A CAPITANIA FLUVIAL DO TIETÊ-PARANÁ É A SEGUNDA MAIOR CAPITANIA DO BRASIL EM NÚMEROS DE AMADORES E EMBARCAÇÕES INSCRITAS E APESAR DE SER UMA ORGANIZAÇÃO MILITAR INTEGRANTE DO SISTEMA DE SEGURANÇA DO TRÁFEGO AQUAVIÁRIO (SSTA), SUAS ATRIBUIÇÕES VÃO MUITO ALÉM DA SEGURANÇA DA NAVEGAÇÃO, SENDO RESPONSÁVEL, TAMBÉM, PELA SAÚDE DE MILITARES E DE PENSIONISTAS (MAIS DE 500 USUÁRIOS), CURSOS DO ENSINO PROFISSIONAL MARÍTIMO, ALISTAMENTO, INSPEÇÕES, VISTORIAS, REGISTRO DE EMBARCAÇÕES, CADASTRO DE AMADORES, ASSISTÊNCIA SOCIAL, ENTRE OUTROS, REPRESENTANDO, ASSIM, A MARINHA DO BRASIL PARA MAIS DE 11.000.000 DE BRASILEIROS NO ESTADO DE SÃO PAULO, O QUE REPRESENTA MAIS DE 5% DA POPULAÇÃO NACIONAL. A FIM DE ILUSTRAR TAL IMPORTÂNCIA E A REFERÊNCIA DA INSTITUIÇÃO NA REGIÃO, FAZ-SE NECESSÁRIO MENCIONAR QUE A ÁREA DE JURISDIÇÃO DA CFTP ABRANGE 369 MUNICÍPIOS NO ESTADO DE SÃO PAULO, COM MAIS DE 1.000 KM DE VIAS NAVEGÁVEIS E UMA ÁREA 139.989,79 KM², MAIS DA METADE DO ESTADO DE SÃO PAULO, FATO QUE PROPORCIONA O TÍTULO DE SEGUNDA MAIOR CAPITANIA DO PAÍS.
A51: 13 | B51: DEFESA | C51: 30520011 | D51: INDIVIDUAL | E51: ACRÉSCIMO - APROPRIAÇÃO | F51: 3052 | G51: BALEIA ROSSI | H51: DEPUTADO FEDERAL | I51: SP | J51: MDB | K51: 52000 | L51: MINISTÉRIO DA DEFESA | M51: 52121 | N51: COMANDO DO EXÉRCITO | O51: 05.153.6112.21A0.0001 | P51: DEFESA NACIONAL | Q51: DEFESA TERRESTRE | R51: DEFESA NACIONAL | S51: APRESTAMENTO DAS FORÇAS - MANUTENÇÃO DA PRONTIDÃO E DA CAPACIDADE OPERATIVA | T51: NACIONAL | U51: NA | V51: NACIONAL | W51: F | X51: 4 | Y51: 90 | Z51: 0 | AA51: 6 | AB51: 1000 | AC51: 500000 | AD51: BENEFICIÁRIO PARA LANÇAMENTO NO SIOP - CNPJ: 00.394.452/0001-03_x000D_ ADQUIRIR EQUIPAMENTOS MUSICAIS PARA A BANDA SINFÔNICA DO EXÉRCITO. | AE51: B Adm Ap Ibirapuera | AF51: Equipamentos musicais para a Banda Sinfônica do Exército.
A52: 13 | B52: DEFESA | C52: 30820001 | D52: INDIVIDUAL | E52: INCLUSÃO - APROPRIAÇÃO | F52: 3082 | G52: DELEGADO ÉDER MAURO | H52: DEPUTADO FEDERAL | I52: PA | J52: PL | K52: 52000 | L52: MINISTÉRIO DA DEFESA | M52: 52131 | N52: COMANDO DA MARINHA | O52: 05.152.6112.219D.0015 | P52: DEFESA NACIONAL | Q52: DEFESA NAVAL | R52: DEFESA NACIONAL | S52: ADEQUAÇÃO DE ATIVOS DE INFRAESTRUTURA DAS ORGANIZAÇÕES MILITARES | T52: NO ESTADO DO PARÁ | U52: PA | V52: PARÁ | W52: F | X52: 4 | Y52: 90 | Z52: 0 | AA52: 6 | AB52: 1000 | AC52: 1000000 | AD52: AMPLIAÇÃO DO PRÉDIO DO GRUPO DE EMBARCAÇÕES DE OPERAÇÕES RIBEIRINHAS DO NORTE ( GREOPRIBN). EMENDA DE AUTORIA INDIVIDUAL DO DEPUTADO DELEGADO ÉDER MAURO.
A53: 13 | B53: DEFESA | C53: 30880001 | D53: INDIVIDUAL | E53: ACRÉSCIMO - APROPRIAÇÃO | F53: 3088 | G53: EDUARDO BOLSONARO | H53: DEPUTADO FEDERAL | I53: SP | J53: PL | K53: 52000 | L53: MINISTÉRIO DA DEFESA | M53: 52121 | N53: COMANDO DO EXÉRCITO | O53: 05.153.6112.20XE.0001 | P53: DEFESA NACIONAL | Q53: DEFESA TERRESTRE | R53: DEFESA NACIONAL | S53: MANUTENÇÃO E MODERNIZAÇÃO DE SISTEMAS DE COMANDO E CONTROLE DO EXÉRCITO | T53: NACIONAL | U53: NA | V53: NACIONAL | W53: F | X53: 3 | Y53: 90 | Z53: 0 | AA53: 6 | AB53: 1000 | AC53: 300000 | AD53: BENEFICIÁRIO PARA LANÇAMENTO NO SIOP - CNPJ: 00.394.452/0001-03_x000D_ MODERNIZAR, ATRAVÉS DO 3º CENTRO DE TELEMÁTICA DE ÁREA, EM SÃO PAULO/SP, O CABEAMENTO ESTRUTURADO PARA MELHORIA DA REDE INTERNA DAS ORGANIZAÇÕES MILITARES NO ESTADO DE SÃO PAULO E INSTALAR CIRCUITO FECHADO TV. | AE53: 3º CTA | AF53: Modernizar o cabeamento estruturado para melhoria da rede interna das OM no Estado de São Paulo e instalar circuito fechado TV.
A54: 13 | B54: DEFESA | C54: 30880001 | D54: INDIVIDUAL | E54: ACRÉSCIMO - APROPRIAÇÃO | F54: 3088 | G54: EDUARDO BOLSONARO | H54: DEPUTADO FEDERAL | I54: SP | J54: PL | K54: 52000 | L54: MINISTÉRIO DA DEFESA | M54: 52121 | N54: COMANDO DO EXÉRCITO | O54: 05.153.6112.20XE.0001 | P54: DEFESA NACIONAL | Q54: DEFESA TERRESTRE | R54: DEFESA NACIONAL | S54: MANUTENÇÃO E MODERNIZAÇÃO DE SISTEMAS DE COMANDO E CONTROLE DO EXÉRCITO | T54: NACIONAL | U54: NA | V54: NACIONAL | W54: F | X54: 4 | Y54: 90 | Z54: 0 | AA54: 6 | AB54: 1000 | AC54: 100000 | AD54: BENEFICIÁRIO PARA LANÇAMENTO NO SIOP - CNPJ: 00.394.452/0001-03_x000D_ MODERNIZAR, ATRAVÉS DO 3º CENTRO DE TELEMÁTICA DE ÁREA, EM SÃO PAULO/SP, O CABEAMENTO ESTRUTURADO PARA MELHORIA DA REDE INTERNA DAS ORGANIZAÇÕES MILITARES NO ESTADO DE SÃO PAULO E INSTALAR CIRCUITO FECHADO TV. | AE54: 3º CTA | AF54: Modernizar o cabeamento estruturado para melhoria da rede interna das OM no Estado de São Paulo e instalar circuito fechado TV.
A55: 13 | B55: DEFESA | C55: 30880003 | D55: INDIVIDUAL | E55: INCLUSÃO - APROPRIAÇÃO | F55: 3088 | G55: EDUARDO BOLSONARO | H55: DEPUTADO FEDERAL | I55: SP | J55: PL | K55: 52000 | L55: MINISTÉRIO DA DEFESA | M55: 52111 | N55: COMANDO DA AERONÁUTICA | O55: 05.301.0032.2E74.0035 | P55: DEFESA NACIONAL | Q55: ATENÇÃO BÁSICA | R55: PROGRAMA DE GESTÃO E MANUTENÇÃO DO PODER EXECUTIVO | S55: ESTRUTURAÇÃO E MODERNIZAÇÃO DE UNIDADES DE SAÚDE DAS FORÇAS ARMADAS | T55: NO ESTADO DE SÃO PAULO | U55: SP | V55: SÃO PAULO | W55: S | X55: 4 | Y55: 90 | Z55: 0 | AA55: 6 | AB55: 1000 | AC55: 200000 | AD55: CNPJ PARA LANÇAMENTO NO SIOP: 00.394.429/0001-00 - COMANDO DA AERONÁUTICA_x000D_ UNIDADE BENEFICIADA: HOSPITAL DE FORÇA AÉREA DE SÃO PAULO - HFASP_x000D_ OBJETO RESUMIDO: AQUISIÇÃO DE APARELHOS DE FOCO CIRÚRGICO.
A56: 13 | B56: DEFESA | C56: 30880007 | D56: INDIVIDUAL | E56: ACRÉSCIMO - APROPRIAÇÃO | F56: 3088 | G56: EDUARDO BOLSONARO | H56: DEPUTADO FEDERAL | I56: SP | J56: PL | K56: 52000 | L56: MINISTÉRIO DA DEFESA | M56: 52131 | N56: COMANDO DA MARINHA | O56: 05.152.6112.219D.0001 | P56: DEFESA NACIONAL | Q56: DEFESA NAVAL | R56: DEFESA NACIONAL | S56: ADEQUAÇÃO DE ATIVOS DE INFRAESTRUTURA DAS ORGANIZAÇÕES MILITARES | T56: NACIONAL | U56: NA | V56: NACIONAL | W56: F | X56: 4 | Y56: 90 | Z56: 0 | AA56: 6 | AB56: 1000 | AC56: 300000 | AD56: COMANDO DO 8º DISTRITO NAVAL - COM8ºDN_x000D_ CNPJ: 00.394.502/0455-98_x000D_ _x000D_ A CONSTRUÇÃO E ADEQUAÇÃO DAS INSTALAÇÕES DA ESCOLA DE FORMAÇÃO DE RESERVISTAS NAVAIS E ENSINO PROFISSIONAL MARÍTIMO PERMITIRÁ A FORMAÇÃO DOS(AS) RECRUTAS E MÉDICOS DO SERVIÇO MILITAR OBRIGATÓRIO E DOS CERCA DE 200 JOVENS/ANO (NÍVEL SUPERIOR) DO SERVIÇO MILITAR VOLUNTÁRIO QUE BUSCAM OCUPAÇÃO PROFISSIONAL NAS ÁREAS DE ADMINISTRAÇÃO, ARQUITETURA, DIREITO, ENGENHARIAS, TECNOLOGIA DA INFORMAÇÃO, ASSISTÊNCIA SOCIAL, PSICOLOGIA E ODONTOLOGIA. REFERIDAS INSTALAÇÕES TAMBÉM SERÃO UTILIZADAS EM PROVEITO DA AMPLIAÇÃO DA CAPACIDADE DE FORMAÇÃO PROFISSIONAL MARÍTIMA DE MILHARES DE PROFISSIONAIS AQUAVIÁRIOS E PORTUÁRIOS NO ESTADO DE SÃO PAULO. PROPICIARÁ, AINDA, ESPAÇO ADEQUADO PARA A EXECUÇÃO DOS PROJETOS SOCIAIS E CÍVICO-MILITARES, DESENVOLVIDOS EM PARCERIA COM A SECRETARIA DE EDUCAÇÃO DO ESTADO DE SÃO PAULO, ÀS CENTENAS DE CRIANÇAS COM IDADES ENTRE 12 E 14 ANOS DAS ESCOLAS ESTADUAIS E MUNICIPAIS DE SÃO PAULO, DESPERTANDO O INTERESSE CÍVICO NOS JOVENS PAULISTAS, ALÉM DE PROPORCIONAR A OPORTUNIDADE DE CONHECER AS AÇÕES DESENVOLVIDAS PELA MARINHA DO BRASIL._x000D_ O PRÉDIO TERÁ 1.630 M² COM 7 PAVIMENTOS, AO LADO DE QUADRAS POLIVALENTES JÁ EXISTENTES, CAPAZ DE ATENDER ATÉ 150 ALUNOS (POPULAÇÃO FLUTUANTE) COM ATÉ 20 FUNCIONÁRIOS/PROFESSORES. É PREVISTO AUDITÓRIO, ALOJAMENTO, VESTIÁRIOS, COPA E SALA DE ESTAR DOS ALUNOS, SALAS ADMINISTRATIVAS, SALA DOS INSTRUTORES, SECRETARIA, ELEVADOR, ETC. ESTIMATIVA DE CUSTO UTILIZANDO O CUSTO UNITÁRIO BÁSICO (CUB) DE CONSTRUÇÃO, R$ 6.000.000,00.
A57: 13 | B57: DEFESA | C57: 31340001 | D57: INDIVIDUAL | E57: INCLUSÃO - APROPRIAÇÃO | F57: 3134 | G57: FAUSTO PINATO | H57: DEPUTADO FEDERAL | I57: SP | J57: PP | K57: 52000 | L57: MINISTÉRIO DA DEFESA | M57: 52111 | N57: COMANDO DA AERONÁUTICA | O57: 05.122.0032.2000.0035 | P57: DEFESA NACIONAL | Q57: ADMINISTRAÇÃO GERAL | R57: PROGRAMA DE GESTÃO E MANUTENÇÃO DO PODER EXECUTIVO | S57: ADMINISTRAÇÃO DA UNIDADE | T57: NO ESTADO DE SÃO PAULO | U57: SP | V57: SÃO PAULO | W57: F | X57: 4 | Y57: 90 | Z57: 0 | AA57: 6 | AB57: 1000 | AC57: 200000 | AD57: 00.394.429/0001-00 - COMANDO DA AERONÁUTICA PARA ATENDER O ESQUADRÃO DE DEMONSTRAÇÃO AÉREA - EDA COM AQUISIÇÃO DE EQUIPAMENTOS AUDIOVISUAL.
A58: 13 | B58: DEFESA | C58: 31600001 | D58: INDIVIDUAL | E58: ACRÉSCIMO - APROPRIAÇÃO | F58: 3160 | G58: CELSO RUSSOMANNO | H58: DEPUTADO FEDERAL | I58: SP | J58: REPUBLICANOS | K58: 52000 | L58: MINISTÉRIO DA DEFESA | M58: 52133 | N58: SECRETARIA DA COMISSÃO INTERMINISTERIAL PARA OS RECURSOS DO MAR | O58: 05.571.6113.2345.0001 | P58: DEFESA NACIONAL | Q58: DESENVOLVIMENTO CIENTÍFICO | R58: OCEANO, ZONA COSTEIRA E ANTÁRTICA | S58: APOIO LOGÍSTICO À PESQUISA CIENTÍFICA NA ANTÁRTICA | T58: NACIONAL | U58: NA | V58: NACIONAL | W58: F | X58: 3 | Y58: 90 | Z58: 0 | AA58: 6 | AB58: 1000 | AC58: 450000 | AD58: SECRETARIA DA COMISSÃO INTERMINISTERIAL PARA OS RECURSOS DO MAR - SECIRM_x000D_ CNPJ: 00.394.502/0165-71_x000D_ _x000D_ PROVER APOIO E SUPORTE LOGÍSTICO ÀS ATIVIDADES CIENTÍFICAS BRASILEIRAS REALIZADAS NO CONTINENTE ANTÁRTICO, PELO PROGRAMA ANTÁRTICO BRASILEIRO (PROANTAR), CORROBORANDO COM A PRESENÇA DO ESTADO BRASILEIRO NA REALIZAÇÃO DE RENOMADAS PESQUISAS A BORDO DOS NAVIOS DA MARINHA DO BRASIL, NAS ESTAÇÃO ANTÁRTICA COMANDANTE FERRAZ E ACAMPAMENTOS NO CONTINENTE, NA PRODUÇÃO DE CONHECIMENTOS, INCENTIVO À PESQUISA E FOMENTO À PARTICIPAÇÃO DE PESQUISADORES E INSTITUIÇÕES NACIONAIS NA COMPREENSÃO DOS FENÔMENOS QUE ALI OCORREM E QUE TENHAM REPERCUSSÃO GLOBAL E, PRINCIPALMENTE, NO PAÍS.
A59: 13 | B59: DEFESA | C59: 31600001 | D59: INDIVIDUAL | E59: ACRÉSCIMO - APROPRIAÇÃO | F59: 3160 | G59: CELSO RUSSOMANNO | H59: DEPUTADO FEDERAL | I59: SP | J59: REPUBLICANOS | K59: 52000 | L59: MINISTÉRIO DA DEFESA | M59: 52133 | N59: SECRETARIA DA COMISSÃO INTERMINISTERIAL PARA OS RECURSOS DO MAR | O59: 05.571.6113.2345.0001 | P59: DEFESA NACIONAL | Q59: DESENVOLVIMENTO CIENTÍFICO | R59: OCEANO, ZONA COSTEIRA E ANTÁRTICA | S59: APOIO LOGÍSTICO À PESQUISA CIENTÍFICA NA ANTÁRTICA | T59: NACIONAL | U59: NA | V59: NACIONAL | W59: F | X59: 4 | Y59: 90 | Z59: 0 | AA59: 6 | AB59: 1000 | AC59: 100000 | AD59: SECRETARIA DA COMISSÃO INTERMINISTERIAL PARA OS RECURSOS DO MAR - SECIRM_x000D_ CNPJ: 00.394.502/0165-71_x000D_ _x000D_ PROVER APOIO E SUPORTE LOGÍSTICO ÀS ATIVIDADES CIENTÍFICAS BRASILEIRAS REALIZADAS NO CONTINENTE ANTÁRTICO, PELO PROGRAMA ANTÁRTICO BRASILEIRO (PROANTAR), CORROBORANDO COM A PRESENÇA DO ESTADO BRASILEIRO NA REALIZAÇÃO DE RENOMADAS PESQUISAS A BORDO DOS NAVIOS DA MARINHA DO BRASIL, NAS ESTAÇÃO ANTÁRTICA COMANDANTE FERRAZ E ACAMPAMENTOS NO CONTINENTE, NA PRODUÇÃO DE CONHECIMENTOS, INCENTIVO À PESQUISA E FOMENTO À PARTICIPAÇÃO DE PESQUISADORES E INSTITUIÇÕES NACIONAIS NA COMPREENSÃO DOS FENÔMENOS QUE ALI OCORREM E QUE TENHAM REPERCUSSÃO GLOBAL E, PRINCIPALMENTE, NO PAÍS.
A60: 13 | B60: DEFESA | C60: 31600002 | D60: INDIVIDUAL | E60: ACRÉSCIMO - APROPRIAÇÃO | F60: 3160 | G60: CELSO RUSSOMANNO | H60: DEPUTADO FEDERAL | I60: SP | J60: REPUBLICANOS | K60: 52000 | L60: MINISTÉRIO DA DEFESA | M60: 52121 | N60: COMANDO DO EXÉRCITO | O60: 05.153.6112.21A0.0001 | P60: DEFESA NACIONAL | Q60: DEFESA TERRESTRE | R60: DEFESA NACIONAL | S60: APRESTAMENTO DAS FORÇAS - MANUTENÇÃO DA PRONTIDÃO E DA CAPACIDADE OPERATIVA | T60: NACIONAL | U60: NA | V60: NACIONAL | W60: F | X60: 4 | Y60: 90 | Z60: 0 | AA60: 6 | AB60: 1000 | AC60: 400000 | AD60: BENEFICIÁRIO PARA LANÇAMENTO NO SIOP - CNPJ: 00.394.452/0001-03_x000D_ MELHORAR A ACOMODAÇÃO DE PESSOAL NOS REFEITÓRIOS DO CENTRO DE PREPARAÇÃO DE OFICIAIS DA RESERVA E COLÉGIO MILITAR DE SÃO PAULO, NA CIDADE DE SÃO PAULO/SP. | AE60: CPOR/SP | AF60: Melhoria dos refeitórios
A61: 13 | B61: DEFESA | C61: 31600003 | D61: INDIVIDUAL | E61: ACRÉSCIMO - APROPRIAÇÃO | F61: 3160 | G61: CELSO RUSSOMANNO | H61: DEPUTADO FEDERAL | I61: SP | J61: REPUBLICANOS | K61: 52000 | L61: MINISTÉRIO DA DEFESA | M61: 52121 | N61: COMANDO DO EXÉRCITO | O61: 05.153.6112.21A0.0001 | P61: DEFESA NACIONAL | Q61: DEFESA TERRESTRE | R61: DEFESA NACIONAL | S61: APRESTAMENTO DAS FORÇAS - MANUTENÇÃO DA PRONTIDÃO E DA CAPACIDADE OPERATIVA | T61: NACIONAL | U61: NA | V61: NACIONAL | W61: F | X61: 4 | Y61: 90 | Z61: 0 | AA61: 6 | AB61: 1000 | AC61: 200000 | AD61: BENEFICIÁRIO PARA LANÇAMENTO NO SIOP - CNPJ: 00.394.452/0001-03_x000D_ ADQUIRIR EQUIPAMENTOS MUSICAIS PARA A BANDA SINFÔNICA DO EXÉRCITO. | AE61: B Adm Ap Ibirapuera | AF61: Equipamentos musicais para a Banda Sinfônica do Exército.
A62: 13 | B62: DEFESA | C62: 31600004 | D62: INDIVIDUAL | E62: INCLUSÃO - APROPRIAÇÃO | F62: 3160 | G62: CELSO RUSSOMANNO | H62: DEPUTADO FEDERAL | I62: SP | J62: REPUBLICANOS | K62: 52000 | L62: MINISTÉRIO DA DEFESA | M62: 52121 | N62: COMANDO DO EXÉRCITO | O62: 05.363.6112.21GN.3970 | P62: DEFESA NACIONAL | Q62: ENSINO PROFISSIONAL | R62: DEFESA NACIONAL | S62: FUNCIONAMENTO DE ESTABELECIMENTOS DE ENSINO PROFISSIONAL MILITARES DO MINISTÉRIO DA DEFESA | T62: NO MUNICÍPIO DE TAUBATÉ - SP | U62: SP | V62: TAUBATÉ | W62: F | X62: 4 | Y62: 90 | Z62: 0 | AA62: 6 | AB62: 1000 | AC62: 500000 | AD62: BENEFICIÁRIO PARA LANÇAMENTO NO SIOP - CNPJ: 00.394.452/0001-03_x000D_ ATUALIZAR O SISTEMA DE PROJEÇÃO, MODERNIZAÇÃO DA PLATAFORMA DE MOVIMENTO, INCLUSÃO DO SISTEMA DE FORCE FEEDBACK NOS COMANDOS E INCLUSÃO DE SISTEMA DE VIBRAÇÃO NO SIMULADOR DE VOO DO CENTRO DE INSTRUÇÃO DE AVIAÇÃO DO EXÉRCITO, EM TAUBATÉ/SP, MELHORANDO A FORMAÇÃO DAS TRIPULAÇÕES E ECONOMIZANDO HORAS DE VOO QUE PODEM SER UTILIZADAS EM OPERAÇÕES DE RESGATE DURANTE CALAMIDADES. | AE62: CIAvEx | AF62: Atualizar o sistema de projeção, modernização da plataforma de movimento, inclusão do sistema de force feedback nos comandos e inclusão de sistema de vibração no simulador de voo.
A63: 13 | B63: DEFESA | C63: 31600005 | D63: INDIVIDUAL | E63: INCLUSÃO - APROPRIAÇÃO | F63: 3160 | G63: CELSO RUSSOMANNO | H63: DEPUTADO FEDERAL | I63: SP | J63: REPUBLICANOS | K63: 52000 | L63: MINISTÉRIO DA DEFESA | M63: 52131 | N63: COMANDO DA MARINHA | O63: 05.152.6112.219D.0035 | P63: DEFESA NACIONAL | Q63: DEFESA NAVAL | R63: DEFESA NACIONAL | S63: ADEQUAÇÃO DE ATIVOS DE INFRAESTRUTURA DAS ORGANIZAÇÕES MILITARES | T63: NO ESTADO DE SÃO PAULO | U63: SP | V63: SÃO PAULO | W63: F | X63: 4 | Y63: 90 | Z63: 0 | AA63: 6 | AB63: 1000 | AC63: 450000 | AD63: A INSTALAÇÃO DE UM NOVO ELEVADOR VISA AMPLIAR A ACESSIBILIDADE AOS DIFERENTES NÍVEIS EXISTENTES NO PRÉDIO CNPJ: 00394502045598, OM BENEFICIADA COMANDO 08 DN89000-81 SP
A64: 13 | B64: DEFESA | C64: 31600006 | D64: INDIVIDUAL | E64: INCLUSÃO - APROPRIAÇÃO | F64: 3160 | G64: CELSO RUSSOMANNO | H64: DEPUTADO FEDERAL | I64: SP | J64: REPUBLICANOS | K64: 52000 | L64: MINISTÉRIO DA DEFESA | M64: 52911 | N64: FUNDO AERONÁUTICO | O64: 05.364.6112.21GQ.0035 | P64: DEFESA NACIONAL | Q64: ENSINO SUPERIOR | R64: DEFESA NACIONAL | S64: FUNCIONAMENTO DOS ESTABELECIMENTOS DE ENSINO SUPERIOR MILITARES DO MINISTÉRIO DA DEFESA | T64: NO ESTADO DE SÃO PAULO | U64: SP | V64: SÃO PAULO | W64: F | X64: 4 | Y64: 90 | Z64: 0 | AA64: 6 | AB64: 1000 | AC64: 650000 | AD64: CNPJ PARA LANÇAMENTO NO SIOP: 00.394.429/0001-00 - COMANDO DA AERONÁUTICA_x000D_ _x000D_ UNIDADE BENEFICIADA: ACADEMIA DA FORÇA AÉREA - AFA_x000D_ _x000D_ OBJETO RESUMIDO: AQUISIÇÃO DE MOBILIÁRIO E READEQUAÇÃO DAS SALAS DE INSTRUÇÃO DOS RECRUTAS E DOS CADETES.
A65: 13 | B65: DEFESA | C65: 32390006 | D65: INDIVIDUAL | E65: INCLUSÃO - APROPRIAÇÃO | F65: 3239 | G65: JOÃO LEÃO | H65: DEPUTADO FEDERAL | I65: BA | J65: PP | K65: 52000 | L65: MINISTÉRIO DA DEFESA | M65: 52121 | N65: COMANDO DO EXÉRCITO | O65: 05.122.0032.2000.0029 | P65: DEFESA NACIONAL | Q65: ADMINISTRAÇÃO GERAL | R65: PROGRAMA DE GESTÃO E MANUTENÇÃO DO PODER EXECUTIVO | S65: ADMINISTRAÇÃO DA UNIDADE | T65: NO ESTADO DA BAHIA | U65: BA | V65: BAHIA | W65: F | X65: 4 | Y65: 90 | Z65: 0 | AA65: 6 | AB65: 1000 | AC65: 250000 | AD65: O RECURSO SERÁ DESTINADO PARA A MELHORIA DAS CONDIÇÕES DE INSTRUÇÃO DA TROPA DO 4º BATALHÃO DE ENGENHARIA DE CONSTRUÇÃO, EM BARREIRAS/BA, ALÉM DE SERVIR DE APOIO PARA AS ATIVIDADES EDUCACIONAIS, COMO PROJETO SOLDADO-CIDADÃO, QUE CONTRIBUEM PARA SEU MELHOR INGRESSO NO MERCADO DE TRABALHO. | AE65: 4º BEC | AF65: Aquisição de material permanente
A66: 13 | B66: DEFESA | C66: 32620006 | D66: INDIVIDUAL | E66: ACRÉSCIMO - APROPRIAÇÃO | F66: 3262 | G66: JOSÉ ROCHA | H66: DEPUTADO FEDERAL | I66: BA | J66: UNIÃO | K66: 52000 | L66: MINISTÉRIO DA DEFESA | M66: 52931 | N66: FUNDO NAVAL | O66: 05.122.0032.2000.0001 | P66: DEFESA NACIONAL | Q66: ADMINISTRAÇÃO GERAL | R66: PROGRAMA DE GESTÃO E MANUTENÇÃO DO PODER EXECUTIVO | S66: ADMINISTRAÇÃO DA UNIDADE | T66: NACIONAL | U66: NA | V66: NACIONAL | W66: F | X66: 3 | Y66: 90 | Z66: 0 | AA66: 6 | AB66: 1000 | AC66: 300000 | AD66: GRUPAMENTO DE FUZILEIROS NAVAIS DE SALVADOR - GPTFNSA_x000D_ CNPJ: 00.394.502/0118-55_x000D_ _x000D_ A PROMOÇÃO DE REFORMA/REVITALIZAÇÃO DA INFRAESTRUTURA DO PARQUE ESPORTIVO E ALOJAMENTOS/VESTIÁRIOS DO GRUPAMENTO DE FUZILEIROS NAVAIS DE SALVADOR (GPTFNSA). ESSA INFRAESTRUTURA É UTILIZADA NO APRIMORAMENTO FÍSICO DE MILITARES DE CARREIRA/PRESTANDO SERVIÇO MILITAR TEMPORÁRIO, BENEFICIÁRIOS DO PROJETO SOLDADO-CIDADÃO (PSC), NA APLICAÇÃO DE PROVAS FÍSICAS DE CONCURSOS PÚBLICOS DE COMPETÊNCIA DA MARINHA DO BRASIL, A EXEMPLO DOS PROCESSOS SELETIVOS PARA INGRESSO NO COLÉGIO NAVAL, ESCOLA NAVAL, NO CORPO AUXILIAR DE PRAÇAS DA MARINHA E NA ESCOLA DE APRENDIZES-MARINHEIROS. _x000D_ _x000D_ A ESTRUTURA ESPORTIVA E DE ALOJAMENTOS/VESTIÁRIOS É UTILIZADA TAMBÉM PELOS BENEFICIÁRIOS DO PROGRAMA FORÇAS NO ESPORTE (PROFESP), SENDO ESTE, UM PROGRAMA SOCIAL DO MINISTÉRIO DA DEFESA, QUE TEM COMO PÚBLICO-ALVO CRIANÇAS E ADOLESCENTES DE SEIS AOS DEZOITO ANOS DE IDADE, DE AMBOS OS SEXOS, MATRICULADOS NA REDE PÚBLICA DE ENSINO, EM SITUAÇÃO DE VULNERABILIDADE SOCIAL, PROMOVENDO O LAZER E A CONVIVÊNCIA SALUTAR, POR MEIO DO ACESSO À PRÁTICA DE ATIVIDADES ESPORTIVAS E FÍSICAS SAUDÁVEIS E ATIVIDADES SOCIALMENTE INCLUSIVAS. ENTRETANTO, O ATUAL NÍVEL DE DESGASTE DE PARCELA DAS INSTALAÇÕES TEM IMPOSSIBILITADO A SUA UTILIZAÇÃO PELOS JOVENS DO PROFESP E DOS DEMAIS USUÁRIOS, UMA VEZ QUE PODE VIR A OCASIONAR PREJUÍZOS AO BEM-ESTAR DOS ENVOLVIDOS. A REVITALIZAÇÃO DAS INFRAESTRUTURAS SE FAZ PREMENTE, A FIM DE QUE AS ATIVIDADES SEJAM RETOMADAS INTEGRALMENTE, DE MANEIRA ADEQUADA E SEGURA.
A67: 13 | B67: DEFESA | C67: 32620008 | D67: INDIVIDUAL | E67: ACRÉSCIMO - APROPRIAÇÃO | F67: 3262 | G67: JOSÉ ROCHA | H67: DEPUTADO FEDERAL | I67: BA | J67: UNIÃO | K67: 52000 | L67: MINISTÉRIO DA DEFESA | M67: 52133 | N67: SECRETARIA DA COMISSÃO INTERMINISTERIAL PARA OS RECURSOS DO MAR | O67: 05.571.6113.2345.0001 | P67: DEFESA NACIONAL | Q67: DESENVOLVIMENTO CIENTÍFICO | R67: OCEANO, ZONA COSTEIRA E ANTÁRTICA | S67: APOIO LOGÍSTICO À PESQUISA CIENTÍFICA NA ANTÁRTICA | T67: NACIONAL | U67: NA | V67: NACIONAL | W67: F | X67: 3 | Y67: 90 | Z67: 0 | AA67: 6 | AB67: 1000 | AC67: 250000 | AD67: SECRETARIA DA COMISSÃO INTERMINISTERIAL PARA OS RECURSOS DO MAR - SECIRM_x000D_ CNPJ: 00.394.502/0165-71_x000D_ _x000D_ PROVER APOIO E SUPORTE LOGÍSTICO ÀS ATIVIDADES CIENTÍFICAS BRASILEIRAS REALIZADAS NO CONTINENTE ANTÁRTICO, PELO PROGRAMA ANTÁRTICO BRASILEIRO (PROANTAR), CORROBORANDO COM A PRESENÇA DO ESTADO BRASILEIRO NA REALIZAÇÃO DE RENOMADAS PESQUISAS A BORDO DOS NAVIOS DA MARINHA DO BRASIL, NA ESTAÇÃO ANTÁRTICA COMANDANTE FERRAZ E ACAMPAMENTOS NO CONTINENTE, NA PRODUÇÃO DE CONHECIMENTOS, INCENTIVO À PESQUISA E FOMENTO À PARTICIPAÇÃO DE PESQUISADORES E INSTITUIÇÕES NACIONAIS NA COMPREENSÃO DOS FENÔMENOS QUE ALI OCORREM E QUE TENHAM REPERCUSSÃO GLOBAL E, PRINCIPALMENTE, NO PAÍS.
A68: 13 | B68: DEFESA | C68: 32620008 | D68: INDIVIDUAL | E68: ACRÉSCIMO - APROPRIAÇÃO | F68: 3262 | G68: JOSÉ ROCHA | H68: DEPUTADO FEDERAL | I68: BA | J68: UNIÃO | K68: 52000 | L68: MINISTÉRIO DA DEFESA | M68: 52133 | N68: SECRETARIA DA COMISSÃO INTERMINISTERIAL PARA OS RECURSOS DO MAR | O68: 05.571.6113.2345.0001 | P68: DEFESA NACIONAL | Q68: DESENVOLVIMENTO CIENTÍFICO | R68: OCEANO, ZONA COSTEIRA E ANTÁRTICA | S68: APOIO LOGÍSTICO À PESQUISA CIENTÍFICA NA ANTÁRTICA | T68: NACIONAL | U68: NA | V68: NACIONAL | W68: F | X68: 4 | Y68: 90 | Z68: 0 | AA68: 6 | AB68: 1000 | AC68: 50000 | AD68: SECRETARIA DA COMISSÃO INTERMINISTERIAL PARA OS RECURSOS DO MAR - SECIRM_x000D_ CNPJ: 00.394.502/0165-71_x000D_ _x000D_ PROVER APOIO E SUPORTE LOGÍSTICO ÀS ATIVIDADES CIENTÍFICAS BRASILEIRAS REALIZADAS NO CONTINENTE ANTÁRTICO, PELO PROGRAMA ANTÁRTICO BRASILEIRO (PROANTAR), CORROBORANDO COM A PRESENÇA DO ESTADO BRASILEIRO NA REALIZAÇÃO DE RENOMADAS PESQUISAS A BORDO DOS NAVIOS DA MARINHA DO BRASIL, NA ESTAÇÃO ANTÁRTICA COMANDANTE FERRAZ E ACAMPAMENTOS NO CONTINENTE, NA PRODUÇÃO DE CONHECIMENTOS, INCENTIVO À PESQUISA E FOMENTO À PARTICIPAÇÃO DE PESQUISADORES E INSTITUIÇÕES NACIONAIS NA COMPREENSÃO DOS FENÔMENOS QUE ALI OCORREM E QUE TENHAM REPERCUSSÃO GLOBAL E, PRINCIPALMENTE, NO PAÍS.
A69: 13 | B69: DEFESA | C69: 32680014 | D69: INDIVIDUAL | E69: ACRÉSCIMO - APROPRIAÇÃO | F69: 3268 | G69: LAURA CARNEIRO | H69: DEPUTADO FEDERAL | I69: RJ | J69: PSD | K69: 52000 | L69: MINISTÉRIO DA DEFESA | M69: 52931 | N69: FUNDO NAVAL | O69: 05.122.0032.2000.0001 | P69: DEFESA NACIONAL | Q69: ADMINISTRAÇÃO GERAL | R69: PROGRAMA DE GESTÃO E MANUTENÇÃO DO PODER EXECUTIVO | S69: ADMINISTRAÇÃO DA UNIDADE | T69: NACIONAL | U69: NA | V69: NACIONAL | W69: F | X69: 4 | Y69: 90 | Z69: 0 | AA69: 6 | AB69: 1000 | AC69: 200000 | AD69: CENTRO DE EDUCAÇÃO FÍSICA ALMIRANTE ADALBERTO NUNES - CEFAN_x000D_ CNPJ: 00.394.502/0129-08_x000D_ _x000D_ "A CANO HAVAIANA É UMA MODALIDADE ESPORTIVA INTRODUZIDA EM 2023 NO PROGRAMA FORÇAS NO ESPORTE (PROFESP), FRUTO DE UMA PARCERIA COM O CLUBE ARARIBÓIA COM SEDE NA CIDADE DE NITERÓI. APESAR DO POUCO TEMPO DE PRÁTICA, OS JOVENS ADOLESCENTES DO PROGRAMA ALCANÇARAM RESULTADOS SIGNIFICATIVOS NO ÂMBITO ESTADUAL E FEDERAL, CONSEGUINDO INCLUSIVE A CLASSIFICAÇÃO PARA O MUNDIAL DA MODALIDADE NO HAVAÍ, ESTADOS UNIDOS. COM ISSO, FAZ NECESSÁRIO A AQUISIÇÃO DE UNIFORMES, REMOS E COLETES PARA A REFERIDA EQUIPE, A FIM DE MELHORAR AINDA MAIS A QUALIDADE DAS ATIVIDADES REALIZADAS PELOS JOVENS PARTICIPANTES DO PROFESP._x000D_ O PROFESP ATENDE ATUALMENTE 830 ALUNOS, NA FAIXA ETÁRIA DE 10 A 18 ANOS, QUE SE ENCONTRAM EM SITUAÇÃO DE VULNERABILIDADE SOCIAL, ORIUNDOS DAS COMUNIDADES DO ENTORNO DO CEFAN."
A70: 13 | B70: DEFESA | C70: 32680017 | D70: INDIVIDUAL | E70: ACRÉSCIMO - APROPRIAÇÃO | F70: 3268 | G70: LAURA CARNEIRO | H70: DEPUTADO FEDERAL | I70: RJ | J70: PSD | K70: 52000 | L70: MINISTÉRIO DA DEFESA | M70: 52131 | N70: COMANDO DA MARINHA | O70: 05.152.6112.219D.0001 | P70: DEFESA NACIONAL | Q70: DEFESA NAVAL | R70: DEFESA NACIONAL | S70: ADEQUAÇÃO DE ATIVOS DE INFRAESTRUTURA DAS ORGANIZAÇÕES MILITARES | T70: NACIONAL | U70: NA | V70: NACIONAL | W70: F | X70: 3 | Y70: 90 | Z70: 0 | AA70: 6 | AB70: 1000 | AC70: 200000 | AD70: CENTRO DE INSTRUÇÃO ALMIRANTE MILCÍADES PORTELA ALVES - CIAMPA_x000D_ CNPJ: 00.394.502/0077-42_x000D_ _x000D_ NO ANO DE 2024 O CENTRO DE INSTRUÇÃO ALMIRANTE MILCÍADES PORTELA ALVES (CIAMPA) RECEBEU AS PRIMEIRAS 120 MULHERES PARA O CURSO DE FORMAÇÃO DE SOLDADOS FUZILEIROS NAVAIS. ASSIM, FORAM IDENTIFICADAS NECESSIDADES DE AMPLIAÇÃO DE INSTALAÇÕES, PARA MELHOR RECEBER ESSAS ALUNAS. _x000D_ A PRESENTE EMENDA VISA A AMPLIAÇÃO DA ENFERMARIA FEMININA DO CIAMPA, AUMENTANDO O NÚMERO DE LEITOS E DE CONSULTÓRIOS. VALE DESTACAR QUE OS JOVENS DO PROGRAMA FORÇA NO ESPORTE (PROFESP) TAMBÉM UTILIZARÃO AS NOVAS INSTALAÇÕES.
A71: 13 | B71: DEFESA | C71: 32990004 | D71: INDIVIDUAL | E71: INCLUSÃO - APROPRIAÇÃO | F71: 3299 | G71: MENDONÇA FILHO | H71: DEPUTADO FEDERAL | I71: PE | J71: UNIÃO | K71: 52000 | L71: MINISTÉRIO DA DEFESA | M71: 52121 | N71: COMANDO DO EXÉRCITO | O71: 05.122.0032.2000.0026 | P71: DEFESA NACIONAL | Q71: ADMINISTRAÇÃO GERAL | R71: PROGRAMA DE GESTÃO E MANUTENÇÃO DO PODER EXECUTIVO | S71: ADMINISTRAÇÃO DA UNIDADE | T71: NO ESTADO DE PERNAMBUCO | U71: PE | V71: PERNAMBUCO | W71: F | X71: 3 | Y71: 90 | Z71: 0 | AA71: 6 | AB71: 1000 | AC71: 200000 | AD71: A REFERIDA EMENDA TEM COMO FINALIDADE DESTINAR RECURSOS PARA ADEQUAÇÃO DAS INSTALAÇÕES DO COMANDO MILITAR DO NORDESTE. | AE71: Cmdo CMNE | AF71: Adequação das instalações
A72: 13 | B72: DEFESA | C72: 32990004 | D72: INDIVIDUAL | E72: INCLUSÃO - APROPRIAÇÃO | F72: 3299 | G72: MENDONÇA FILHO | H72: DEPUTADO FEDERAL | I72: PE | J72: UNIÃO | K72: 52000 | L72: MINISTÉRIO DA DEFESA | M72: 52121 | N72: COMANDO DO EXÉRCITO | O72: 05.122.0032.2000.0026 | P72: DEFESA NACIONAL | Q72: ADMINISTRAÇÃO GERAL | R72: PROGRAMA DE GESTÃO E MANUTENÇÃO DO PODER EXECUTIVO | S72: ADMINISTRAÇÃO DA UNIDADE | T72: NO ESTADO DE PERNAMBUCO | U72: PE | V72: PERNAMBUCO | W72: F | X72: 4 | Y72: 90 | Z72: 0 | AA72: 6 | AB72: 1000 | AC72: 50000 | AD72: A REFERIDA EMENDA TEM COMO FINALIDADE DESTINAR RECURSOS PARA ADEQUAÇÃO DAS INSTALAÇÕES DO COMANDO MILITAR DO NORDESTE. | AE72: Cmdo CMNE | AF72: Adequação das instalações
A73: 13 | B73: DEFESA | C73: 33120004 | D73: INDIVIDUAL | E73: INCLUSÃO - APROPRIAÇÃO | F73: 3312 | G73: HELDER SALOMÃO | H73: DEPUTADO FEDERAL | I73: ES | J73: PT | K73: 52000 | L73: MINISTÉRIO DA DEFESA | M73: 52931 | N73: FUNDO NAVAL | O73: 05.125.6112.21BY.0001 | P73: DEFESA NACIONAL | Q73: NORMATIZAÇÃO E FISCALIZAÇÃO | R73: DEFESA NACIONAL | S73: FISCALIZAÇÃO DA NAVEGAÇÃO AQUAVIÁRIA | T73: NACIONAL | U73: NA | V73: NACIONAL | W73: F | X73: 4 | Y73: 90 | Z73: 0 | AA73: 6 | AB73: 1000 | AC73: 200000 | AD73: ESTA EMENDA BUSCA VISA APOIAR O INCREMENTO NAS ATIVIDADES DE FISCALIZAÇÃO QUE A CAPITANIA DOS PORTOS REALIZA NO ESTADO DO ESPÍRITO SANTO, OFERECER MAIS SEGURANÇA À POPULAÇÃO CAPIXABA E AUXILIAR NA PREVENÇÃO DA POLUIÇÃO AMBIENTAL POR PARTE DAS EMBARCAÇÕES.
A74: 13 | B74: DEFESA | C74: 35300016 | D74: INDIVIDUAL | E74: ACRÉSCIMO - APROPRIAÇÃO | F74: 3530 | G74: DAMIÃO FELICIANO | H74: DEPUTADO FEDERAL | I74: PB | J74: UNIÃO | K74: 52000 | L74: MINISTÉRIO DA DEFESA | M74: 52931 | N74: FUNDO NAVAL | O74: 05.125.6112.21BY.0001 | P74: DEFESA NACIONAL | Q74: NORMATIZAÇÃO E FISCALIZAÇÃO | R74: DEFESA NACIONAL | S74: FISCALIZAÇÃO DA NAVEGAÇÃO AQUAVIÁRIA | T74: NACIONAL | U74: NA | V74: NACIONAL | W74: F | X74: 3 | Y74: 90 | Z74: 0 | AA74: 6 | AB74: 1000 | AC74: 200000 | AD74: CAPITANIA DOS PORTOS DA PARAÍBA - CPPB_x000D_ CNPJ: 00.394.502/0037-55_x000D_ _x000D_ A CAPITANIA DOS PORTOS DA PARAÍBA É RESPONSÁVEL POR FAZER CUMPRIR AS LEGISLAÇÕES NACIONAIS E INTERNACIONAIS QUE REGULAM O TRÁFEGO MARÍTIMO, FLUVIAL E LACUSTRE, NO QUE TANGE À SALVAGUARDA DA VIDA HUMANA NO MAR, À SEGURANÇA DA NAVEGAÇÃO E A PREVENÇÃO DA POLUIÇÃO HÍDRICA PROVOCADA POR EMBARCAÇÕES NO MAR ABERTO E NAS ÁREAS INTERIORES. DESSA FORMA, A PRESENTE PROPOSTA DE EMENDA PARLAMENTAR GARANTIRÁ AS MANUTENÇÕES DOS MEIOS E INSTALAÇÕES, A FIM DE ASSEGURAR O DESEMPENHO NAS ATIVIDADES DE FISCALIZAÇÃO AO LONGO DOS 138KM DE LITORAL E 134 BARRAGENS E AÇÚDES DO INTERIOR DO ESTADO, BEM COMO AMPLIAR A CAPACIDADE DE LEVAR O ENSINO PROFISSIONAL MARÍTIMO ÀS CERCA DE 78 COLÔNIAS DE PESCA EXISTENTES NA PARAÍBA.
A75: 13 | B75: DEFESA | C75: 35390010 | D75: INDIVIDUAL | E75: ACRÉSCIMO - APROPRIAÇÃO | F75: 3539 | G75: LUCIANO BIVAR | H75: DEPUTADO FEDERAL | I75: PE | J75: UNIÃO | K75: 52000 | L75: MINISTÉRIO DA DEFESA | M75: 52931 | N75: FUNDO NAVAL | O75: 05.125.6112.21BY.0001 | P75: DEFESA NACIONAL | Q75: NORMATIZAÇÃO E FISCALIZAÇÃO | R75: DEFESA NACIONAL | S75: FISCALIZAÇÃO DA NAVEGAÇÃO AQUAVIÁRIA | T75: NACIONAL | U75: NA | V75: NACIONAL | W75: F | X75: 3 | Y75: 90 | Z75: 0 | AA75: 6 | AB75: 1000 | AC75: 250000 | AD75: CAPITANIA DOS PORTOS DE PERNAMBUCO - CPPE_x000D_ CNPJ: 00.394.502/0038-36_x000D_ _x000D_ INCREMENTO DA MANUTENÇÃO PREVENTIVA E CORRETIVA DAS EMBARCAÇÕES EMPREGADAS NAS ATIVIDADES DE FISCALIZAÇÃO DO TRÁFEGO AQUAVIÁRIO, NO APOIO A OUTRAS AGÊNCIAS DO GOVERNO MUNICIPAL, ESTADUAL E FEDERAL AFETAS A SEGURANÇA MARÍTIMA, DEFESA CIVIL E GARANTIA DA LEI E DA ORDEM.
A76: 13 | B76: DEFESA | C76: 35390011 | D76: INDIVIDUAL | E76: ACRÉSCIMO - APROPRIAÇÃO | F76: 3539 | G76: LUCIANO BIVAR | H76: DEPUTADO FEDERAL | I76: PE | J76: UNIÃO | K76: 52000 | L76: MINISTÉRIO DA DEFESA | M76: 52931 | N76: FUNDO NAVAL | O76: 05.125.6112.21BY.0001 | P76: DEFESA NACIONAL | Q76: NORMATIZAÇÃO E FISCALIZAÇÃO | R76: DEFESA NACIONAL | S76: FISCALIZAÇÃO DA NAVEGAÇÃO AQUAVIÁRIA | T76: NACIONAL | U76: NA | V76: NACIONAL | W76: F | X76: 4 | Y76: 90 | Z76: 0 | AA76: 6 | AB76: 1000 | AC76: 250000 | AD76: CAPITANIA DOS PORTOS DE PERNAMBUCO - CPPE_x000D_ CNPJ: 00.394.502/0038-36_x000D_ _x000D_ TRANSPORTAR MILITARES E EMBARCAÇÕES PARA DESEMPENHAR ATIVIDADES DE INSPEÇÃO NAVAL E VISTORIA DE EMBARCAÇÕES DE MODO A INTENSIFICAR ESSAS ATIVIDADES NO LITORAL, RIOS, BARRAGENS E AÇUDES PERNAMBUCANOS.
A77: 13 | B77: DEFESA | C77: 35390012 | D77: INDIVIDUAL | E77: ACRÉSCIMO - APROPRIAÇÃO | F77: 3539 | G77: LUCIANO BIVAR | H77: DEPUTADO FEDERAL | I77: PE | J77: UNIÃO | K77: 52000 | L77: MINISTÉRIO DA DEFESA | M77: 52121 | N77: COMANDO DO EXÉRCITO | O77: 05.122.0032.2000.0001 | P77: DEFESA NACIONAL | Q77: ADMINISTRAÇÃO GERAL | R77: PROGRAMA DE GESTÃO E MANUTENÇÃO DO PODER EXECUTIVO | S77: ADMINISTRAÇÃO DA UNIDADE | T77: NACIONAL | U77: NA | V77: NACIONAL | W77: F | X77: 4 | Y77: 90 | Z77: 0 | AA77: 6 | AB77: 1000 | AC77: 500000 | AD77: BENEFICIÁRIO PARA LANÇAMENTO NO SIOP - CNPJ: 00.394.452/0001-03_x000D_ ADEQUAR AS ESTRUTURAS DO AUDITÓRIO DO COMANDO MILITAR DO NORDESTE, EM RECIFE/PE, COM SISTEMA DE ÁUDIO E VÍDEO MODERNO, ALÉM DE ATENDER A DEMANDA DAS PESSOAS PORTADORAS DE NECESSIDADES ESPECIAIS COM MELHOR ACESSIBILIDADE. | AE77: Cmdo CMNE | AF77: Adequar as estruturas das estruturas do auditório e aquisição de mobiliário e equipamentos para o CCOp
A78: 13 | B78: DEFESA | C78: 35390013 | D78: INDIVIDUAL | E78: ACRÉSCIMO - APROPRIAÇÃO | F78: 3539 | G78: LUCIANO BIVAR | H78: DEPUTADO FEDERAL | I78: PE | J78: UNIÃO | K78: 52000 | L78: MINISTÉRIO DA DEFESA | M78: 52121 | N78: COMANDO DO EXÉRCITO | O78: 05.153.6112.219D.0001 | P78: DEFESA NACIONAL | Q78: DEFESA TERRESTRE | R78: DEFESA NACIONAL | S78: ADEQUAÇÃO DE ATIVOS DE INFRAESTRUTURA DAS ORGANIZAÇÕES MILITARES | T78: NACIONAL | U78: NA | V78: NACIONAL | W78: F | X78: 3 | Y78: 90 | Z78: 0 | AA78: 6 | AB78: 1000 | AC78: 200000 | AD78: BENEFICIÁRIO PARA LANÇAMENTO NO SIOP - CNPJ: 00.394.452/0001-03_x000D_ PROPORCIONAR MAIOR SEGURANÇA E MELHORES CONDIÇÕES AOS MILITARES PARA UTILIZAÇÃO DA QUADRA ESPORTIVA DO 3º CENTRO DE GEOINFORMAÇÃO, EM OLINDA/PE. | AE78: 3º CGEO | AF78: Adequação da quadra poliesportiva
A79: 13 | B79: DEFESA | C79: 35390014 | D79: INDIVIDUAL | E79: ACRÉSCIMO - APROPRIAÇÃO | F79: 3539 | G79: LUCIANO BIVAR | H79: DEPUTADO FEDERAL | I79: PE | J79: UNIÃO | K79: 52000 | L79: MINISTÉRIO DA DEFESA | M79: 52121 | N79: COMANDO DO EXÉRCITO | O79: 05.153.6112.21A0.0001 | P79: DEFESA NACIONAL | Q79: DEFESA TERRESTRE | R79: DEFESA NACIONAL | S79: APRESTAMENTO DAS FORÇAS - MANUTENÇÃO DA PRONTIDÃO E DA CAPACIDADE OPERATIVA | T79: NACIONAL | U79: NA | V79: NACIONAL | W79: F | X79: 4 | Y79: 90 | Z79: 0 | AA79: 6 | AB79: 1000 | AC79: 200000 | AD79: BENEFICIÁRIO PARA LANÇAMENTO NO SIOP - CNPJ: 00.394.452/0001-03_x000D_ A AQUISIÇÃO JUSTIFICA-SE PELA NECESSIDADE DE VIATURA SIMPLES PARA REALIZAR O TRANSPORTE DAS EQUIPES E DOS MATERIAIS DO SERVIÇO DE ASSISTÊNCIA DOMICILIAR E DAS EQUIPES DE AUDITORIA EXTERNA DO HOSPITAL MILITAR DE ÁREA DE RECIFE/PE, NOS DESLOCAMENTOS DIÁRIOS. | AE79: HMAR | AF79: Aquisição de Vtr Adm
A80: 13 | B80: DEFESA | C80: 35390015 | D80: INDIVIDUAL | E80: INCLUSÃO - APROPRIAÇÃO | F80: 3539 | G80: LUCIANO BIVAR | H80: DEPUTADO FEDERAL | I80: PE | J80: UNIÃO | K80: 52000 | L80: MINISTÉRIO DA DEFESA | M80: 52111 | N80: COMANDO DA AERONÁUTICA | O80: 05.301.0032.2E74.0026 | P80: DEFESA NACIONAL | Q80: ATENÇÃO BÁSICA | R80: PROGRAMA DE GESTÃO E MANUTENÇÃO DO PODER EXECUTIVO | S80: ESTRUTURAÇÃO E MODERNIZAÇÃO DE UNIDADES DE SAÚDE DAS FORÇAS ARMADAS | T80: NO ESTADO DE PERNAMBUCO | U80: PE | V80: PERNAMBUCO | W80: S | X80: 4 | Y80: 90 | Z80: 0 | AA80: 6 | AB80: 1000 | AC80: 200000 | AD80: CNPJ PARA LANÇAMENTO NO SIOP: 00.394.429/0001-00 - COMANDO DA AERONÁUTICA UNIDADE BENEFICIADA: HOSPITAL DE AERONÁUTICA DE RECIFE. OBJETO RESUMIDO: AQUISIÇÃO DE EQUIPAMENTOS MÉDICO-HOSPITALARES.
A81: 13 | B81: DEFESA | C81: 35970004 | D81: INDIVIDUAL | E81: INCLUSÃO - APROPRIAÇÃO | F81: 3597 | G81: ALBERTO MOURÃO | H81: DEPUTADO FEDERAL | I81: SP | J81: MDB | K81: 52000 | L81: MINISTÉRIO DA DEFESA | M81: 52131 | N81: COMANDO DA MARINHA | O81: 05.152.6112.219D.3908 | P81: DEFESA NACIONAL | Q81: DEFESA NAVAL | R81: DEFESA NACIONAL | S81: ADEQUAÇÃO DE ATIVOS DE INFRAESTRUTURA DAS ORGANIZAÇÕES MILITARES | T81: NO MUNICÍPIO DE SANTOS - SP | U81: SP | V81: SANTOS | W81: F | X81: 3 | Y81: 90 | Z81: 0 | AA81: 6 | AB81: 1000 | AC81: 190000 | AD81: COM A APROVAÇÃO DESSA EMENDA, VISAMOS OTIMIZAR A GESTÃO DE ENERGIA DESTA CAPITANIA, COM A INSTALAÇÃO DE SISTEMA DE GERAÇÃO DE ENERGIA SOLAR E COM O PROPÓSITO DE ATENDER AOS PARÂMETROS DO PROGRAMA ENERGIA NAVAL, POSSIBILITANDO A ADESÃO AO CONTEXTO DE ENERGIA LIMPA EM PROL DA SUSTENTABILIDADE AMBIENTAL._x000D_ A CAPITANIA DOS PORTOS DE SÃO PAULO (CPSP), EXERCE O PAPEL DE AGENTE DA AUTORIDADE MARÍTIMA, QUE CONTRIBUI DENTRE OUTRAS FINALIDADES, PARA SEGURANÇA DA NAVEGAÇÃO, SALVAGUARDA DA VIDA HUMANA E PREVENÇÃO DA POLUIÇÃO HÍDRICA EM SUA JURISDIÇÃO, CUJA ÁREA COMPREENDE 151MUNICÍPIOS._x000D_ ATUAMOS DIRETAMENTE NO ENSINO PROFISSIONAL MARÍTIMO DE AQUAVIÁRIOS E PORTUÁRIOS, DE FORMA A PROFISSIONALIZAR E ORIENTAR A COMUNIDADE MARÍTIMA. ALÉM DISSO, SÃO PROCESSADOS UMA MÉDIA DE 3.000 (TRÊS MIL) PROCESSOS/MÊS EM ATENÇÃO AOS CIDADÃOS DA NOSSA ÁREA DE JURISDIÇÃO,_x000D_ ATENDENDO A DEMANDA DE HABILITAÇÃO DE AMADOR E CADASTRO DE EMBARCAÇÕES._x000D_ ADICIONALMENTE SÃO REALIZADAS AÇÕES DE FISCALIZAÇÃO DO TRÁFEGO AQUAVIÁRIOS E DE BUSCAS E SALVAMENTO, CONTRIBUINDO PARA A SEGURANÇA DA NAVEGAÇÃO, SALVAGUARDA DA VIDA HUMANA NO MAR E PREVENÇÃO DA POLUIÇÃO HÍDRICA.
A82: 13 | B82: DEFESA | C82: 35970005 | D82: INDIVIDUAL | E82: INCLUSÃO - APROPRIAÇÃO | F82: 3597 | G82: ALBERTO MOURÃO | H82: DEPUTADO FEDERAL | I82: SP | J82: MDB | K82: 52000 | L82: MINISTÉRIO DA DEFESA | M82: 52931 | N82: FUNDO NAVAL | O82: 05.125.6112.21BY.3908 | P82: DEFESA NACIONAL | Q82: NORMATIZAÇÃO E FISCALIZAÇÃO | R82: DEFESA NACIONAL | S82: FISCALIZAÇÃO DA NAVEGAÇÃO AQUAVIÁRIA | T82: NO MUNICÍPIO DE SANTOS - SP | U82: SP | V82: SANTOS | W82: F | X82: 4 | Y82: 90 | Z82: 0 | AA82: 6 | AB82: 1000 | AC82: 410000 | AD82: COM A CONCRETIZAÇÃO DESSA EMENDA, VISAMOS DOTAR A CAPITANIA DOS PORTOS DE SÃO PAULO (CPSP) DOS MEIOS NECESSÁRIOS À CONDUÇÃO DE SUAS ATIVIDADES EM PROVEITO DA SOCIEDADE, PERMITINDO O DESLOCAMENTO DE SEUS MEIOS E PESSOAL PARA ATENDIMENTO DAS DEMANDAS DA POPULAÇÃO, EM ESPECIAL AQUELAS RELACIONADAS A BUSCAS E SOCORRO NAS ORLAS, PRAIAS, HIDROVIAS E REPRESAS DO INTERIOR, CONTRIBUINDO PARA EVITAR ACIDENTES DE NATUREZA PESSOAL, MATERIAL E AMBIENTAL._x000D_ A CPSP EXERCE O PAPEL DE AGENTE DA AUTORIDADE MARÍTIMA, CUJA ÁREA DE JURISDIÇÃO COMPREENDE 151 MUNICÍPIOS. ATUAMOS DIRETAMENTE NO ENSINO PROFISSIONAL MARÍTIMO DE AQUAVIÁRIOS E PORTUÁRIOS, DE FORMA A PROFISSIONALIZAR E ORIENTAR A COMUNIDADE MARÍTIMA. _x000D_ ALÉM DISSO, SÃO PROCESSADOS UMA MÉDIA DE 3.000 (TRÊS MIL) PROCESSOS/MÊS EM ATENÇÃO AOS CIDADÃOS DA NOSSA ÁREA DE JURISDIÇÃO, ATENDENDO A DEMANDA DE HABILITAÇÃO DE AMADOR E CADASTRO DE EMBARCAÇÕES. ADICIONALMENTE SÃO REALIZADAS AÇÕES DE FISCALIZAÇÃO DO TRÁFEGO AQUAVIÁRIOS E DE BUSCAS E SALVAMENTO, CONTRIBUINDO PARA A SEGURANÇA DA NAVEGAÇÃO, SALVAGUARDA DA VIDA HUMANA NO MAR E PREVENÇÃO DA POLUIÇÃO HÍDRICA.
A83: 13 | B83: DEFESA | C83: 36300003 | D83: INDIVIDUAL | E83: ACRÉSCIMO - APROPRIAÇÃO | F83: 3630 | G83: ALBERTO FRAGA | H83: DEPUTADO FEDERAL | I83: DF | J83: PL | K83: 52000 | L83: MINISTÉRIO DA DEFESA | M83: 52121 | N83: COMANDO DO EXÉRCITO | O83: 05.153.6112.219D.0001 | P83: DEFESA NACIONAL | Q83: DEFESA TERRESTRE | R83: DEFESA NACIONAL | S83: ADEQUAÇÃO DE ATIVOS DE INFRAESTRUTURA DAS ORGANIZAÇÕES MILITARES | T83: NACIONAL | U83: NA | V83: NACIONAL | W83: F | X83: 3 | Y83: 90 | Z83: 0 | AA83: 6 | AB83: 1000 | AC83: 205000 | AD83: BENEFICIÁRIO PARA LANÇAMENTO NO SIOP - CNPJ: 00.394.452/0001-03_x000D_ MELHORAR A ACESSIBILIDADE DO AUDITÓRIO DA 11ª REGIÃO MILITAR, EM BRASÍLIA/DF, PROPORCIONANDO MAIS SEGURANÇA PARA TODOS OS VISITANTES, BEM COMO CRIAR UM AMBIENTE MAIS ADEQUADO PARA ACOMODAR EVENTOS DE GRANDE ESCALA. | AE83: Cmdo 11ª RM | AF83: Adequação das instalações da Comissão de Seleção Permanente das Forças Armadas do Cmdo da 11ª RM.
A84: 13 | B84: DEFESA | C84: 36300004 | D84: INDIVIDUAL | E84: ACRÉSCIMO - APROPRIAÇÃO | F84: 3630 | G84: ALBERTO FRAGA | H84: DEPUTADO FEDERAL | I84: DF | J84: PL | K84: 52000 | L84: MINISTÉRIO DA DEFESA | M84: 52931 | N84: FUNDO NAVAL | O84: 05.122.0032.2000.0001 | P84: DEFESA NACIONAL | Q84: ADMINISTRAÇÃO GERAL | R84: PROGRAMA DE GESTÃO E MANUTENÇÃO DO PODER EXECUTIVO | S84: ADMINISTRAÇÃO DA UNIDADE | T84: NACIONAL | U84: NA | V84: NACIONAL | W84: F | X84: 4 | Y84: 90 | Z84: 0 | AA84: 6 | AB84: 1000 | AC84: 1000000 | AD84: CAPITANIA FLUVIAL DE BRASILIA - CFB_x000D_ CNPJ: 03.811.661/0001-95_x000D_ _x000D_ ATUALMENTE A SEDE DA CAPITANIA FICA NO PRÉDIO DO 7º DISTRITO, ANEXO DA MARINHA. CONTUDO, PARA DAR MAIOR CELERIDADE AS AÇÕES NO LAGO PARANOÁ SERÁ CONSTRUÍDA UM NOVO PRÉDIO EM LOCAL IDEAL A OCUPAÇÃO PERTENCENTE A CAPITANIA ÀS MARGENS DO LAGO, SENDO NECESSÁRIA MOBILIAR O NOVO PRÉDIO PARA GARANTIR O PLENO FUNCIONAMENTO DE TODOS OS SERVIÇOS.
